Workbook

Sheet JHora
A1: ='[1]Selected Chart'!$A$2 -> Chart | B1: ='[1]Selected Chart'!B2 -> Date | C1: ='[1]Selected Chart'!C2 -> Event
A2: C:\Users\sprabhakara2\Google Drive\charts\Family&Self\Sanjay Prabhakaran | B2: 26133 | C2: Born in CIM Stores
B3: 36723 | C3: Joined SJC/SJVC
A4: Natal Chart | B4: 37926 | C4: Bought Car D16 | AF4: 0
B5: 38779 | C5: Marriage D9 | AF5: 0
A6: Date: July 19, 1971 | B6: 41694 | C6: Bought Car D16 | AF6: 0
A7: Time: 9:13:10 | AF7: 0
A8: Time Zone: 5:30:00 (East of GMT) | AF8: 0
A9: Place: 78 E 05' 05", 10 N 57' 47" | AF9: 0
A10: Karur CIM Store, India | AF10: 0
A11: Altitude: 123.00 meters | AF11: 0
AF12: 0
A13: Lunar Yr-Mo: Virodha-krit - Ashadha | AF13: 0
A14: Tithi: Krishna Dwadasi (Me) (28.19% left) | AF14: 0
A15: Vedic Weekday: Monday (Mo) | AF15: 0
A16: Nakshatra: Rohini (Mo) (2.38% left) | AF16: 0
A17: Yoga: Vriddhi (Me) (9.39% left) | AF17: 0
A18: Karana: Taitula (Me) (56.39% left) | AF18: 0
A19: Hora Lord: Mars (5 min sign: Sg) | AF19: 0
A20: Mahakala Hora: Jupiter (5 min sign: Aq) | AF20: 0
A21: Kaala Lord: Rahu (Mahakala: Rahu) | AF21: 0
AF22: 0
A23: Sunrise: 6:03:17 | AF23: 0
A24: Sunset: 18:44:17 | AF24: 0
A25: Janma Ghatis: 7.9117 | AF25: 0
AF26: 0
A27: Ayanamsa: 23-26-39.19 | AF27: 0
A28: Sidereal Time: 4:40:40 | AF28: 0
AF29: 0
A30: Body Longitude Nakshatra Pada Rasi Navamsa | AF30: 0
AF31: 0
A32: Lagna 16 Le 42' 41.46" PPha 2 Le Vi | AF32: 0
A33: Sun - DK 2 Cn 23' 57.13" Puna 4 Cn Cn | AF33: 0
A34: Moon - BK 23 Ta 00' 57.40" Rohi 4 Ta Cn | AF34: 0
A35: Mars (R) - AK 28 Cp 06' 31.19" Dhan 2 Cp Vi | AF35: 0
A36: Mercury - AmK 27 Cn 07' 47.23" Asre 4 Cn Pi | AF36: 0
A37: Jupiter (R) - GK 3 Sc 11' 49.83" Visa 4 Sc Cn | AF37: 0
A38: Venus - MK 21 Ge 32' 26.17" Puna 1 Ge Ar | AF38: 0
A39: Saturn - PiK 9 Ta 53' 06.76" Krit 4 Ta Pi | AF39: 0
A40: Rahu - PK 21 Cp 58' 02.06" Srav 4 Cp Cn | AF40: 0
A41: Ketu 21 Cn 58' 02.06" Asre 2 Cn Cp | AF41: 0
A42: Maandi 8 Sc 13' 55.81" Anu 2 Sc Vi | AF42: 0
A43: Gulika 19 Sc 06' 14.77" Jye 1 Sc Sg | AF43: 0
... A77: YogaSaham 28 Sc 44' 54.53" Jye 4 Sc Pi | AF77: 0
A78: ='[1]Selected Chart'!A79 -> 0 | B78: ='[1]Selected Chart'!B79 -> 0 | C78: ='[1]Selected Chart'!C79 -> 0 | AF78: 0
A79: ='[1]Selected Chart'!A80 -> 0 | B79: ='[1]Selected Chart'!B80 -> 0 | C79: ='[1]Selected Chart'!C80 -> 0 | AF79: 0
A80: ='[1]Selected Chart'!A81 -> 0 | B80: ='[1]Selected Chart'!B81 -> 0 | C80: ='[1]Selected Chart'!C81 -> 0 | AF80: 0
A81: ='[1]Selected Chart'!A82 -> 0 | B81: ='[1]Selected Chart'!B82 -> 0 | C81: ='[1]Selected Chart'!C82 -> 0 | AF81: 0
A82: ='[1]Selected Chart'!A83 -> 0 | B82: ='[1]Selected Chart'!B83 -> 0 | C82: ='[1]Selected Chart'!C83 -> 0 | AF82: 0
A83: ='[1]Selected Chart'!A84 -> 0 | B83: ='[1]Selected Chart'!B84 -> 0 | C83: ='[1]Selected Chart'!C84 -> 0 | AF83: 0
A84: ='[1]Selected Chart'!A85 -> 0 | B84: ='[1]Selected Chart'!B85 -> 0 | C84: ='[1]Selected Chart'!C85 -> 0 | AF84: 0
A85: ='[1]Selected Chart'!A86 -> 0 | B85: ='[1]Selected Chart'!B86 -> 0 | C85: ='[1]Selected Chart'!C86 -> 0 | AF85: 0
A86: ='[1]Selected Chart'!A87 -> 0 | B86: ='[1]Selected Chart'!B87 -> 0 | C86: ='[1]Selected Chart'!C87 -> 0 | AF86: 0
A87: ='[1]Selected Chart'!A88 -> 0 | B87: ='[1]Selected Chart'!B88 -> 0 | C87: ='[1]Selected Chart'!C88 -> 0 | AF87: 0
A88: ='[1]Selected Chart'!A89 -> 0 | B88: ='[1]Selected Chart'!B89 -> 0 | C88: ='[1]Selected Chart'!C89 -> 0 | AF88: 0
A89: ='[1]Selected Chart'!A90 -> 0 | B89: ='[1]Selected Chart'!B90 -> 0 | C89: ='[1]Selected Chart'!C90 -> 0 | AF89: 0
... A108: ='[1]Selected Chart'!A109 -> 0 | B108: ='[1]Selected Chart'!B109 -> 0 | C108: ='[1]Selected Chart'!C109 -> 0 | AF108: 0
A109: ='[1]Selected Chart'!A110 -> 0 | B109: ='[1]Selected Chart'!B110 -> 0 | C109: ='[1]Selected Chart'!C110 -> 0 | D109: 0 | E109: 0 | F109: 0 | G109: 0 | H109: 0 | I109: 0 | J109: 0 | K109: 0 | L109: 0 | M109: 0 | N109: 0 | O109: 0 | P109: 0 | Q109: 0 | R109: 0 | S109: 0 | T109: 0 | U109: 0 | V109: 0 | W109: 0 | X109: 0 | Y109: 0 | Z109: 0 | AA109: 0 | AB109: 0 | AC109: 0 | AD109: 0 | AE109: 0 | AF109: 0

Sheet Basics
A1: =JHora!A2 -> C:\Users\sprabhakara2\Google Drive\charts\Family&Self\Sanjay Prabhakaran
A2: Date Of Birth | B2: =LEFT(TRIM(MID(JHora!A6,6,100)),FIND(" ",TRIM(MID(JHora!A6,6,100)))) -> July | C2: =REPLACE(RIGHT(TRIM(MID(JHora!A6,6,100)),8),3,1,B2) -> 19July 1971 | E2: =VALUE(C2)+VALUE(RIGHT(JHora!A7,12)) -> 26133.384 | G2: =INT(DoB) -> 26133 | H2: =DoB-INT(DoB) -> 0.38414352 | J2: =ROUNDUP((MINUTE(DoB-B44)+HOUR(DoB-B44)*60)/24,0) -> 8 | K2: =HOUR(DoB-B44)*60 -> 180 | P2: {=SUM(L7:L14)} -> -38
A3: Days In Year | B3: 365.25487 | G3: Days | J3: =TIME(0,24,0) -> 0.016666667
A4: Yellow Cells are Input Cells
A5: After you do Edit;Copy Basic Calculations in Jhora. Goto the JHora Sheet and Paste in 1st row 1st col | W5: 1 | X5: 2 | Y5: 3 | Z5: 4 | AA5: 5
G6: Sphuta Deg | H6: Bhavan Deg | I6: Nakhshatra Ruler | J6: Avastha | K6: Retrograde | L6: Graha Tithi | M6: Tithi Lord | N6: D20Deity | O6: D20Deity | P6: D27Deity | Q6: D27Deity | R6: D27 Position | S6: D150Division | T6: D150Index | U6: D150Names | V6: Avastha | W6: AvashtaInt1 | X6: AvashtaInt2 | Y6: AvashtaInt3 | Z6: AvashtaInt4 | AA6: AvashtaInt5 | AB6: GrahaOrder | AC6: MyValue
A7: =TRIM(LEFT(JHora!A32,FIND(" ",JHora!A32))) -> Lagna | B7: =MID(JHora!A32,FIND("'",JHora!A32)-8,2) -> 16 | C7: =MID(JHora!A32,FIND("'",JHora!A32)-5,2) -> Le | D7: =MID(JHora!A32,FIND("'",JHora!A32)-2,2)+VALUE(MID(JHora!A32,FIND("'",JHora!A32)+2,5))/60 -> 42.691 | E7: =INDEX(NakshatraTbl,INT(G7*0.075)+1,1) -> Purva Phalguni | F7: - | G7: =VLOOKUP(C7,RasiDeg,2,0)+B7+D7/60 -> 136.71152 | H7: =B7+D7/60 -> 16.711517 | I7: =INDEX(NakshatraTbl,INT(G7*0.075)+1,3) -> Venus | K7: =NOT(ISERROR(SEARCH("(R)",JHora!A32))) -> 0 | L7: =ROUNDUP(IF((Moon-G7)<0,-1*(180+(Moon-G7)),Moon-G7)/12,0) -> -9 | N7: =INDEX(D20Deities,ROUNDUP(H7/1.5,0)+MOD(ROUNDUP(G7/30,0)-1,2)*20,1) -> bagalāmukhī | O7: =INDEX(D20Deities,ROUNDUP(H7/1.5,0)+MOD(ROUNDUP(G7/30,0)-1,2)*20,2) -> बगलामुखी | P7: =INDEX(D27Deities,ROUNDUP(H7/30*27,0),1) -> śakrāgni | Q7: =INDEX(D27Deities,ROUNDUP(H7/30*27,0),2) -> शक्राग्नि | R7: =INT(H7/900*360)&" s"&" "&TEXT(MOD(H7/30*360,30)/24,"[HH]:MM:ss") -> 6 s 20:32:18 | S7: =MATCH(H7,D150InequalDegrees) -> 84 | T7: =CHOOSE(ROUNDUP(MOD(G7/30,3),0),S7,150-S7+1,MOD(74+S7,150)+1) -> 67 | U7: =INDEX(D150EnglishNames,T7) -> gadaharā | AB7: 0
A8: =TRIM(LEFT(JHora!A33,FIND(" ",JHora!A33))) -> Sun | B8: =MID(JHora!A33,FIND("'",JHora!A33)-8,2) -> 2 | C8: =MID(JHora!A33,FIND("'",JHora!A33)-5,2) -> Cn | D8: =MID(JHora!A33,FIND("'",JHora!A33)-2,2)+VALUE(MID(JHora!A33,FIND("'",JHora!A33)+2,5))/60 -> 23.952167 | E8: =INDEX(NakshatraTbl,INT(G8*0.075)+1,1) -> Punarvasu | F8: =CHOOSE(RANK(H8,H$8:H$15),"Ak","Amk","Bk","Mk","PiK","PuK","Gk","Dk") -> Dk | G8: =VLOOKUP(C8,RasiDeg,2,0)+B8+D8/60 -> 92.399203 | H8: =B8+D8/60 -> 2.3992028 | I8: =INDEX(NakshatraTbl,INT(G8*0.075)+1,3) -> Jupiter | J8: =MOD(ROUNDUP(G8/13.3333333333,0)*1*ROUNDUP(MOD(G8,30)/3.33333,0)+ROUNDUP(Moon/13.333,0)+ROUNDUP(JanmaGhatika,0)+ROUNDUP(Lagna/30,0)+11,12)+1 -> 12 | K8: =NOT(ISERROR(SEARCH("(R)",JHora!A33))) -> 0 | L8: =ROUNDUP(IF((Moon-G8)<0,-1*(180+(Moon-G8)),Moon-G8)/12,0) -> -12 | M8: =INDEX(Tithi,MOD(ABS(L8),8)) -> Mercury | N8: =INDEX(D20Deities,ROUNDUP(H8/1.5,0)+MOD(ROUNDUP(G8/30,0)-1,2)*20,1) -> medhā | O8: =INDEX(D20Deities,ROUNDUP(H8/1.5,0)+MOD(ROUNDUP(G8/30,0)-1,2)*20,2) -> मेधा | P8: =INDEX(D27Deities,ROUNDUP(H8/30*27,0),1) -> vahni | Q8: =INDEX(D27Deities,ROUNDUP(H8/30*27,0),2) -> वह्नि | R8: =INT(H8/900*360)&" s"&" "&TEXT(MOD(H8/30*360,30)/24,"[HH]:MM:ss") -> 0 s 28:47:26 | S8: =MATCH(H8,D150InequalDegrees) -> 13 | T8: =CHOOSE(ROUNDUP(MOD(G8/30,3),0),S8,150-S8+1,MOD(74+S8,150)+1) -> 13 | U8: =INDEX(D150EnglishNames,T8) -> mañjusvanā | V8: =INDEX(ShayanaadiAvastha,J8) -> Nidraa | W8: =MOD(MOD(($J8*$J8+W$5)+11,12)*INDEX(GrahaShayanadiGunanka,$AB8)+2,3)+1 -> 3 | X8: =MOD(MOD(($J8*$J8+X$5)+11,12)*INDEX(GrahaShayanadiGunanka,$AB8)+2,3)+1 -> 2 | Y8: =MOD(MOD(($J8*$J8+Y$5)+11,12)*INDEX(GrahaShayanadiGunanka,$AB8)+2,3)+1 -> 1 | Z8: =MOD(MOD(($J8*$J8+Z$5)+11,12)*INDEX(GrahaShayanadiGunanka,$AB8)+2,3)+1 -> 3 | AA8: =MOD(MOD(($J8*$J8+AA$5)+11,12)*INDEX(GrahaShayanadiGunanka,$AB8)+2,3)+1 -> 2 | AB8: 1 | AC8: 3 | AD8: If Surya is in Sayan Avastha, the native will incur digestive deficiency, many diseases, stoutness of legs, bilious vitiation, ulcer in the anus and heart strokes;
A9: =TRIM(LEFT(JHora!A34,FIND(" ",JHora!A34))) -> Moon | B9: =MID(JHora!A34,FIND("'",JHora!A34)-8,2) -> 23 | C9: =MID(JHora!A34,FIND("'",JHora!A34)-5,2) -> Ta | D9: =MID(JHora!A34,FIND("'",JHora!A34)-2,2)+VALUE(MID(JHora!A34,FIND("'",JHora!A34)+2,5))/60 -> 0.95666667 | E9: =INDEX(NakshatraTbl,INT(G9*0.075)+1,1) -> Rohini | F9: =CHOOSE(RANK(H9,H$8:H$15),"Ak","Amk","Bk","Mk","PiK","PuK","Gk","Dk") -> Bk | G9: =VLOOKUP(C9,RasiDeg,2,0)+B9+D9/60 -> 53.015944 | H9: =B9+D9/60 -> 23.015944 | I9: =INDEX(NakshatraTbl,INT(G9*0.075)+1,3) -> Moon | J9: =MOD(ROUNDUP(G9/13.3333333333,0)*2*ROUNDUP(MOD(G9,30)/3.33333,0)+ROUNDUP(Moon/13.333,0)+ROUNDUP(JanmaGhatika,0)+ROUNDUP(Lagna/30,0)+11,12)+1 -> 1 | K9: =NOT(ISERROR(SEARCH("(R)",JHora!A34))) -> 0 | N9: =INDEX(D20Deities,ROUNDUP(H9/1.5,0)+MOD(ROUNDUP(G9/30,0)-1,2)*20,1) -> sitā | O9: =INDEX(D20Deities,ROUNDUP(H9/1.5,0)+MOD(ROUNDUP(G9/30,0)-1,2)*20,2) -> सिता | P9: =INDEX(D27Deities,ROUNDUP(H9/30*27,0),1) -> viśve aja | Q9: =INDEX(D27Deities,ROUNDUP(H9/30*27,0),2) -> विश्वे अज | R9: =INT(H9/900*360)&" s"&" "&TEXT(MOD(H9/30*360,30)/24,"[HH]:MM:ss") -> 9 s 06:11:29 | S9: =MATCH(H9,D150InequalDegrees) -> 116 | T9: =CHOOSE(ROUNDUP(MOD(G9/30,3),0),S9,150-S9+1,MOD(74+S9,150)+1) -> 35 | U9: =INDEX(D150EnglishNames,T9) -> kṣamā | V9: =INDEX(ShayanaadiAvastha,J9) -> Sayana | W9: =MOD(MOD(($J9*$J9+W$5)+11,12)*INDEX(GrahaShayanadiGunanka,$AB9)+2,3)+1 -> 2 | X9: =MOD(MOD(($J9*$J9+X$5)+11,12)*INDEX(GrahaShayanadiGunanka,$AB9)+2,3)+1 -> 1 | Y9: =MOD(MOD(($J9*$J9+Y$5)+11,12)*INDEX(GrahaShayanadiGunanka,$AB9)+2,3)+1 -> 3 | Z9: =MOD(MOD(($J9*$J9+Z$5)+11,12)*INDEX(GrahaShayanadiGunanka,$AB9)+2,3)+1 -> 2 | AA9: =MOD(MOD(($J9*$J9+AA$5)+11,12)*INDEX(GrahaShayanadiGunanka,$AB9)+2,3)+1 -> 1 | AB9: 2 | AC9: 1 | AD9: if in Upavesan, will be troubled by diseases, be dull-witted, not endowed with mentionable wealth, will be hard-hearted, will do unworthy acts and will steal others’ wealth;
A10: =TRIM(LEFT(JHora!A35,FIND(" ",JHora!A35))) -> Mars | B10: =MID(JHora!A35,FIND("'",JHora!A35)-8,2) -> 28 | C10: =MID(JHora!A35,FIND("'",JHora!A35)-5,2) -> Cp | D10: =MID(JHora!A35,FIND("'",JHora!A35)-2,2)+VALUE(MID(JHora!A35,FIND("'",JHora!A35)+2,5))/60 -> 6.5198333 | E10: =INDEX(NakshatraTbl,INT(G10*0.075)+1,1) -> Shravan | F10: =CHOOSE(RANK(H10,H$8:H$15),"Ak","Amk","Bk","Mk","PiK","PuK","Gk","Dk") -> Ak | G10: =VLOOKUP(C10,RasiDeg,2,0)+B10+D10/60 -> 298.10866 | H10: =B10+D10/60 -> 28.108664 | I10: =INDEX(NakshatraTbl,INT(G10*0.075)+1,3) -> Moon | J10: =MOD(ROUNDUP(G10/13.3333333333,0)*3*ROUNDUP(MOD(G10,30)/3.33333,0)+ROUNDUP(Moon/13.333,0)+ROUNDUP(JanmaGhatika,0)+ROUNDUP(Lagna/30,0)+11,12)+1 -> 2 | K10: =NOT(ISERROR(SEARCH("(R)",JHora!A35))) -> 1 | L10: =ROUNDUP(IF((Moon-G10)<0,-1*(180+(Moon-G10)),Moon-G10)/12,0) -> 6 | M10: =INDEX(Tithi,MOD(ABS(L10),8)) -> Venus | N10: =INDEX(D20Deities,ROUNDUP(H10/1.5,0)+MOD(ROUNDUP(G10/30,0)-1,2)*20,1) -> maṅgalā | O10: =INDEX(D20Deities,ROUNDUP(H10/1.5,0)+MOD(ROUNDUP(G10/30,0)-1,2)*20,2) -> मङ्गला | P10: =INDEX(D27Deities,ROUNDUP(H10/30*27,0),1) -> ahirbudhnya | Q10: =INDEX(D27Deities,ROUNDUP(H10/30*27,0),2) -> अहिर्बुध्न्य | R10: =INT(H10/900*360)&" s"&" "&TEXT(MOD(H10/30*360,30)/24,"[HH]:MM:ss") -> 11 s 07:18:14 | S10: =MATCH(H10,D150InequalDegrees) -> 141 | T10: =CHOOSE(ROUNDUP(MOD(G10/30,3),0),S10,150-S10+1,MOD(74+S10,150)+1) -> 141 | U10: =INDEX(D150EnglishNames,T10) -> kalaśodbhavā | V10: =INDEX(ShayanaadiAvastha,J10) -> Upavesana | W10: =MOD(MOD(($J10*$J10+W$5)+11,12)*INDEX(GrahaShayanadiGunanka,$AB10)+2,3)+1 -> 2 | X10: =MOD(MOD(($J10*$J10+X$5)+11,12)*INDEX(GrahaShayanadiGunanka,$AB10)+2,3)+1 -> 1 | Y10: =MOD(MOD(($J10*$J10+Y$5)+11,12)*INDEX(GrahaShayanadiGunanka,$AB10)+2,3)+1 -> 3 | Z10: =MOD(MOD(($J10*$J10+Z$5)+11,12)*INDEX(GrahaShayanadiGunanka,$AB10)+2,3)+1 -> 2 | AA10: =MOD(MOD(($J10*$J10+AA$5)+11,12)*INDEX(GrahaShayanadiGunanka,$AB10)+2,3)+1 -> 1 | AB10: 3 | AD10: If Mangal is placed in Lagn and happens to be in Netrapani, there will be penury; if placed in other Bhavas, Netrapani will confer rulership of a city.
A11: =TRIM(LEFT(JHora!A36,FIND(" ",JHora!A36))) -> Mercury | B11: =MID(JHora!A36,FIND("'",JHora!A36)-8,2) -> 27 | C11: =MID(JHora!A36,FIND("'",JHora!A36)-5,2) -> Cn | D11: =MID(JHora!A36,FIND("'",JHora!A36)-2,2)+VALUE(MID(JHora!A36,FIND("'",JHora!A36)+2,5))/60 -> 7.7871667 | E11: =INDEX(NakshatraTbl,INT(G11*0.075)+1,1) -> Ashlesha | F11: =CHOOSE(RANK(H11,H$8:H$15),"Ak","Amk","Bk","Mk","PiK","PuK","Gk","Dk") -> Amk | G11: =VLOOKUP(C11,RasiDeg,2,0)+B11+D11/60 -> 117.12979 | H11: =B11+D11/60 -> 27.129786 | I11: =INDEX(NakshatraTbl,INT(G11*0.075)+1,3) -> Merc | J11: =MOD(ROUNDUP(G11/13.3333333333,0)*4*ROUNDUP(MOD(G11,30)/3.33333,0)+ROUNDUP(Moon/13.333,0)+ROUNDUP(JanmaGhatika,0)+ROUNDUP(Lagna/30,0)+11,12)+1 -> 5 | K11: =NOT(ISERROR(SEARCH("(R)",JHora!A36))) -> 0 | L11: =ROUNDUP(IF((Moon-G11)<0,-1*(180+(Moon-G11)),Moon-G11)/12,0) -> -10 | M11: =INDEX(Tithi,MOD(ABS(L11),8)) -> Moon | N11: =INDEX(D20Deities,ROUNDUP(H11/1.5,0)+MOD(ROUNDUP(G11/30,0)-1,2)*20,1) -> maṅgalā | O11: =INDEX(D20Deities,ROUNDUP(H11/1.5,0)+MOD(ROUNDUP(G11/30,0)-1,2)*20,2) -> मङ्गला | P11: =INDEX(D27Deities,ROUNDUP(H11/30*27,0),1) -> ajapād | Q11: =INDEX(D27Deities,ROUNDUP(H11/30*27,0),2) -> अजपाद् | R11: =INT(H11/900*360)&" s"&" "&TEXT(MOD(H11/30*360,30)/24,"[HH]:MM:ss") -> 10 s 25:33:27 | S11: =MATCH(H11,D150InequalDegrees) -> 136 | T11: =CHOOSE(ROUNDUP(MOD(G11/30,3),0),S11,150-S11+1,MOD(74+S11,150)+1) -> 136 | U11: =INDEX(D150EnglishNames,T11) -> smarā | V11: =INDEX(ShayanaadiAvastha,J11) -> Gamana | W11: =MOD(MOD(($J11*$J11+W$5)+11,12)*INDEX(GrahaShayanadiGunanka,$AB11)+2,3)+1 -> 3 | X11: =MOD(MOD(($J11*$J11+X$5)+11,12)*INDEX(GrahaShayanadiGunanka,$AB11)+2,3)+1 -> 3 | Y11: =MOD(MOD(($J11*$J11+Y$5)+11,12)*INDEX(GrahaShayanadiGunanka,$AB11)+2,3)+1 -> 3 | Z11: =MOD(MOD(($J11*$J11+Z$5)+11,12)*INDEX(GrahaShayanadiGunanka,$AB11)+2,3)+1 -> 3 | AA11: =MOD(MOD(($J11*$J11+AA$5)+11,12)*INDEX(GrahaShayanadiGunanka,$AB11)+2,3)+1 -> 3 | AB11: 4 | AD11: if in Agaman, the same effects, due to his being in Gaman, will fructify; (if in Gaman, will visit the courts of kings on many occasions and Goddess Lakshmi will dwell in his abode)
A12: =TRIM(LEFT(JHora!A37,FIND(" ",JHora!A37))) -> Jupiter | B12: =MID(JHora!A37,FIND("'",JHora!A37)-8,2) -> 3 | C12: =MID(JHora!A37,FIND("'",JHora!A37)-5,2) -> Sc | D12: =MID(JHora!A37,FIND("'",JHora!A37)-2,2)+VALUE(MID(JHora!A37,FIND("'",JHora!A37)+2,5))/60 -> 11.8305 | E12: =INDEX(NakshatraTbl,INT(G12*0.075)+1,1) -> Vishakha | F12: =CHOOSE(RANK(H12,H$8:H$15),"Ak","Amk","Bk","Mk","PiK","PuK","Gk","Dk") -> Gk | G12: =VLOOKUP(C12,RasiDeg,2,0)+B12+D12/60 -> 213.19717 | H12: =B12+D12/60 -> 3.197175 | I12: =INDEX(NakshatraTbl,INT(G12*0.075)+1,3) -> Jupiter | J12: =MOD(ROUNDUP(G12/13.3333333333,0)*5*ROUNDUP(MOD(G12,30)/3.33333,0)+ROUNDUP(Moon/13.333,0)+ROUNDUP(JanmaGhatika,0)+ROUNDUP(Lagna/30,0),12) -> 1 | K12: =NOT(ISERROR(SEARCH("(R)",JHora!A37))) -> 1 | L12: =ROUNDUP(IF((Moon-G12)<0,-1*(180+(Moon-G12)),Moon-G12)/12,0) -> -2 | M12: =INDEX(Tithi,MOD(ABS(L12),8)) -> Moon | N12: =INDEX(D20Deities,ROUNDUP(H12/1.5,0)+MOD(ROUNDUP(G12/30,0)-1,2)*20,1) -> chinnaśīrṣā | O12: =INDEX(D20Deities,ROUNDUP(H12/1.5,0)+MOD(ROUNDUP(G12/30,0)-1,2)*20,2) -> छिन्नशीर्षा | P12: =INDEX(D27Deities,ROUNDUP(H12/30*27,0),1) -> vahni | Q12: =INDEX(D27Deities,ROUNDUP(H12/30*27,0),2) -> वह्नि | R12: =INT(H12/900*360)&" s"&" "&TEXT(MOD(H12/30*360,30)/24,"[HH]:MM:ss") -> 1 s 08:21:58 | S12: =MATCH(H12,D150InequalDegrees) -> 16 | T12: =CHOOSE(ROUNDUP(MOD(G12/30,3),0),S12,150-S12+1,MOD(74+S12,150)+1) -> 135 | U12: =INDEX(D150EnglishNames,T12) -> kadalī | V12: =INDEX(ShayanaadiAvastha,J12) -> Sayana | W12: =MOD(MOD(($J12*$J12+W$5)+11,12)*INDEX(GrahaShayanadiGunanka,$AB12)+2,3)+1 -> 2 | X12: =MOD(MOD(($J12*$J12+X$5)+11,12)*INDEX(GrahaShayanadiGunanka,$AB12)+2,3)+1 -> 1 | Y12: =MOD(MOD(($J12*$J12+Y$5)+11,12)*INDEX(GrahaShayanadiGunanka,$AB12)+2,3)+1 -> 3 | Z12: =MOD(MOD(($J12*$J12+Z$5)+11,12)*INDEX(GrahaShayanadiGunanka,$AB12)+2,3)+1 -> 2 | AA12: =MOD(MOD(($J12*$J12+AA$5)+11,12)*INDEX(GrahaShayanadiGunanka,$AB12)+2,3)+1 -> 1 | AB12: 5 | AD12: if in Upavesan, will be garrulous and very proud, will be troubled by the king and enemies and will have ulcers on the feet shanks, face and hands;
A13: =TRIM(LEFT(JHora!A38,FIND(" ",JHora!A38))) -> Venus | B13: =MID(JHora!A38,FIND("'",JHora!A38)-8,2) -> 21 | C13: =MID(JHora!A38,FIND("'",JHora!A38)-5,2) -> Ge | D13: =MID(JHora!A38,FIND("'",JHora!A38)-2,2)+VALUE(MID(JHora!A38,FIND("'",JHora!A38)+2,5))/60 -> 32.436167 | E13: =INDEX(NakshatraTbl,INT(G13*0.075)+1,1) -> Punarvasu | F13: =CHOOSE(RANK(H13,H$8:H$15),"Ak","Amk","Bk","Mk","PiK","PuK","Gk","Dk") -> Mk | G13: =VLOOKUP(C13,RasiDeg,2,0)+B13+D13/60 -> 81.540603 | H13: =B13+D13/60 -> 21.540603 | I13: =INDEX(NakshatraTbl,INT(G13*0.075)+1,3) -> Jupiter | J13: =MOD(ROUNDUP(G13/13.3333333333,0)*6*ROUNDUP(MOD(G13,30)/3.33333,0)+ROUNDUP(Moon/13.333,0)+ROUNDUP(JanmaGhatika,0)+ROUNDUP(Lagna/30,0)+11,12)+1 -> 11 | K13: =NOT(ISERROR(SEARCH("(R)",JHora!A38))) -> 0 | L13: =ROUNDUP(IF((Moon-G13)<0,-1*(180+(Moon-G13)),Moon-G13)/12,0) -> -13 | M13: =INDEX(Tithi,MOD(ABS(L13),8)) -> Jupiter | N13: =INDEX(D20Deities,ROUNDUP(H13/1.5,0)+MOD(ROUNDUP(G13/30,0)-1,2)*20,1) -> raudrī | O13: =INDEX(D20Deities,ROUNDUP(H13/1.5,0)+MOD(ROUNDUP(G13/30,0)-1,2)*20,2) -> रौद्री | P13: =INDEX(D27Deities,ROUNDUP(H13/30*27,0),1) -> udaka | Q13: =INDEX(D27Deities,ROUNDUP(H13/30*27,0),2) -> उदक | R13: =INT(H13/900*360)&" s"&" "&TEXT(MOD(H13/30*360,30)/24,"[HH]:MM:ss") -> 8 s 18:29:14 | S13: =MATCH(H13,D150InequalDegrees) -> 110 | T13: =CHOOSE(ROUNDUP(MOD(G13/30,3),0),S13,150-S13+1,MOD(74+S13,150)+1) -> 35 | U13: =INDEX(D150EnglishNames,T13) -> kṣamā | V13: =INDEX(ShayanaadiAvastha,J13) -> Kautuka | W13: =MOD(MOD(($J13*$J13+W$5)+11,12)*INDEX(GrahaShayanadiGunanka,$AB13)+2,3)+1 -> 3 | X13: =MOD(MOD(($J13*$J13+X$5)+11,12)*INDEX(GrahaShayanadiGunanka,$AB13)+2,3)+1 -> 3 | Y13: =MOD(MOD(($J13*$J13+Y$5)+11,12)*INDEX(GrahaShayanadiGunanka,$AB13)+2,3)+1 -> 3 | Z13: =MOD(MOD(($J13*$J13+Z$5)+11,12)*INDEX(GrahaShayanadiGunanka,$AB13)+2,3)+1 -> 3 | AA13: =MOD(MOD(($J13*$J13+AA$5)+11,12)*INDEX(GrahaShayanadiGunanka,$AB13)+2,3)+1 -> 3 | AB13: 6 | AD13: if in Nidr, will be interested in serving others, will blame others, be heroic, garrulous and will be wandering all over the earth.
A14: =TRIM(LEFT(JHora!A39,FIND(" ",JHora!A39))) -> Saturn | B14: =MID(JHora!A39,FIND("'",JHora!A39)-8,2) -> 9 | C14: =MID(JHora!A39,FIND("'",JHora!A39)-5,2) -> Ta | D14: =MID(JHora!A39,FIND("'",JHora!A39)-2,2)+VALUE(MID(JHora!A39,FIND("'",JHora!A39)+2,5))/60 -> 53.112667 | E14: =INDEX(NakshatraTbl,INT(G14*0.075)+1,1) -> Kritika | F14: =CHOOSE(RANK(H14,H$8:H$15),"Ak","Amk","Bk","Mk","PiK","PuK","Gk","Dk") -> PiK | G14: =VLOOKUP(C14,RasiDeg,2,0)+B14+D14/60 -> 39.885211 | H14: =B14+D14/60 -> 9.8852111 | I14: =INDEX(NakshatraTbl,INT(G14*0.075)+1,3) -> Sun | J14: =MOD(ROUNDUP(G14/13.3333333333,0)*7*ROUNDUP(MOD(G14,30)/3.33333,0)+ROUNDUP(Moon/13.333,0)+ROUNDUP(JanmaGhatika,0)+ROUNDUP(Lagna/30,0)+11,12)+1 -> 8 | K14: =NOT(ISERROR(SEARCH("(R)",JHora!A39))) -> 0 | L14: =ROUNDUP(IF((Moon-G14)<0,-1*(180+(Moon-G14)),Moon-G14)/12,0) -> 2 | M14: =INDEX(Tithi,MOD(ABS(L14),8)) -> Moon | N14: =INDEX(D20Deities,ROUNDUP(H14/1.5,0)+MOD(ROUNDUP(G14/30,0)-1,2)*20,1) -> bālā | O14: =INDEX(D20Deities,ROUNDUP(H14/1.5,0)+MOD(ROUNDUP(G14/30,0)-1,2)*20,2) -> बाला | P14: =INDEX(D27Deities,ROUNDUP(H14/30*27,0),1) -> ahi | Q14: =INDEX(D27Deities,ROUNDUP(H14/30*27,0),2) -> अहि | R14: =INT(H14/900*360)&" s"&" "&TEXT(MOD(H14/30*360,30)/24,"[HH]:MM:ss") -> 3 s 28:37:21 | S14: =MATCH(H14,D150InequalDegrees) -> 51 | T14: =CHOOSE(ROUNDUP(MOD(G14/30,3),0),S14,150-S14+1,MOD(74+S14,150)+1) -> 100 | U14: =INDEX(D150EnglishNames,T14) -> sārā | V14: =INDEX(ShayanaadiAvastha,J14) -> Aagama | W14: =MOD(MOD(($J14*$J14+W$5)+11,12)*INDEX(GrahaShayanadiGunanka,$AB14)+2,3)+1 -> 3 | X14: =MOD(MOD(($J14*$J14+X$5)+11,12)*INDEX(GrahaShayanadiGunanka,$AB14)+2,3)+1 -> 3 | Y14: =MOD(MOD(($J14*$J14+Y$5)+11,12)*INDEX(GrahaShayanadiGunanka,$AB14)+2,3)+1 -> 3 | Z14: =MOD(MOD(($J14*$J14+Z$5)+11,12)*INDEX(GrahaShayanadiGunanka,$AB14)+2,3)+1 -> 3 | AA14: =MOD(MOD(($J14*$J14+AA$5)+11,12)*INDEX(GrahaShayanadiGunanka,$AB14)+2,3)+1 -> 3 | AB14: 7 | AC14: 3 | AD14: if in Bhojan, will enjoy tastes of food, will be weak-sighted and will be fickle-minded, due to mental delusion;
A15: =TRIM(LEFT(JHora!A40,FIND(" ",JHora!A40))) -> Rahu | B15: =MID(JHora!A40,FIND("'",JHora!A40)-8,2) -> 21 | C15: =MID(JHora!A40,FIND("'",JHora!A40)-5,2) -> Cp | D15: =MID(JHora!A40,FIND("'",JHora!A40)-2,2)+VALUE(MID(JHora!A40,FIND("'",JHora!A40)+2,5))/60 -> 58.034333 | E15: =INDEX(NakshatraTbl,INT(G15*0.075)+1,1) -> Abhijit | F15: =CHOOSE(RANK(H15,H$8:H$15),"Ak","Amk","Bk","Mk","PiK","PuK","Gk","Dk") -> PuK | G15: =VLOOKUP(C15,RasiDeg,2,0)+B15+D15/60 -> 291.96724 | H15: =30-(B15+D15/60) -> 8.0327611 | I15: =INDEX(NakshatraTbl,INT(G15*0.075)+1,3) -> Sun | J15: =MOD(ROUNDUP(G15/13.3333333333,0)*8*ROUNDUP(MOD(G15,30)/3.33333,0)+ROUNDUP(Moon/13.333,0)+ROUNDUP(JanmaGhatika,0)+ROUNDUP(Lagna/30,0)+11,12)+1 -> 1 | K15: =NOT(ISERROR(SEARCH("(R)",JHora!A40))) -> 0 | N15: =INDEX(D20Deities,ROUNDUP(H15/1.5,0)+MOD(ROUNDUP(G15/30,0)-1,2)*20,1) -> mātaṅgī | O15: =INDEX(D20Deities,ROUNDUP(H15/1.5,0)+MOD(ROUNDUP(G15/30,0)-1,2)*20,2) -> मातङ्गी | P15: =INDEX(D27Deities,ROUNDUP(H15/30*27,0),1) -> jīva | Q15: =INDEX(D27Deities,ROUNDUP(H15/30*27,0),2) -> जीव | R15: =INT(H15/900*360)&" s"&" "&TEXT(MOD(H15/30*360,30)/24,"[HH]:MM:ss") -> 3 s 06:23:35 | S15: =MATCH(H15,D150InequalDegrees) -> 40 | T15: =CHOOSE(ROUNDUP(MOD(G15/30,3),0),S15,150-S15+1,MOD(74+S15,150)+1) -> 40 | U15: =INDEX(D150EnglishNames,T15) -> vikaṭā | V15: =INDEX(ShayanaadiAvastha,J15) -> Sayana | W15: =MOD(MOD(($J15*$J15+W$5)+11,12)*INDEX(GrahaShayanadiGunanka,$AB15)+2,3)+1 -> 1 | X15: =MOD(MOD(($J15*$J15+X$5)+11,12)*INDEX(GrahaShayanadiGunanka,$AB15)+2,3)+1 -> 2 | Y15: =MOD(MOD(($J15*$J15+Y$5)+11,12)*INDEX(GrahaShayanadiGunanka,$AB15)+2,3)+1 -> 3 | Z15: =MOD(MOD(($J15*$J15+Z$5)+11,12)*INDEX(GrahaShayanadiGunanka,$AB15)+2,3)+1 -> 1 | AA15: =MOD(MOD(($J15*$J15+AA$5)+11,12)*INDEX(GrahaShayanadiGunanka,$AB15)+2,3)+1 -> 2 | AB15: 8 | AD15: If Rahu is in Upavesan, the native will be distressed, due to ulcers, will be endowed with royal association, be highly honourable and ever devoid of financial happiness;
A16: =TRIM(LEFT(JHora!A41,FIND(" ",JHora!A41))) -> Ketu | B16: =MID(JHora!A41,FIND("'",JHora!A41)-8,2) -> 21 | C16: =MID(JHora!A41,FIND("'",JHora!A41)-5,2) -> Cn | D16: =MID(JHora!A41,FIND("'",JHora!A41)-2,2)+VALUE(MID(JHora!A41,FIND("'",JHora!A41)+2,5))/60 -> 58.034333 | E16: =INDEX(NakshatraTbl,INT(G16*0.075)+1,1) -> Ashlesha | F16: - | G16: =VLOOKUP(C16,RasiDeg,2,0)+B16+D16/60 -> 111.96724 | H16: =B16+D16/60 -> 21.967239 | I16: =INDEX(NakshatraTbl,INT(G16*0.075)+1,3) -> Merc | J16: =MOD(ROUNDUP(G16/13.3333333333,0)*9*ROUNDUP(MOD(G16,30)/3.33333,0)+ROUNDUP(Moon/13.333,0)+ROUNDUP(JanmaGhatika,0)+ROUNDUP(Lagna/30,0)+11,12)+1 -> 8 | K16: =NOT(ISERROR(SEARCH("(R)",JHora!A41))) -> 0 | N16: =INDEX(D20Deities,ROUNDUP(H16/1.5,0)+MOD(ROUNDUP(G16/30,0)-1,2)*20,1) -> vaiṣṇavī | O16: =INDEX(D20Deities,ROUNDUP(H16/1.5,0)+MOD(ROUNDUP(G16/30,0)-1,2)*20,2) -> वैष्णवी | P16: =INDEX(D27Deities,ROUNDUP(H16/30*27,0),1) -> udaka | Q16: =INDEX(D27Deities,ROUNDUP(H16/30*27,0),2) -> उदक | R16: =INT(H16/900*360)&" s"&" "&TEXT(MOD(H16/30*360,30)/24,"[HH]:MM:ss") -> 8 s 23:36:25 | S16: =MATCH(H16,D150InequalDegrees) -> 111 | T16: =CHOOSE(ROUNDUP(MOD(G16/30,3),0),S16,150-S16+1,MOD(74+S16,150)+1) -> 111 | U16: =INDEX(D150EnglishNames,T16) -> brahmiḥ | V16: =INDEX(ShayanaadiAvastha,J16) -> Aagama | W16: =MOD(MOD(($J16*$J16+W$5)+11,12)*INDEX(GrahaShayanadiGunanka,$AB16)+2,3)+1 -> 1 | X16: =MOD(MOD(($J16*$J16+X$5)+11,12)*INDEX(GrahaShayanadiGunanka,$AB16)+2,3)+1 -> 2 | Y16: =MOD(MOD(($J16*$J16+Y$5)+11,12)*INDEX(GrahaShayanadiGunanka,$AB16)+2,3)+1 -> 3 | Z16: =MOD(MOD(($J16*$J16+Z$5)+11,12)*INDEX(GrahaShayanadiGunanka,$AB16)+2,3)+1 -> 1 | AA16: =MOD(MOD(($J16*$J16+AA$5)+11,12)*INDEX(GrahaShayanadiGunanka,$AB16)+2,3)+1 -> 2 | AB16: 9 | AD16: if in Bhojan, will always be distressed with hunger, penury and diseases and will roam all over the earth;
A17: =TRIM(LEFT(JHora!A42,FIND(" ",JHora!A42))) -> Maandi | B17: =MID(JHora!A42,FIND("'",JHora!A42)-8,2) -> 8 | C17: =MID(JHora!A42,FIND("'",JHora!A42)-5,2) -> Sc | D17: =MID(JHora!A42,FIND("'",JHora!A42)-2,2)+VALUE(MID(JHora!A42,FIND("'",JHora!A42)+2,5))/60 -> 13.930167 | E17: =INDEX(NakshatraTbl,INT(G17*0.075)+1,1) -> Anuradha | F17: - | G17: =VLOOKUP(C17,RasiDeg,2,0)+B17+D17/60 -> 218.23217 | H17: =B17+D17/60 -> 8.2321694 | I17: =INDEX(NakshatraTbl,INT(G17*0.075)+1,3) -> Sat | N17: =INDEX(D20Deities,ROUNDUP(H17/1.5,0)+MOD(ROUNDUP(G17/30,0)-1,2)*20,1) -> mātaṅgī | O17: =INDEX(D20Deities,ROUNDUP(H17/1.5,0)+MOD(ROUNDUP(G17/30,0)-1,2)*20,2) -> मातङ्गी | P17: =INDEX(D27Deities,ROUNDUP(H17/30*27,0),1) -> jīva | Q17: =INDEX(D27Deities,ROUNDUP(H17/30*27,0),2) -> जीव | R17: =INT(H17/900*360)&" s"&" "&TEXT(MOD(H17/30*360,30)/24,"[HH]:MM:ss") -> 3 s 08:47:10 | S17: =MATCH(H17,D150InequalDegrees) -> 40 | T17: =CHOOSE(ROUNDUP(MOD(G17/30,3),0),S17,150-S17+1,MOD(74+S17,150)+1) -> 111 | U17: =INDEX(D150EnglishNames,T17) -> brahmiḥ
A18: =TRIM(LEFT(JHora!A43,FIND(" ",JHora!A43))) -> Gulika | B18: =MID(JHora!A43,FIND("'",JHora!A43)-8,2) -> 19 | C18: =MID(JHora!A43,FIND("'",JHora!A43)-5,2) -> Sc | D18: =MID(JHora!A43,FIND("'",JHora!A43)-2,2)+VALUE(MID(JHora!A43,FIND("'",JHora!A43)+2,5))/60 -> 6.2461667 | E18: =INDEX(NakshatraTbl,INT(G18*0.075)+1,1) -> Jyeshtha | F18: - | G18: =VLOOKUP(C18,RasiDeg,2,0)+B18+D18/60 -> 229.1041 | H18: =B18+D18/60 -> 19.104103 | I18: =INDEX(NakshatraTbl,INT(G18*0.075)+1,3) -> Merc | N18: =INDEX(D20Deities,ROUNDUP(H18/1.5,0)+MOD(ROUNDUP(G18/30,0)-1,2)*20,1) -> ghorā | O18: =INDEX(D20Deities,ROUNDUP(H18/1.5,0)+MOD(ROUNDUP(G18/30,0)-1,2)*20,2) -> घोरा | P18: =INDEX(D27Deities,ROUNDUP(H18/30*27,0),1) -> vāsava | Q18: =INDEX(D27Deities,ROUNDUP(H18/30*27,0),2) -> वासव | R18: =INT(H18/900*360)&" s"&" "&TEXT(MOD(H18/30*360,30)/24,"[HH]:MM:ss") -> 7 s 19:14:57 | S18: =MATCH(H18,D150InequalDegrees) -> 97 | T18: =CHOOSE(ROUNDUP(MOD(G18/30,3),0),S18,150-S18+1,MOD(74+S18,150)+1) -> 54 | U18: =INDEX(D150EnglishNames,T18) -> viṣākhyā
A19: =TRIM(LEFT(JHora!A44,FIND(" ",JHora!A44))) -> Bhava | B19: =MID(JHora!A44,FIND("'",JHora!A44)-8,2) -> 19 | C19: =MID(JHora!A44,FIND("'",JHora!A44)-5,2) -> Le | D19: =MID(JHora!A44,FIND("'",JHora!A44)-2,2)+VALUE(MID(JHora!A44,FIND("'",JHora!A44)+2,5))/60 -> 52.181667 | E19: =INDEX(NakshatraTbl,INT(G19*0.075)+1,1) -> Purva Phalguni | F19: - | G19: =VLOOKUP(C19,RasiDeg,2,0)+B19+D19/60 -> 139.86969 | H19: =B19+D19/60 -> 19.869694 | I19: =INDEX(NakshatraTbl,INT(G19*0.075)+1,3) -> Venus | N19: =INDEX(D20Deities,ROUNDUP(H19/1.5,0)+MOD(ROUNDUP(G19/30,0)-1,2)*20,1) -> śacī | O19: =INDEX(D20Deities,ROUNDUP(H19/1.5,0)+MOD(ROUNDUP(G19/30,0)-1,2)*20,2) -> शची | P19: =INDEX(D27Deities,ROUNDUP(H19/30*27,0),1) -> vāsava | Q19: =INDEX(D27Deities,ROUNDUP(H19/30*27,0),2) -> वासव | R19: =INT(H19/900*360)&" s"&" "&TEXT(MOD(H19/30*360,30)/24,"[HH]:MM:ss") -> 7 s 28:26:11 | S19: =MATCH(H19,D150InequalDegrees) -> 99 | T19: =CHOOSE(ROUNDUP(MOD(G19/30,3),0),S19,150-S19+1,MOD(74+S19,150)+1) -> 52 | U19: =INDEX(D150EnglishNames,T19) -> kundinī
A20: =TRIM(LEFT(JHora!A45,FIND(" ",JHora!A45))) -> Hora | B20: =MID(JHora!A45,FIND("'",JHora!A45)-8,2) -> 7 | C20: =MID(JHora!A45,FIND("'",JHora!A45)-5,2) -> Li | D20: =MID(JHora!A45,FIND("'",JHora!A45)-2,2)+VALUE(MID(JHora!A45,FIND("'",JHora!A45)+2,5))/60 -> 20.411333 | E20: =INDEX(NakshatraTbl,INT(G20*0.075)+1,1) -> Swati | F20: - | G20: =VLOOKUP(C20,RasiDeg,2,0)+B20+D20/60 -> 187.34019 | H20: =B20+D20/60 -> 7.3401889 | I20: =INDEX(NakshatraTbl,INT(G20*0.075)+1,3) -> Rahu | N20: =INDEX(D20Deities,ROUNDUP(H20/1.5,0)+MOD(ROUNDUP(G20/30,0)-1,2)*20,1) -> vijayā | O20: =INDEX(D20Deities,ROUNDUP(H20/1.5,0)+MOD(ROUNDUP(G20/30,0)-1,2)*20,2) -> विजया | P20: =INDEX(D27Deities,ROUNDUP(H20/30*27,0),1) -> aditi | Q20: =INDEX(D27Deities,ROUNDUP(H20/30*27,0),2) -> अदिति | R20: =INT(H20/900*360)&" s"&" "&TEXT(MOD(H20/30*360,30)/24,"[HH]:MM:ss") -> 2 s 28:04:56 | S20: =MATCH(H20,D150InequalDegrees) -> 37 | T20: =CHOOSE(ROUNDUP(MOD(G20/30,3),0),S20,150-S20+1,MOD(74+S20,150)+1) -> 37 | U20: =INDEX(D150EnglishNames,T20) -> durbhagā
A21: =TRIM(LEFT(JHora!A46,FIND(" ",JHora!A46))) -> Ghati | B21: =MID(JHora!A46,FIND("'",JHora!A46)-8,2) -> 29 | C21: =MID(JHora!A46,FIND("'",JHora!A46)-5,2) -> Aq | D21: =MID(JHora!A46,FIND("'",JHora!A46)-2,2)+VALUE(MID(JHora!A46,FIND("'",JHora!A46)+2,5))/60 -> 45.099833 | E21: =INDEX(NakshatraTbl,INT(G21*0.075)+1,1) -> Satabishak | F21: - | G21: =VLOOKUP(C21,RasiDeg,2,0)+B21+D21/60 -> 329.75166 | H21: =B21+D21/60 -> 29.751664 | I21: =INDEX(NakshatraTbl,INT(G21*0.075)+1,3) -> Rahu | N21: =INDEX(D20Deities,ROUNDUP(H21/1.5,0)+MOD(ROUNDUP(G21/30,0)-1,2)*20,1) -> sumukhī | O21: =INDEX(D20Deities,ROUNDUP(H21/1.5,0)+MOD(ROUNDUP(G21/30,0)-1,2)*20,2) -> सुमुखी | P21: =INDEX(D27Deities,ROUNDUP(H21/30*27,0),1) -> pūṣā | Q21: =INDEX(D27Deities,ROUNDUP(H21/30*27,0),2) -> पूषा | R21: =INT(H21/900*360)&" s"&" "&TEXT(MOD(H21/30*360,30)/24,"[HH]:MM:ss") -> 11 s 27:01:12 | S21: =MATCH(H21,D150InequalDegrees) -> 150 | T21: =CHOOSE(ROUNDUP(MOD(G21/30,3),0),S21,150-S21+1,MOD(74+S21,150)+1) -> 1 | U21: =INDEX(D150EnglishNames,T21) -> vasudhā
A22: =TRIM(LEFT(JHora!A47,FIND(" ",JHora!A47))) -> Vighati | B22: =MID(JHora!A47,FIND("'",JHora!A47)-8,2) -> 21 | C22: =MID(JHora!A47,FIND("'",JHora!A47)-5,2) -> Aq | D22: =MID(JHora!A47,FIND("'",JHora!A47)-2,2)+VALUE(MID(JHora!A47,FIND("'",JHora!A47)+2,5))/60 -> 48.543 | E22: =INDEX(NakshatraTbl,INT(G22*0.075)+1,1) -> Satabishak | F22: - | G22: =VLOOKUP(C22,RasiDeg,2,0)+B22+D22/60 -> 321.80905 | H22: =B22+D22/60 -> 21.80905 | I22: =INDEX(NakshatraTbl,INT(G22*0.075)+1,3) -> Rahu | N22: =INDEX(D20Deities,ROUNDUP(H22/1.5,0)+MOD(ROUNDUP(G22/30,0)-1,2)*20,1) -> raudrī | O22: =INDEX(D20Deities,ROUNDUP(H22/1.5,0)+MOD(ROUNDUP(G22/30,0)-1,2)*20,2) -> रौद्री | P22: =INDEX(D27Deities,ROUNDUP(H22/30*27,0),1) -> udaka | Q22: =INDEX(D27Deities,ROUNDUP(H22/30*27,0),2) -> उदक | R22: =INT(H22/900*360)&" s"&" "&TEXT(MOD(H22/30*360,30)/24,"[HH]:MM:ss") -> 8 s 21:42:31 | S22: =MATCH(H22,D150InequalDegrees) -> 111 | T22: =CHOOSE(ROUNDUP(MOD(G22/30,3),0),S22,150-S22+1,MOD(74+S22,150)+1) -> 40 | U22: =INDEX(D150EnglishNames,T22) -> vikaṭā
A23: =TRIM(LEFT(JHora!A48,FIND(" ",JHora!A48))) -> Varnada | B23: =MID(JHora!A48,FIND("'",JHora!A48)-8,2) -> 16 | C23: =MID(JHora!A48,FIND("'",JHora!A48)-5,2) -> Pi | D23: =MID(JHora!A48,FIND("'",JHora!A48)-2,2)+VALUE(MID(JHora!A48,FIND("'",JHora!A48)+2,5))/60 -> 42.691 | E23: =INDEX(NakshatraTbl,INT(G23*0.075)+1,1) -> Uttara Bhadrapad | F23: - | G23: =VLOOKUP(C23,RasiDeg,2,0)+B23+D23/60 -> 346.71152 | H23: =B23+D23/60 -> 16.711517 | I23: =INDEX(NakshatraTbl,INT(G23*0.075)+1,3) -> Sat | N23: =INDEX(D20Deities,ROUNDUP(H23/1.5,0)+MOD(ROUNDUP(G23/30,0)-1,2)*20,1) -> chucchukā | O23: =INDEX(D20Deities,ROUNDUP(H23/1.5,0)+MOD(ROUNDUP(G23/30,0)-1,2)*20,2) -> छुच्छुका | P23: =INDEX(D27Deities,ROUNDUP(H23/30*27,0),1) -> śakrāgni | Q23: =INDEX(D27Deities,ROUNDUP(H23/30*27,0),2) -> शक्राग्नि | R23: =INT(H23/900*360)&" s"&" "&TEXT(MOD(H23/30*360,30)/24,"[HH]:MM:ss") -> 6 s 20:32:18 | S23: =MATCH(H23,D150InequalDegrees) -> 84 | T23: =CHOOSE(ROUNDUP(MOD(G23/30,3),0),S23,150-S23+1,MOD(74+S23,150)+1) -> 9 | U23: =INDEX(D150EnglishNames,T23) -> surā
A24: =TRIM(LEFT(JHora!A49,FIND(" ",JHora!A49))) -> Sree | B24: =MID(JHora!A49,FIND("'",JHora!A49)-8,2) -> 8 | C24: =MID(JHora!A49,FIND("'",JHora!A49)-5,2) -> Le | D24: =MID(JHora!A49,FIND("'",JHora!A49)-2,2)+VALUE(MID(JHora!A49,FIND("'",JHora!A49)+2,5))/60 -> 8.519 | E24: =INDEX(NakshatraTbl,INT(G24*0.075)+1,1) -> Magha | F24: - | G24: =VLOOKUP(C24,RasiDeg,2,0)+B24+D24/60 -> 128.14198 | H24: =B24+D24/60 -> 8.1419833 | I24: =INDEX(NakshatraTbl,INT(G24*0.075)+1,3) -> Ketu | N24: =INDEX(D20Deities,ROUNDUP(H24/1.5,0)+MOD(ROUNDUP(G24/30,0)-1,2)*20,1) -> vimalā | O24: =INDEX(D20Deities,ROUNDUP(H24/1.5,0)+MOD(ROUNDUP(G24/30,0)-1,2)*20,2) -> विमला | P24: =INDEX(D27Deities,ROUNDUP(H24/30*27,0),1) -> jīva | Q24: =INDEX(D27Deities,ROUNDUP(H24/30*27,0),2) -> जीव | R24: =INT(H24/900*360)&" s"&" "&TEXT(MOD(H24/30*360,30)/24,"[HH]:MM:ss") -> 3 s 07:42:14 | S24: =MATCH(H24,D150InequalDegrees) -> 40 | T24: =CHOOSE(ROUNDUP(MOD(G24/30,3),0),S24,150-S24+1,MOD(74+S24,150)+1) -> 111 | U24: =INDEX(D150EnglishNames,T24) -> brahmiḥ
A25: =TRIM(LEFT(JHora!A50,FIND(" ",JHora!A50))) -> Pranapada | B25: =MID(JHora!A50,FIND("'",JHora!A50)-8,2) -> 21 | C25: =MID(JHora!A50,FIND("'",JHora!A50)-5,2) -> Aq | D25: =MID(JHora!A50,FIND("'",JHora!A50)-2,2)+VALUE(MID(JHora!A50,FIND("'",JHora!A50)+2,5))/60 -> 48.543 | E25: =INDEX(NakshatraTbl,INT(G25*0.075)+1,1) -> Satabishak | F25: - | G25: =VLOOKUP(C25,RasiDeg,2,0)+B25+D25/60 -> 321.80905 | H25: =B25+D25/60 -> 21.80905 | I25: =INDEX(NakshatraTbl,INT(G25*0.075)+1,3) -> Rahu | N25: =INDEX(D20Deities,ROUNDUP(H25/1.5,0)+MOD(ROUNDUP(G25/30,0)-1,2)*20,1) -> raudrī | O25: =INDEX(D20Deities,ROUNDUP(H25/1.5,0)+MOD(ROUNDUP(G25/30,0)-1,2)*20,2) -> रौद्री | P25: =INDEX(D27Deities,ROUNDUP(H25/30*27,0),1) -> udaka | Q25: =INDEX(D27Deities,ROUNDUP(H25/30*27,0),2) -> उदक | R25: =INT(H25/900*360)&" s"&" "&TEXT(MOD(H25/30*360,30)/24,"[HH]:MM:ss") -> 8 s 21:42:31 | S25: =MATCH(H25,D150InequalDegrees) -> 111 | T25: =CHOOSE(ROUNDUP(MOD(G25/30,3),0),S25,150-S25+1,MOD(74+S25,150)+1) -> 40 | U25: =INDEX(D150EnglishNames,T25) -> vikaṭā
A26: =TRIM(LEFT(JHora!A51,FIND(" ",JHora!A51))) -> Indu | B26: =MID(JHora!A51,FIND("'",JHora!A51)-8,2) -> 23 | C26: =MID(JHora!A51,FIND("'",JHora!A51)-5,2) -> Sc | D26: =MID(JHora!A51,FIND("'",JHora!A51)-2,2)+VALUE(MID(JHora!A51,FIND("'",JHora!A51)+2,5))/60 -> 0.95666667 | E26: =INDEX(NakshatraTbl,INT(G26*0.075)+1,1) -> Jyeshtha | F26: - | G26: =VLOOKUP(C26,RasiDeg,2,0)+B26+D26/60 -> 233.01594 | H26: =B26+D26/60 -> 23.015944 | I26: =INDEX(NakshatraTbl,INT(G26*0.075)+1,3) -> Merc | N26: =INDEX(D20Deities,ROUNDUP(H26/1.5,0)+MOD(ROUNDUP(G26/30,0)-1,2)*20,1) -> sitā | O26: =INDEX(D20Deities,ROUNDUP(H26/1.5,0)+MOD(ROUNDUP(G26/30,0)-1,2)*20,2) -> सिता | P26: =INDEX(D27Deities,ROUNDUP(H26/30*27,0),1) -> viśve aja | Q26: =INDEX(D27Deities,ROUNDUP(H26/30*27,0),2) -> विश्वे अज | R26: =INT(H26/900*360)&" s"&" "&TEXT(MOD(H26/30*360,30)/24,"[HH]:MM:ss") -> 9 s 06:11:29 | S26: =MATCH(H26,D150InequalDegrees) -> 116 | T26: =CHOOSE(ROUNDUP(MOD(G26/30,3),0),S26,150-S26+1,MOD(74+S26,150)+1) -> 35 | U26: =INDEX(D150EnglishNames,T26) -> kṣamā
A27: =TRIM(LEFT(JHora!A52,FIND(" ",JHora!A52))) -> Bhrigu | B27: =MID(JHora!A52,FIND("'",JHora!A52)-8,2) -> 22 | C27: =MID(JHora!A52,FIND("'",JHora!A52)-5,2) -> Pi | D27: =MID(JHora!A52,FIND("'",JHora!A52)-2,2)+VALUE(MID(JHora!A52,FIND("'",JHora!A52)+2,5))/60 -> 29.4955 | E27: =INDEX(NakshatraTbl,INT(G27*0.075)+1,1) -> Uttara Bhadrapad | F27: - | G27: =VLOOKUP(C27,RasiDeg,2,0)+B27+D27/60 -> 352.49159 | H27: =B27+D27/60 -> 22.491592 | I27: =INDEX(NakshatraTbl,INT(G27*0.075)+1,3) -> Sat | N27: =INDEX(D20Deities,ROUNDUP(H27/1.5,0)+MOD(ROUNDUP(G27/30,0)-1,2)*20,1) -> vaiṣṇavī | O27: =INDEX(D20Deities,ROUNDUP(H27/1.5,0)+MOD(ROUNDUP(G27/30,0)-1,2)*20,2) -> वैष्णवी | P27: =INDEX(D27Deities,ROUNDUP(H27/30*27,0),1) -> viśve aja | Q27: =INDEX(D27Deities,ROUNDUP(H27/30*27,0),2) -> विश्वे अज | R27: =INT(H27/900*360)&" s"&" "&TEXT(MOD(H27/30*360,30)/24,"[HH]:MM:ss") -> 8 s 29:53:57 | S27: =MATCH(H27,D150InequalDegrees) -> 113 | T27: =CHOOSE(ROUNDUP(MOD(G27/30,3),0),S27,150-S27+1,MOD(74+S27,150)+1) -> 38 | U27: =INDEX(D150EnglishNames,T27) -> viśvā
A28: =TRIM(LEFT(JHora!A53,FIND(" ",JHora!A53))) -> Dhooma | B28: =MID(JHora!A53,FIND("'",JHora!A53)-8,2) -> 15 | C28: =MID(JHora!A53,FIND("'",JHora!A53)-5,2) -> Sc | D28: =MID(JHora!A53,FIND("'",JHora!A53)-2,2)+VALUE(MID(JHora!A53,FIND("'",JHora!A53)+2,5))/60 -> 43.952167 | E28: =INDEX(NakshatraTbl,INT(G28*0.075)+1,1) -> Anuradha | F28: - | G28: =VLOOKUP(C28,RasiDeg,2,0)+B28+D28/60 -> 225.73254 | H28: =B28+D28/60 -> 15.732536 | I28: =INDEX(NakshatraTbl,INT(G28*0.075)+1,3) -> Sat | N28: =INDEX(D20Deities,ROUNDUP(H28/1.5,0)+MOD(ROUNDUP(G28/30,0)-1,2)*20,1) -> piṅgalā | O28: =INDEX(D20Deities,ROUNDUP(H28/1.5,0)+MOD(ROUNDUP(G28/30,0)-1,2)*20,2) -> पिङ्गला | P28: =INDEX(D27Deities,ROUNDUP(H28/30*27,0),1) -> maruta | Q28: =INDEX(D27Deities,ROUNDUP(H28/30*27,0),2) -> मरुत | R28: =INT(H28/900*360)&" s"&" "&TEXT(MOD(H28/30*360,30)/24,"[HH]:MM:ss") -> 6 s 08:47:26 | S28: =MATCH(H28,D150InequalDegrees) -> 79 | T28: =CHOOSE(ROUNDUP(MOD(G28/30,3),0),S28,150-S28+1,MOD(74+S28,150)+1) -> 72 | U28: =INDEX(D150EnglishNames,T28) -> sudhāmṛtāṁśuḥ
... A30: =TRIM(LEFT(JHora!A55,FIND(" ",JHora!A55))) -> Parivesha | B30: =MID(JHora!A55,FIND("'",JHora!A55)-8,2) -> 14 | C30: =MID(JHora!A55,FIND("'",JHora!A55)-5,2) -> Aq | D30: =MID(JHora!A55,FIND("'",JHora!A55)-2,2)+VALUE(MID(JHora!A55,FIND("'",JHora!A55)+2,5))/60 -> 16.047833 | E30: =INDEX(NakshatraTbl,INT(G30*0.075)+1,1) -> Dhanistha | F30: - | G30: =VLOOKUP(C30,RasiDeg,2,0)+B30+D30/60 -> 314.26746 | H30: =B30+D30/60 -> 14.267464 | I30: =INDEX(NakshatraTbl,INT(G30*0.075)+1,3) -> Mars | N30: =INDEX(D20Deities,ROUNDUP(H30/1.5,0)+MOD(ROUNDUP(G30/30,0)-1,2)*20,1) -> śvetā | O30: =INDEX(D20Deities,ROUNDUP(H30/1.5,0)+MOD(ROUNDUP(G30/30,0)-1,2)*20,2) -> श्वेता | P30: =INDEX(D27Deities,ROUNDUP(H30/30*27,0),1) -> arka | Q30: =INDEX(D27Deities,ROUNDUP(H30/30*27,0),2) -> अर्क | R30: =INT(H30/900*360)&" s"&" "&TEXT(MOD(H30/30*360,30)/24,"[HH]:MM:ss") -> 5 s 21:12:34 | S30: =MATCH(H30,D150InequalDegrees) -> 72 | T30: =CHOOSE(ROUNDUP(MOD(G30/30,3),0),S30,150-S30+1,MOD(74+S30,150)+1) -> 79 | U30: =INDEX(D150EnglishNames,T30) -> śobhā
A31: Shri Lagna | B31: =FLOOR(MOD(G31,30),1) -> 8 | C31: =INDEX(RasiDeg,ROUNDUP(G31/30,0),1) -> Le | D31: =ROUND((MOD(G31,30)-B31)*60,1) -> 8.5 | E31: =INDEX(NakshatraTbl,INT(G31*0.075)+1,1) -> Magha | G31: =MOD(((MOD(G9,StarDeg)/StarDeg)*360)+G7,360) -> 128.14202 | H31: =B31+D31/60 -> 8.1416667 | I31: =INDEX(NakshatraTbl,INT(G31*0.075)+1,3) -> Ketu
A32: Varnada Lagna | B32: =FLOOR(MOD(G32,30),1) -> 24 | C32: =INDEX(RasiDeg,ROUNDUP(G32/30,0),1) -> Pi | D32: =ROUND((MOD(G32,30)-B32)*60,1) -> 11.1 | E32: =INDEX(NakshatraTbl,INT(G32*0.075)+1,1) -> Uttara Bhadrapad | G32: =MOD(IF(MOD(INT(G7/30)+INT(G18/30),2)=1,(MOD(INT(G7/30),2)*360-G7)+(MOD(INT(G18/30),2)*360-G18),G7+G18),360) -> 354.18438 | H32: =B32+D32/60 -> 24.185 | I32: =INDEX(NakshatraTbl,INT(G32*0.075)+1,3) -> Sat
A33: Varnada Lagna | B33: =FLOOR(MOD(G33,30),1) -> 24 | C33: =INDEX(RasiDeg,ROUNDUP(G33/30,0),1) -> Aq | D33: =ROUND((MOD(G33,30)-B33)*60,1) -> 3.1 | E33: =INDEX(NakshatraTbl,INT(G33*0.075)+1,1) -> Satabishak | G33: =M33 -> 324.05171 | H33: =B33+D33/60 -> 24.051667 | I33: =INDEX(NakshatraTbl,INT(G33*0.075)+1,3) -> Rahu | J33: =IF(MOD(INT(Lagna/30),2),360-Lagna,Lagna) -> 136.71152 | K33: =IF(MOD(INT(HoraLagna/30),2),360-HoraLagna,HoraLagna) -> 187.34019 | L33: =MOD(IF(MOD(INT(J33/30)+INT(K33/30),2),ABS(J33-K33),J33+K33),360) -> 324.05171 | M33: =IF(MOD(INT(L33/30),2),360-L33,L33) -> 324.05171
A34: Utpanna(5th) Star | B34: =FLOOR(MOD(G34,30),1) -> 16 | C34: =INDEX(RasiDeg,ROUNDUP(G34/30,0),1) -> Cn | D34: =ROUND((MOD(G34,30)-B34)*60,1) -> 21 | E34: =INDEX(NakshatraTbl,INT(G34*0.075)+1,1) -> Pushya | G34: =MOD(MoonDeg+4*StarDeg,360) -> 106.34928 | H34: =B34+D34/60 -> 16.35 | I34: =INDEX(NakshatraTbl,INT(G34*0.075)+1,3) -> Sat
A35: Kshema(4th) Star | B35: =FLOOR(MOD(G35,30),1) -> 3 | C35: =INDEX(RasiDeg,ROUNDUP(G35/30,0),1) -> Cn | D35: =ROUND((MOD(G35,30)-B35)*60,1) -> 1 | E35: =INDEX(NakshatraTbl,INT(G35*0.075)+1,1) -> Punarvasu | G35: =MOD(MoonDeg+3*StarDeg,360) -> 93.015944 | H35: =B35+D35/60 -> 3.0166667 | I35: =INDEX(NakshatraTbl,INT(G35*0.075)+1,3) -> Jupiter | K35: =
A36: Sun+Moon | B36: =FLOOR(MOD(G36,30),1) -> 25 | C36: =INDEX(RasiDeg,ROUNDUP(G36/30,0),1) -> Le | D36: =ROUND((MOD(G36,30)-B36)*60,1) -> 24.9 | E36: =INDEX(NakshatraTbl,INT(G36*0.075)+1,1) -> Purva Phalguni | F36: =INDEX(PanchangaYoga,INT((MOD(360+G36,360))*0.075)+1,2) -> Vriddhi | G36: =MOD(SunDeg+MoonDeg,360) -> 145.41515 | H36: =B36+D36/60 -> 25.415 | I36: =INDEX(NakshatraTbl,INT(G36*0.075)+1,3) -> Venus
A37: Panchanga Yoga | B37: =FLOOR(MOD(G37,30),1) -> 28 | C37: =INDEX(RasiDeg,ROUNDUP(G37/30,0),1) -> Sc | D37: =ROUND((MOD(G37,30)-B37)*60,1) -> 44.9 | E37: =INDEX(NakshatraTbl,INT(G37*0.075)+1,1) -> Jyeshtha | F37: =INDEX(PanchangaYoga,INT((MOD(360+G37-PushyaDegree,360))*0.075)+1,2) -> Vriddhi | G37: =MOD(SunDeg+MoonDeg+PushyaDegree,360) -> 238.74848 | H37: =B37+D37/60 -> 28.748333 | I37: =INDEX(NakshatraTbl,INT(G37*0.075)+1,3) -> Merc | J37: Called "Yogi Point" by Sheshadri Iyer
A38: Ava Yoga/Yogi | B38: =FLOOR(MOD(G38,30),1) -> 5 | C38: =INDEX(RasiDeg,ROUNDUP(G38/30,0),1) -> Ge | D38: =ROUND((MOD(G38,30)-B38)*60,1) -> 24.9 | E38: =INDEX(NakshatraTbl,INT(G38*0.075)+1,1) -> Mrigashira | F38: =INDEX(PanchangaYoga,INT(14*StarDeg*0.075)+1,2) -> Vajra | G38: =MOD(YogiDeg+14*StarDeg,360) -> 65.415147 | H38: =B38+D38/60 -> 5.415 | I38: =INDEX(NakshatraTbl,INT(G38*0.075)+1,3) -> Mars
A39: Sun+Rahu | B39: =FLOOR(MOD(G39,30),1) -> 24 | C39: =INDEX(RasiDeg,ROUNDUP(G39/30,0),1) -> Ar | D39: =ROUND((MOD(G39,30)-B39)*60,1) -> 22 | E39: =INDEX(NakshatraTbl,INT(G39*0.075)+1,1) -> Bharani | G39: =MOD(G8+G15,360) -> 24.366442 | H39: =B39+D39/60 -> 24.366667 | I39: =INDEX(NakshatraTbl,INT(G39*0.075)+1,3) -> Venus
A40: Sun+Saturn | B40: =FLOOR(MOD(G40,30),1) -> 12 | C40: =INDEX(RasiDeg,ROUNDUP(G40/30,0),1) -> Le | D40: =ROUND((MOD(G40,30)-B40)*60,1) -> 17.1 | E40: =INDEX(NakshatraTbl,INT(G40*0.075)+1,1) -> Magha | G40: =MOD(G8+G14,360) -> 132.28441 | H40: =B40+D40/60 -> 12.285 | I40: =INDEX(NakshatraTbl,INT(G40*0.075)+1,3) -> Ketu
A41: Sun+Venus | B41: =FLOOR(MOD(G41,30),1) -> 23 | C41: =INDEX(RasiDeg,ROUNDUP(G41/30,0),1) -> Vi | D41: =ROUND((MOD(G41,30)-B41)*60,1) -> 56.4 | E41: =INDEX(NakshatraTbl,INT(G41*0.075)+1,1) -> Chitra | G41: =MOD(G8+G13,360) -> 173.93981 | H41: =B41+D41/60 -> 23.94 | I41: =INDEX(NakshatraTbl,INT(G41*0.075)+1,3) -> Mars | K41: =FIND(" - ",JHora!A32) -> #VALUE! | L41: =ISERR(K41) -> TRUE
A42: Panchanga Tithi Number | B42: =ROUNDUP(G42/12,0) -> -12 | G42: =IF((Moon-Sun)<0,-1*(180+(Moon-Sun)),Moon-Sun) -> -140.61674 | I42: =INDEX(Tithi,MOD(ABS(B42),8)) -> Mercury | K42: =LEFT(JHora!A33,FIND(" - ",JHora!A33)) -> Sun
A43: Vighatika Lord | B43: =ROUNDUP(MOD(D50*60,9),0) -> 7 | C43: =INDEX(GrahaOrder,B43) -> Saturn | E43: =D50*60/24 -> 19.779514 | G43: =MOD(Lagna*81,360) -> 273.63285 | K43: =LEFT(JHora!A34,FIND(" - ",JHora!A34)) -> Moon
A44: SunRise | B44: =INT(DoB) +MOD(TIMEVALUE(TRIM(MID(JHora!A23,9,14))),1) -> 26133.252 | K44: =LEFT(JHora!A35,FIND(" - ",JHora!A35)) -> Mars (R)
A45: SunSet | B45: =INT(DoB)+MOD(TIMEVALUE(TRIM(MID(JHora!A24,9,18))),1) -> 26133.781 | K45: =LEFT(JHora!A36,FIND(" - ",JHora!A36)) -> Mercury
A46: Vaara | B46: =MOD(DoB-SunRise+6,7)+1 -> 7.1318634 | K46: =LEFT(JHora!A37,FIND(" - ",JHora!A37)) -> Jupiter (R)
A47: Mandi | B47: =SunRise+IF(DoB<SunSet,INDEX(Mandi,B46+2,2)/30*D48,D48+INDEX(Mandi,B46+2,2)/30*D49)/60 -> 26133.288 | C47: Hrs | D47: =IF(DoB<(INT(DoB)+SunSet),INDEX(Mandi,B46+2,2)/30*D48,D48+INDEX(Mandi,B46+2,2)/30*D49) -> 2.1138889 | E47: Ghatikas
A48: Day Duration | B48: =(SunSet-SunRise) -> 0.52847222 | D48: =(SunSet-SunRise)*60 -> 31.708333 | E48: Ghatikas
A49: Night Duration | B49: =1+B44-B45 -> 0.47152778 | D49: =60-D48 -> 28.291667 | E49: Ghatikas
A50: TimeSinceSunRise | B50: =DoB-SunRise -> 0.13186343 | C50: Hrs | D50: =B50*60 -> 7.9118056 | E50: Ghatikas
A51: Tattva Index | B51: =B50/IF(DayBirth,B48/120,B49/120) -> 29.942181
A52: Ahargana | B52: =INT(DoB-AharganaBaseDate+Ahargana) -> 714404096234 | E52: Day | F52: =B52-INT(B52/7)*7 -> 3
A53: day/Night Birth | B53: =IF(AND((DoB>SunRise), (DoB<SunSet)),1,0) -> 1
A54: Kali Era | B54: =YEAR(C2)+3102 -> 5073 | C54: Or | D54: =DoB-"1 Jan 1980"+1822903 -> #VALUE! | E54: Days
A55: Ayanamsha
A57: Planet | B57: Longitude | C57: Nakshatra | D57: Nak Ruler | E57: D1 | F57: D1# | G57: D3# | H57: D3 | I57: D4# | J57: D4 | K57: D7# | L57: D7 | M57: D9# | N57: D9 | O57: D10# | P57: D10 | Q57: D12# | R57: D12 | S57: SD3
A58: Asc | B58: =Lagna -> 136.71152 | C58: =INDEX(NakshatraTbl,INT(B58*0.075)+1,1) -> Purva Phalguni | D58: =INDEX(NakshatraTbl,INT(B58*0.075)+1,3) -> Venus | E58: =INDEX(RsTbl,F58) -> Le | F58: =INT(B58/30)+1 -> 5 | G58: =INT(MOD(FLOOR(MOD(B58,30)/10,1)*120+B58,360)/30)+1 -> 9 | H58: =INDEX(RsTbl,G58) -> Sg | I58: =INT(MOD(FLOOR(MOD(B58,30)/7.5,1)*90+B58,360)/30)+1 -> 11 | J58: =INDEX(RsTbl,I58) -> Aq | K58: =INT(MOD(B58*7,360)/30)+1 -> 8 | L58: =INDEX(RsTbl,K58) -> Sc | M58: =INT(MOD(B58*9,360)/30)+1 -> 6 | N58: =INDEX(RsTbl,M58) -> Vi | O58: =INT(MOD(B58*10+INT(B58/30)*30+MOD(INT(B58/30),2)*270,360)/30)+1 -> 2 | P58: =INDEX(RsTbl,O58) -> Ta | Q58: =INT(MOD((MOD(B58,30)/2.5)*30+INT(B58/30)*30,360)/30)+1 -> 11 | R58: =INDEX(RsTbl,Q58) -> Aq | S58: =(IF(MOD(F58,2),1,-1)*ROUNDUP(F58/2,0)) -> 3
A59: Sun | B59: =Sun -> 92.399203 | C59: =INDEX(NakshatraTbl,INT(B59*0.075)+1,1) -> Punarvasu | D59: =INDEX(NakshatraTbl,INT(B59*0.075)+1,3) -> Jupiter | E59: =INDEX(RsTbl,F59) -> Cn | F59: =INT(B59/30)+1 -> 4 | G59: =INT(MOD(FLOOR(MOD(B59,30)/10,1)*120+B59,360)/30)+1 -> 4 | H59: =INDEX(RsTbl,G59) -> Cn | I59: =INT(MOD(FLOOR(MOD(B59,30)/7.5,1)*90+B59,360)/30)+1 -> 4 | J59: =INDEX(RsTbl,I59) -> Cn | K59: =INT(MOD(B59*7,360)/30)+1 -> 10 | L59: =INDEX(RsTbl,K59) -> Cp | M59: =INT(MOD(B59*9,360)/30)+1 -> 4 | N59: =INDEX(RsTbl,M59) -> Cn | O59: =INT(MOD(B59*10+INT(B59/30)*30+MOD(INT(B59/30),2)*270,360)/30)+1 -> 7 | P59: =INDEX(RsTbl,O59) -> Li | Q59: =INT(MOD((MOD(B59,30)/2.5)*30+INT(B59/30)*30,360)/30)+1 -> 4 | R59: =INDEX(RsTbl,Q59) -> Cn | S59: =(IF(MOD(F59,2),1,-1)*ROUNDUP(F59/2,0)) -> -2
A60: Moon | B60: =Moon -> 53.015944 | C60: =INDEX(NakshatraTbl,INT(B60*0.075)+1,1) -> Rohini | D60: =INDEX(NakshatraTbl,INT(B60*0.075)+1,3) -> Moon | E60: =INDEX(RsTbl,F60) -> Ta | F60: =INT(B60/30)+1 -> 2 | G60: =INT(MOD(FLOOR(MOD(B60,30)/10,1)*120+B60,360)/30)+1 -> 10 | H60: =INDEX(RsTbl,G60) -> Cp | I60: =INT(MOD(FLOOR(MOD(B60,30)/7.5,1)*90+B60,360)/30)+1 -> 11 | J60: =INDEX(RsTbl,I60) -> Aq | K60: =INT(MOD(B60*7,360)/30)+1 -> 1 | L60: =INDEX(RsTbl,K60) -> Ar | M60: =INT(MOD(B60*9,360)/30)+1 -> 4 | N60: =INDEX(RsTbl,M60) -> Cn | O60: =INT(MOD(B60*10+INT(B60/30)*30+MOD(INT(B60/30),2)*270,360)/30)+1 -> 4 | P60: =INDEX(RsTbl,O60) -> Cn | Q60: =INT(MOD((MOD(B60,30)/2.5)*30+INT(B60/30)*30,360)/30)+1 -> 11 | R60: =INDEX(RsTbl,Q60) -> Aq | S60: =(IF(MOD(F60,2),1,-1)*ROUNDUP(F60/2,0)) -> -1
A61: Mars | B61: =Mars -> 298.10866 | C61: =INDEX(NakshatraTbl,INT(B61*0.075)+1,1) -> Shravan | D61: =INDEX(NakshatraTbl,INT(B61*0.075)+1,3) -> Moon | E61: =INDEX(RsTbl,F61) -> Cp | F61: =INT(B61/30)+1 -> 10 | G61: =INT(MOD(FLOOR(MOD(B61,30)/10,1)*120+B61,360)/30)+1 -> 6 | H61: =INDEX(RsTbl,G61) -> Vi | I61: =INT(MOD(FLOOR(MOD(B61,30)/7.5,1)*90+B61,360)/30)+1 -> 7 | J61: =INDEX(RsTbl,I61) -> Li | K61: =INT(MOD(B61*7,360)/30)+1 -> 10 | L61: =INDEX(RsTbl,K61) -> Cp | M61: =INT(MOD(B61*9,360)/30)+1 -> 6 | N61: =INDEX(RsTbl,M61) -> Vi | O61: =INT(MOD(B61*10+INT(B61/30)*30+MOD(INT(B61/30),2)*270,360)/30)+1 -> 10 | P61: =INDEX(RsTbl,O61) -> Cp | Q61: =INT(MOD((MOD(B61,30)/2.5)*30+INT(B61/30)*30,360)/30)+1 -> 9 | R61: =INDEX(RsTbl,Q61) -> Sg | S61: =(IF(MOD(F61,2),1,-1)*ROUNDUP(F61/2,0)) -> -5
A62: Mercury | B62: =Mercury -> 117.12979 | C62: =INDEX(NakshatraTbl,INT(B62*0.075)+1,1) -> Ashlesha | D62: =INDEX(NakshatraTbl,INT(B62*0.075)+1,3) -> Merc | E62: =INDEX(RsTbl,F62) -> Cn | F62: =INT(B62/30)+1 -> 4 | G62: =INT(MOD(FLOOR(MOD(B62,30)/10,1)*120+B62,360)/30)+1 -> 12 | H62: =INDEX(RsTbl,G62) -> Pi | I62: =INT(MOD(FLOOR(MOD(B62,30)/7.5,1)*90+B62,360)/30)+1 -> 1 | J62: =INDEX(RsTbl,I62) -> Ar | K62: =INT(MOD(B62*7,360)/30)+1 -> 4 | L62: =INDEX(RsTbl,K62) -> Cn | M62: =INT(MOD(B62*9,360)/30)+1 -> 12 | N62: =INDEX(RsTbl,M62) -> Pi | O62: =INT(MOD(B62*10+INT(B62/30)*30+MOD(INT(B62/30),2)*270,360)/30)+1 -> 4 | P62: =INDEX(RsTbl,O62) -> Cn | Q62: =INT(MOD((MOD(B62,30)/2.5)*30+INT(B62/30)*30,360)/30)+1 -> 2 | R62: =INDEX(RsTbl,Q62) -> Ta | S62: =(IF(MOD(F62,2),1,-1)*ROUNDUP(F62/2,0)) -> -2
A63: Jupiter | B63: =Jupiter -> 213.19717 | C63: =INDEX(NakshatraTbl,INT(B63*0.075)+1,1) -> Vishakha | D63: =INDEX(NakshatraTbl,INT(B63*0.075)+1,3) -> Jupiter | E63: =INDEX(RsTbl,F63) -> Sc | F63: =INT(B63/30)+1 -> 8 | G63: =INT(MOD(FLOOR(MOD(B63,30)/10,1)*120+B63,360)/30)+1 -> 8 | H63: =INDEX(RsTbl,G63) -> Sc | I63: =INT(MOD(FLOOR(MOD(B63,30)/7.5,1)*90+B63,360)/30)+1 -> 8 | J63: =INDEX(RsTbl,I63) -> Sc | K63: =INT(MOD(B63*7,360)/30)+1 -> 2 | L63: =INDEX(RsTbl,K63) -> Ta | M63: =INT(MOD(B63*9,360)/30)+1 -> 4 | N63: =INDEX(RsTbl,M63) -> Cn | O63: =INT(MOD(B63*10+INT(B63/30)*30+MOD(INT(B63/30),2)*270,360)/30)+1 -> 4 | P63: =INDEX(RsTbl,O63) -> Cn | Q63: =INT(MOD((MOD(B63,30)/2.5)*30+INT(B63/30)*30,360)/30)+1 -> 9 | R63: =INDEX(RsTbl,Q63) -> Sg | S63: =(IF(MOD(F63,2),1,-1)*ROUNDUP(F63/2,0)) -> -4
A64: Venus | B64: =Venus -> 81.540603 | C64: =INDEX(NakshatraTbl,INT(B64*0.075)+1,1) -> Punarvasu | D64: =INDEX(NakshatraTbl,INT(B64*0.075)+1,3) -> Jupiter | E64: =INDEX(RsTbl,F64) -> Ge | F64: =INT(B64/30)+1 -> 3 | G64: =INT(MOD(FLOOR(MOD(B64,30)/10,1)*120+B64,360)/30)+1 -> 11 | H64: =INDEX(RsTbl,G64) -> Aq | I64: =INT(MOD(FLOOR(MOD(B64,30)/7.5,1)*90+B64,360)/30)+1 -> 9 | J64: =INDEX(RsTbl,I64) -> Sg | K64: =INT(MOD(B64*7,360)/30)+1 -> 8 | L64: =INDEX(RsTbl,K64) -> Sc | M64: =INT(MOD(B64*9,360)/30)+1 -> 1 | N64: =INDEX(RsTbl,M64) -> Ar | O64: =INT(MOD(B64*10+INT(B64/30)*30+MOD(INT(B64/30),2)*270,360)/30)+1 -> 6 | P64: =INDEX(RsTbl,O64) -> Vi | Q64: =INT(MOD((MOD(B64,30)/2.5)*30+INT(B64/30)*30,360)/30)+1 -> 11 | R64: =INDEX(RsTbl,Q64) -> Aq | S64: =(IF(MOD(F64,2),1,-1)*ROUNDUP(F64/2,0)) -> 2
A65: Saturn | B65: =Saturn -> 39.885211 | C65: =INDEX(NakshatraTbl,INT(B65*0.075)+1,1) -> Kritika | D65: =INDEX(NakshatraTbl,INT(B65*0.075)+1,3) -> Sun | E65: =INDEX(RsTbl,F65) -> Ta | F65: =INT(B65/30)+1 -> 2 | G65: =INT(MOD(FLOOR(MOD(B65,30)/10,1)*120+B65,360)/30)+1 -> 2 | H65: =INDEX(RsTbl,G65) -> Ta | I65: =INT(MOD(FLOOR(MOD(B65,30)/7.5,1)*90+B65,360)/30)+1 -> 5 | J65: =INDEX(RsTbl,I65) -> Le | K65: =INT(MOD(B65*7,360)/30)+1 -> 10 | L65: =INDEX(RsTbl,K65) -> Cp | M65: =INT(MOD(B65*9,360)/30)+1 -> 12 | N65: =INDEX(RsTbl,M65) -> Pi | O65: =INT(MOD(B65*10+INT(B65/30)*30+MOD(INT(B65/30),2)*270,360)/30)+1 -> 12 | P65: =INDEX(RsTbl,O65) -> Pi | Q65: =INT(MOD((MOD(B65,30)/2.5)*30+INT(B65/30)*30,360)/30)+1 -> 5 | R65: =INDEX(RsTbl,Q65) -> Le | S65: =(IF(MOD(F65,2),1,-1)*ROUNDUP(F65/2,0)) -> -1
A66: Rahu | B66: =Rahu -> 291.96724 | C66: =INDEX(NakshatraTbl,INT(B66*0.075)+1,1) -> Abhijit | D66: =INDEX(NakshatraTbl,INT(B66*0.075)+1,3) -> Sun | E66: =INDEX(RsTbl,F66) -> Cp | F66: =INT(B66/30)+1 -> 10 | G66: =INT(MOD(FLOOR(MOD(B66,30)/10,1)*120+B66,360)/30)+1 -> 6 | H66: =INDEX(RsTbl,G66) -> Vi | I66: =INT(MOD(FLOOR(MOD(B66,30)/7.5,1)*90+B66,360)/30)+1 -> 4 | J66: =INDEX(RsTbl,I66) -> Cn | K66: =INT(MOD(B66*7,360)/30)+1 -> 9 | L66: =INDEX(RsTbl,K66) -> Sg | M66: =INT(MOD(B66*9,360)/30)+1 -> 4 | N66: =INDEX(RsTbl,M66) -> Cn | O66: =INT(MOD(B66*10+INT(B66/30)*30+MOD(INT(B66/30),2)*270,360)/30)+1 -> 8 | P66: =INDEX(RsTbl,O66) -> Sc | Q66: =INT(MOD((MOD(B66,30)/2.5)*30+INT(B66/30)*30,360)/30)+1 -> 6 | R66: =INDEX(RsTbl,Q66) -> Vi | S66: =(IF(MOD(F66,2),1,-1)*ROUNDUP(F66/2,0)) -> -5
A67: Ketu | B67: =Ketu -> 111.96724 | C67: =INDEX(NakshatraTbl,INT(B67*0.075)+1,1) -> Ashlesha | D67: =INDEX(NakshatraTbl,INT(B67*0.075)+1,3) -> Merc | E67: =INDEX(RsTbl,F67) -> Cn | F67: =INT(B67/30)+1 -> 4 | G67: =INT(MOD(FLOOR(MOD(B67,30)/10,1)*120+B67,360)/30)+1 -> 12 | H67: =INDEX(RsTbl,G67) -> Pi | I67: =INT(MOD(FLOOR(MOD(B67,30)/7.5,1)*90+B67,360)/30)+1 -> 10 | J67: =INDEX(RsTbl,I67) -> Cp | K67: =INT(MOD(B67*7,360)/30)+1 -> 3 | L67: =INDEX(RsTbl,K67) -> Ge | M67: =INT(MOD(B67*9,360)/30)+1 -> 10 | N67: =INDEX(RsTbl,M67) -> Cp | O67: =INT(MOD(B67*10+INT(B67/30)*30+MOD(INT(B67/30),2)*270,360)/30)+1 -> 2 | P67: =INDEX(RsTbl,O67) -> Ta | Q67: =INT(MOD((MOD(B67,30)/2.5)*30+INT(B67/30)*30,360)/30)+1 -> 12 | R67: =INDEX(RsTbl,Q67) -> Pi | S67: =(IF(MOD(F67,2),1,-1)*ROUNDUP(F67/2,0)) -> -2
A68: VL | B68: =Basics!G32 -> 354.18438 | C68: =INDEX(NakshatraTbl,INT(B68*0.075)+1,1) -> Uttara Bhadrapad | D68: =INDEX(NakshatraTbl,INT(B68*0.075)+1,3) -> Sat | E68: =INDEX(RsTbl,F68) -> Pi | F68: =INT(B68/30)+1 -> 12 | G68: =INT(MOD(FLOOR(MOD(B68,30)/10,1)*120+B68,360)/30)+1 -> 8 | H68: =INDEX(RsTbl,G68) -> Sc | I68: =INT(MOD(FLOOR(MOD(B68,30)/7.5,1)*90+B68,360)/30)+1 -> 9 | J68: =INDEX(RsTbl,I68) -> Sg | K68: =INT(MOD(B68*7,360)/30)+1 -> 11 | L68: =INDEX(RsTbl,K68) -> Aq | M68: =INT(MOD(B68*9,360)/30)+1 -> 11 | N68: =INDEX(RsTbl,M68) -> Aq | O68: =INT(MOD(B68*10+INT(B68/30)*30+MOD(INT(B68/30),2)*270,360)/30)+1 -> 7 | P68: =INDEX(RsTbl,O68) -> Li | Q68: =INT(MOD((MOD(B68,30)/2.5)*30+INT(B68/30)*30,360)/30)+1 -> 9 | R68: =INDEX(RsTbl,Q68) -> Sg | S68: =(IF(MOD(F68,2),1,-1)*ROUNDUP(F68/2,0)) -> -6
F70: =IF((M67-1)=11,$A$67&"/ ","")&IF((M60-1)=11,$A$60&"/ ","")&IF((M58-1)=11,$A$58&"/ ","")&IF((M59-1)=11,$A$59&"/ ","")&IF((M66-1)=11,$A$66&"/ ","")&IF((M61-1)=11,$A$61&"/ ","")&IF((M65-1)=11,$A$65&"/ ","")&IF((M62-1)=11,$A$62&"/ ","")&IF((M63-1)=11,$A$63&"/ ","")&IF((M64-1)=11,$A$64&"/ ","") -> Saturn/ Mercury/ | G70: =IF((M67-1)=0,$A$67&"/ ","")&IF((M60-1)=0,$A$60&"/ ","")&IF((M58-1)=0,$A$58&"/ ","")&IF((M59-1)=0,$A$59&"/ ","")&IF((M66-1)=0,$A$66&"/ ","")&IF((M61-1)=0,$A$61&"/ ","")&IF((M65-1)=0,$A$65&"/ ","")&IF((M62-1)=0,$A$62&"/ ","")&IF((M63-1)=0,$A$63&"/ ","")&IF((M64-1)=0,$A$64&"/ ","") -> Venus/ | H70: =IF((M67-1)=1,$A$67&"/ ","")&IF((M60-1)=1,$A$60&"/ ","")&IF((M58-1)=1,$A$58&"/ ","")&IF((M59-1)=1,$A$59&"/ ","")&IF((M66-1)=1,$A$66&"/ ","")&IF((M61-1)=1,$A$61&"/ ","")&IF((M65-1)=1,$A$65&"/ ","")&IF((M62-1)=1,$A$62&"/ ","")&IF((M63-1)=1,$A$63&"/ ","")&IF((M64-1)=1,$A$64&"/ ","") | I70: =IF((M67-1)=2,$A$67&"/ ","")&IF((M60-1)=2,$A$60&"/ ","")&IF((M58-1)=2,$A$58&"/ ","")&IF((M59-1)=2,$A$59&"/ ","")&IF((M66-1)=2,$A$66&"/ ","")&IF((M61-1)=2,$A$61&"/ ","")&IF((M65-1)=2,$A$65&"/ ","")&IF((M62-1)=2,$A$62&"/ ","")&IF((M63-1)=2,$A$63&"/ ","")&IF((M64-1)=2,$A$64&"/ ","") | K70: =IF((G67-1)=11,$A$67&"/ ","")&IF((G60-1)=11,$A$60&"/ ","")&IF((G58-1)=11,$A$58&"/ ","")&IF((G59-1)=11,$A$59&"/ ","")&IF((G66-1)=11,$A$66&"/ ","")&IF((G61-1)=11,$A$61&"/ ","")&IF((G65-1)=11,$A$65&"/ ","")&IF((G62-1)=11,$A$62&"/ ","")&IF((G63-1)=11,$A$63&"/ ","")&IF((G64-1)=11,$A$64&"/ ","") -> Ketu/ Mercury/ | L70: =IF((G67-1)=0,$A$67&"/ ","")&IF((G60-1)=0,$A$60&"/ ","")&IF((G58-1)=0,$A$58&"/ ","")&IF((G59-1)=0,$A$59&"/ ","")&IF((G66-1)=0,$A$66&"/ ","")&IF((G61-1)=0,$A$61&"/ ","")&IF((G65-1)=0,$A$65&"/ ","")&IF((G62-1)=0,$A$62&"/ ","")&IF((G63-1)=0,$A$63&"/ ","")&IF((G64-1)=0,$A$64&"/ ","") | M70: =IF((G67-1)=1,$A$67&"/ ","")&IF((G60-1)=1,$A$60&"/ ","")&IF((G58-1)=1,$A$58&"/ ","")&IF((G59-1)=1,$A$59&"/ ","")&IF((G66-1)=1,$A$66&"/ ","")&IF((G61-1)=1,$A$61&"/ ","")&IF((G65-1)=1,$A$65&"/ ","")&IF((G62-1)=1,$A$62&"/ ","")&IF((G63-1)=1,$A$63&"/ ","")&IF((G64-1)=1,$A$64&"/ ","") -> Saturn/ | N70: =IF((G67-1)=2,$A$67&"/ ","")&IF((G60-1)=2,$A$60&"/ ","")&IF((G58-1)=2,$A$58&"/ ","")&IF((G59-1)=2,$A$59&"/ ","")&IF((G66-1)=2,$A$66&"/ ","")&IF((G61-1)=2,$A$61&"/ ","")&IF((G65-1)=2,$A$65&"/ ","")&IF((G62-1)=2,$A$62&"/ ","")&IF((G63-1)=2,$A$63&"/ ","")&IF((G64-1)=2,$A$64&"/ ","") | T70: =Charts!J2 -> Moon/ Saturn/ | U70: =Charts!I2 | V70: =Charts!H2
F71: =IF((M67-1)=10,$A$67&"/ ","")&IF((M60-1)=10,$A$60&"/ ","")&IF((M58-1)=10,$A$58&"/ ","")&IF((M59-1)=10,$A$59&"/ ","")&IF((M66-1)=10,$A$66&"/ ","")&IF((M61-1)=10,$A$61&"/ ","")&IF((M65-1)=10,$A$65&"/ ","")&IF((M62-1)=10,$A$62&"/ ","")&IF((M63-1)=10,$A$63&"/ ","")&IF((M64-1)=10,$A$64&"/ ","") | G71: Navamsa | I71: =IF((M67-1)=3,$A$67&"/ ","")&IF((M60-1)=3,$A$60&"/ ","")&IF((M58-1)=3,$A$58&"/ ","")&IF((M59-1)=3,$A$59&"/ ","")&IF((M66-1)=3,$A$66&"/ ","")&IF((M61-1)=3,$A$61&"/ ","")&IF((M65-1)=3,$A$65&"/ ","")&IF((M62-1)=3,$A$62&"/ ","")&IF((M63-1)=3,$A$63&"/ ","")&IF((M64-1)=3,$A$64&"/ ","") -> Moon/ Sun/ Rahu/ Jupiter/ | K71: =IF((G67-1)=10,$A$67&"/ ","")&IF((G60-1)=10,$A$60&"/ ","")&IF((G58-1)=10,$A$58&"/ ","")&IF((G59-1)=10,$A$59&"/ ","")&IF((G66-1)=10,$A$66&"/ ","")&IF((G61-1)=10,$A$61&"/ ","")&IF((G65-1)=10,$A$65&"/ ","")&IF((G62-1)=10,$A$62&"/ ","")&IF((G63-1)=10,$A$63&"/ ","")&IF((G64-1)=10,$A$64&"/ ","") -> Venus/ | L71: Drekkana | N71: =IF((G67-1)=3,$A$67&"/ ","")&IF((G60-1)=3,$A$60&"/ ","")&IF((G58-1)=3,$A$58&"/ ","")&IF((G59-1)=3,$A$59&"/ ","")&IF((G66-1)=3,$A$66&"/ ","")&IF((G61-1)=3,$A$61&"/ ","")&IF((G65-1)=3,$A$65&"/ ","")&IF((G62-1)=3,$A$62&"/ ","")&IF((G63-1)=3,$A$63&"/ ","")&IF((G64-1)=3,$A$64&"/ ","") -> Sun/ | S71: =Charts!K2 -> Venus/ | W71: =Charts!H3
F72: =IF((M67-1)=9,$A$67&"/ ","")&IF((M60-1)=9,$A$60&"/ ","")&IF((M58-1)=9,$A$58&"/ ","")&IF((M59-1)=9,$A$59&"/ ","")&IF((M66-1)=9,$A$66&"/ ","")&IF((M61-1)=9,$A$61&"/ ","")&IF((M65-1)=9,$A$65&"/ ","")&IF((M62-1)=9,$A$62&"/ ","")&IF((M63-1)=9,$A$63&"/ ","")&IF((M64-1)=9,$A$64&"/ ","") -> Ketu/ | H72: D9 | I72: =IF((M67-1)=4,$A$67&"/ ","")&IF((M60-1)=4,$A$60&"/ ","")&IF((M58-1)=4,$A$58&"/ ","")&IF((M59-1)=4,$A$59&"/ ","")&IF((M66-1)=4,$A$66&"/ ","")&IF((M61-1)=4,$A$61&"/ ","")&IF((M65-1)=4,$A$65&"/ ","")&IF((M62-1)=4,$A$62&"/ ","")&IF((M63-1)=4,$A$63&"/ ","")&IF((M64-1)=4,$A$64&"/ ","") | K72: =IF((G67-1)=9,$A$67&"/ ","")&IF((G60-1)=9,$A$60&"/ ","")&IF((G58-1)=9,$A$58&"/ ","")&IF((G59-1)=9,$A$59&"/ ","")&IF((G66-1)=9,$A$66&"/ ","")&IF((G61-1)=9,$A$61&"/ ","")&IF((G65-1)=9,$A$65&"/ ","")&IF((G62-1)=9,$A$62&"/ ","")&IF((G63-1)=9,$A$63&"/ ","")&IF((G64-1)=9,$A$64&"/ ","") -> Moon/ | M72: =G57 -> D3# | N72: =IF((G67-1)=4,$A$67&"/ ","")&IF((G60-1)=4,$A$60&"/ ","")&IF((G58-1)=4,$A$58&"/ ","")&IF((G59-1)=4,$A$59&"/ ","")&IF((G66-1)=4,$A$66&"/ ","")&IF((G61-1)=4,$A$61&"/ ","")&IF((G65-1)=4,$A$65&"/ ","")&IF((G62-1)=4,$A$62&"/ ","")&IF((G63-1)=4,$A$63&"/ ","")&IF((G64-1)=4,$A$64&"/ ","") | S72: =Charts!K3 -> Ketu/ Sun/ Mercury/ | U72: =Charts!I3 -> RASI CHART | W72: =Charts!H4 -> Rahu/ Mars/
F73: =IF((M67-1)=8,$A$67&"/ ","")&IF((M60-1)=8,$A$60&"/ ","")&IF((M58-1)=8,$A$58&"/ ","")&IF((M59-1)=8,$A$59&"/ ","")&IF((M66-1)=8,$A$66&"/ ","")&IF((M61-1)=8,$A$61&"/ ","")&IF((M65-1)=8,$A$65&"/ ","")&IF((M62-1)=8,$A$62&"/ ","")&IF((M63-1)=8,$A$63&"/ ","")&IF((M64-1)=8,$A$64&"/ ","") | G73: =IF((M67-1)=7,$A$67&"/ ","")&IF((M60-1)=7,$A$60&"/ ","")&IF((M58-1)=7,$A$58&"/ ","")&IF((M59-1)=7,$A$59&"/ ","")&IF((M66-1)=7,$A$66&"/ ","")&IF((M61-1)=7,$A$61&"/ ","")&IF((M65-1)=7,$A$65&"/ ","")&IF((M62-1)=7,$A$62&"/ ","")&IF((M63-1)=7,$A$63&"/ ","")&IF((M64-1)=7,$A$64&"/ ","") | H73: =IF((M67-1)=6,$A$67&"/ ","")&IF((M60-1)=6,$A$60&"/ ","")&IF((M58-1)=6,$A$58&"/ ","")&IF((M59-1)=6,$A$59&"/ ","")&IF((M66-1)=6,$A$66&"/ ","")&IF((M61-1)=6,$A$61&"/ ","")&IF((M65-1)=6,$A$65&"/ ","")&IF((M62-1)=6,$A$62&"/ ","")&IF((M63-1)=6,$A$63&"/ ","")&IF((M64-1)=6,$A$64&"/ ","") | I73: =IF((M67-1)=5,$A$67&"/ ","")&IF((M60-1)=5,$A$60&"/ ","")&IF((M58-1)=5,$A$58&"/ ","")&IF((M59-1)=5,$A$59&"/ ","")&IF((M66-1)=5,$A$66&"/ ","")&IF((M61-1)=5,$A$61&"/ ","")&IF((M65-1)=5,$A$65&"/ ","")&IF((M62-1)=5,$A$62&"/ ","")&IF((M63-1)=5,$A$63&"/ ","")&IF((M64-1)=5,$A$64&"/ ","") -> Asc/ Mars/ | K73: =IF((G67-1)=8,$A$67&"/ ","")&IF((G60-1)=8,$A$60&"/ ","")&IF((G58-1)=8,$A$58&"/ ","")&IF((G59-1)=8,$A$59&"/ ","")&IF((G66-1)=8,$A$66&"/ ","")&IF((G61-1)=8,$A$61&"/ ","")&IF((G65-1)=8,$A$65&"/ ","")&IF((G62-1)=8,$A$62&"/ ","")&IF((G63-1)=8,$A$63&"/ ","")&IF((G64-1)=8,$A$64&"/ ","") -> Asc/ | L73: =IF((G67-1)=7,$A$67&"/ ","")&IF((G60-1)=7,$A$60&"/ ","")&IF((G58-1)=7,$A$58&"/ ","")&IF((G59-1)=7,$A$59&"/ ","")&IF((G66-1)=7,$A$66&"/ ","")&IF((G61-1)=7,$A$61&"/ ","")&IF((G65-1)=7,$A$65&"/ ","")&IF((G62-1)=7,$A$62&"/ ","")&IF((G63-1)=7,$A$63&"/ ","")&IF((G64-1)=7,$A$64&"/ ","") -> Jupiter/ | M73: =IF((G67-1)=6,$A$67&"/ ","")&IF((G60-1)=6,$A$60&"/ ","")&IF((G58-1)=6,$A$58&"/ ","")&IF((G59-1)=6,$A$59&"/ ","")&IF((G66-1)=6,$A$66&"/ ","")&IF((G61-1)=6,$A$61&"/ ","")&IF((G65-1)=6,$A$65&"/ ","")&IF((G62-1)=6,$A$62&"/ ","")&IF((G63-1)=6,$A$63&"/ ","")&IF((G64-1)=6,$A$64&"/ ","") | N73: =IF((G67-1)=5,$A$67&"/ ","")&IF((G60-1)=5,$A$60&"/ ","")&IF((G58-1)=5,$A$58&"/ ","")&IF((G59-1)=5,$A$59&"/ ","")&IF((G66-1)=5,$A$66&"/ ","")&IF((G61-1)=5,$A$61&"/ ","")&IF((G65-1)=5,$A$65&"/ ","")&IF((G62-1)=5,$A$62&"/ ","")&IF((G63-1)=5,$A$63&"/ ","")&IF((G64-1)=5,$A$64&"/ ","") -> Rahu/ Mars/ | S73: =Charts!K4 -> Asc/ | W73: =Charts!H5
W74: =Charts!K5 | X74: =Charts!J5 | Y74: =Charts!I5 -> Jupiter/
D75: =IF((O67-1)=11,$A$67&"/ ","")&IF((O60-1)=11,$A$60&"/ ","")&IF((O58-1)=11,$A$58&"/ ","")&IF((O59-1)=11,$A$59&"/ ","")&IF((O66-1)=11,$A$66&"/ ","")&IF((O61-1)=11,$A$61&"/ ","")&IF((O65-1)=11,$A$65&"/ ","")&IF((O62-1)=11,$A$62&"/ ","")&IF((O63-1)=11,$A$63&"/ ","")&IF((O64-1)=11,$A$64&"/ ","") -> Saturn/ | E75: =IF((O67-1)=0,$A$67&"/ ","")&IF((O60-1)=0,$A$60&"/ ","")&IF((O58-1)=0,$A$58&"/ ","")&IF((O59-1)=0,$A$59&"/ ","")&IF((O66-1)=0,$A$66&"/ ","")&IF((O61-1)=0,$A$61&"/ ","")&IF((O65-1)=0,$A$65&"/ ","")&IF((O62-1)=0,$A$62&"/ ","")&IF((O63-1)=0,$A$63&"/ ","")&IF((O64-1)=0,$A$64&"/ ","") | F75: =IF((O67-1)=1,$A$67&"/ ","")&IF((O60-1)=1,$A$60&"/ ","")&IF((O58-1)=1,$A$58&"/ ","")&IF((O59-1)=1,$A$59&"/ ","")&IF((O66-1)=1,$A$66&"/ ","")&IF((O61-1)=1,$A$61&"/ ","")&IF((O65-1)=1,$A$65&"/ ","")&IF((O62-1)=1,$A$62&"/ ","")&IF((O63-1)=1,$A$63&"/ ","")&IF((O64-1)=1,$A$64&"/ ","") -> Ketu/ Asc/ | G75: =IF((O67-1)=2,$A$67&"/ ","")&IF((O60-1)=2,$A$60&"/ ","")&IF((O58-1)=2,$A$58&"/ ","")&IF((O59-1)=2,$A$59&"/ ","")&IF((O66-1)=2,$A$66&"/ ","")&IF((O61-1)=2,$A$61&"/ ","")&IF((O65-1)=2,$A$65&"/ ","")&IF((O62-1)=2,$A$62&"/ ","")&IF((O63-1)=2,$A$63&"/ ","")&IF((O64-1)=2,$A$64&"/ ","")
D76: =IF((O67-1)=10,$A$67&"/ ","")&IF((O60-1)=10,$A$60&"/ ","")&IF((O58-1)=10,$A$58&"/ ","")&IF((O59-1)=10,$A$59&"/ ","")&IF((O66-1)=10,$A$66&"/ ","")&IF((O61-1)=10,$A$61&"/ ","")&IF((O65-1)=10,$A$65&"/ ","")&IF((O62-1)=10,$A$62&"/ ","")&IF((O63-1)=10,$A$63&"/ ","")&IF((O64-1)=10,$A$64&"/ ","") | E76: Drekkana | G76: =IF((O67-1)=3,$A$67&"/ ","")&IF((O60-1)=3,$A$60&"/ ","")&IF((O58-1)=3,$A$58&"/ ","")&IF((O59-1)=3,$A$59&"/ ","")&IF((O66-1)=3,$A$66&"/ ","")&IF((O61-1)=3,$A$61&"/ ","")&IF((O65-1)=3,$A$65&"/ ","")&IF((O62-1)=3,$A$62&"/ ","")&IF((O63-1)=3,$A$63&"/ ","")&IF((O64-1)=3,$A$64&"/ ","") -> Moon/ Mercury/ Jupiter/
D77: =IF((O67-1)=9,$A$67&"/ ","")&IF((O60-1)=9,$A$60&"/ ","")&IF((O58-1)=9,$A$58&"/ ","")&IF((O59-1)=9,$A$59&"/ ","")&IF((O66-1)=9,$A$66&"/ ","")&IF((O61-1)=9,$A$61&"/ ","")&IF((O65-1)=9,$A$65&"/ ","")&IF((O62-1)=9,$A$62&"/ ","")&IF((O63-1)=9,$A$63&"/ ","")&IF((O64-1)=9,$A$64&"/ ","") -> Mars/ | F77: =O57 -> D10# | G77: =IF((O67-1)=4,$A$67&"/ ","")&IF((O60-1)=4,$A$60&"/ ","")&IF((O58-1)=4,$A$58&"/ ","")&IF((O59-1)=4,$A$59&"/ ","")&IF((O66-1)=4,$A$66&"/ ","")&IF((O61-1)=4,$A$61&"/ ","")&IF((O65-1)=4,$A$65&"/ ","")&IF((O62-1)=4,$A$62&"/ ","")&IF((O63-1)=4,$A$63&"/ ","")&IF((O64-1)=4,$A$64&"/ ","")
D78: =IF((O67-1)=8,$A$67&"/ ","")&IF((O60-1)=8,$A$60&"/ ","")&IF((O58-1)=8,$A$58&"/ ","")&IF((O59-1)=8,$A$59&"/ ","")&IF((O66-1)=8,$A$66&"/ ","")&IF((O61-1)=8,$A$61&"/ ","")&IF((O65-1)=8,$A$65&"/ ","")&IF((O62-1)=8,$A$62&"/ ","")&IF((O63-1)=8,$A$63&"/ ","")&IF((O64-1)=8,$A$64&"/ ","") | E78: =IF((O67-1)=7,$A$67&"/ ","")&IF((O60-1)=7,$A$60&"/ ","")&IF((O58-1)=7,$A$58&"/ ","")&IF((O59-1)=7,$A$59&"/ ","")&IF((O66-1)=7,$A$66&"/ ","")&IF((O61-1)=7,$A$61&"/ ","")&IF((O65-1)=7,$A$65&"/ ","")&IF((O62-1)=7,$A$62&"/ ","")&IF((O63-1)=7,$A$63&"/ ","")&IF((O64-1)=7,$A$64&"/ ","") -> Rahu/ | F78: =IF((O67-1)=6,$A$67&"/ ","")&IF((O60-1)=6,$A$60&"/ ","")&IF((O58-1)=6,$A$58&"/ ","")&IF((O59-1)=6,$A$59&"/ ","")&IF((O66-1)=6,$A$66&"/ ","")&IF((O61-1)=6,$A$61&"/ ","")&IF((O65-1)=6,$A$65&"/ ","")&IF((O62-1)=6,$A$62&"/ ","")&IF((O63-1)=6,$A$63&"/ ","")&IF((O64-1)=6,$A$64&"/ ","") -> Sun/ | G78: =IF((O67-1)=5,$A$67&"/ ","")&IF((O60-1)=5,$A$60&"/ ","")&IF((O58-1)=5,$A$58&"/ ","")&IF((O59-1)=5,$A$59&"/ ","")&IF((O66-1)=5,$A$66&"/ ","")&IF((O61-1)=5,$A$61&"/ ","")&IF((O65-1)=5,$A$65&"/ ","")&IF((O62-1)=5,$A$62&"/ ","")&IF((O63-1)=5,$A$63&"/ ","")&IF((O64-1)=5,$A$64&"/ ","") -> Venus/

Sheet Charts
A1: {={1,2,3}} -> 1 | B1: 2 | C1: 3
B2: * * * | C2: =J2 -> Moon/ Saturn/ | D2: =I2 | E2: =H2 | F2: * * * | H2: =IF(TRUNC(Basics!B67/30)=11,Basics!$A$67&"/ ","")&IF(TRUNC(Basics!B60/30)=11,Basics!$A$60&"/ ","")&IF(TRUNC(Basics!B58/30)=11,Basics!$A$58&"/ ","")&IF(TRUNC(Basics!B59/30)=11,Basics!$A$59&"/ ","")&IF(TRUNC(Basics!B66/30)=11,Basics!$A$66&"/ ","")&IF(TRUNC(Basics!B61/30)=11,Basics!$A$61&"/ ","")&IF(TRUNC(Basics!B65/30)=11,Basics!$A$65&"/ ","")&IF(TRUNC(Basics!B62/30)=11,Basics!$A$62&"/ ","")&IF(TRUNC(Basics!B63/30)=11,Basics!$A$63&"/ ","")&IF(TRUNC(Basics!B64/30)=11,Basics!$A$64&"/ ","") | I2: =IF(TRUNC(Basics!B67/30)=0,Basics!$A$67&"/ ","")&IF(TRUNC(Basics!B60/30)=0,Basics!$A$60&"/ ","")&IF(TRUNC(Basics!B58/30)=0,Basics!$A$58&"/ ","")&IF(TRUNC(Basics!B59/30)=0,Basics!$A$59&"/ ","")&IF(TRUNC(Basics!B66/30)=0,Basics!$A$66&"/ ","")&IF(TRUNC(Basics!B61/30)=0,Basics!$A$61&"/ ","")&IF(TRUNC(Basics!B65/30)=0,Basics!$A$65&"/ ","")&IF(TRUNC(Basics!B62/30)=0,Basics!$A$62&"/ ","")&IF(TRUNC(Basics!B63/30)=0,Basics!$A$63&"/ ","")&IF(TRUNC(Basics!B64/30)=0,Basics!$A$64&"/ ","") | J2: =IF(TRUNC(Basics!B67/30)=1,Basics!$A$67&"/ ","")&IF(TRUNC(Basics!B60/30)=1,Basics!$A$60&"/ ","")&IF(TRUNC(Basics!B58/30)=1,Basics!$A$58&"/ ","")&IF(TRUNC(Basics!B59/30)=1,Basics!$A$59&"/ ","")&IF(TRUNC(Basics!B66/30)=1,Basics!$A$66&"/ ","")&IF(TRUNC(Basics!B61/30)=1,Basics!$A$61&"/ ","")&IF(TRUNC(Basics!B65/30)=1,Basics!$A$65&"/ ","")&IF(TRUNC(Basics!B62/30)=1,Basics!$A$62&"/ ","")&IF(TRUNC(Basics!B63/30)=1,Basics!$A$63&"/ ","")&IF(TRUNC(Basics!B64/30)=1,Basics!$A$64&"/ ","") -> Moon/ Saturn/ | K2: =IF(TRUNC(Basics!B67/30)=2,Basics!$A$67&"/ ","")&IF(TRUNC(Basics!B60/30)=2,Basics!$A$60&"/ ","")&IF(TRUNC(Basics!B58/30)=2,Basics!$A$58&"/ ","")&IF(TRUNC(Basics!B59/30)=2,Basics!$A$59&"/ ","")&IF(TRUNC(Basics!B66/30)=2,Basics!$A$66&"/ ","")&IF(TRUNC(Basics!B61/30)=2,Basics!$A$61&"/ ","")&IF(TRUNC(Basics!B65/30)=2,Basics!$A$65&"/ ","")&IF(TRUNC(Basics!B62/30)=2,Basics!$A$62&"/ ","")&IF(TRUNC(Basics!B63/30)=2,Basics!$A$63&"/ ","")&IF(TRUNC(Basics!B64/30)=2,Basics!$A$64&"/ ","") -> Venus/
B3: =K2 -> Venus/ | C3: * * * | E3: * * * | F3: =H3 | H3: =IF(TRUNC(Basics!B67/30)=10,Basics!$A$67&"/ ","")&IF(TRUNC(Basics!B60/30)=10,Basics!$A$60&"/ ","")&IF(TRUNC(Basics!B58/30)=10,Basics!$A$58&"/ ","")&IF(TRUNC(Basics!B59/30)=10,Basics!$A$59&"/ ","")&IF(TRUNC(Basics!B66/30)=10,Basics!$A$66&"/ ","")&IF(TRUNC(Basics!B61/30)=10,Basics!$A$61&"/ ","")&IF(TRUNC(Basics!B65/30)=10,Basics!$A$65&"/ ","")&IF(TRUNC(Basics!B62/30)=10,Basics!$A$62&"/ ","")&IF(TRUNC(Basics!B63/30)=10,Basics!$A$63&"/ ","")&IF(TRUNC(Basics!B64/30)=10,Basics!$A$64&"/ ","") | I3: RASI CHART | K3: =IF(TRUNC(Basics!B67/30)=3,Basics!$A$67&"/ ","")&IF(TRUNC(Basics!B60/30)=3,Basics!$A$60&"/ ","")&IF(TRUNC(Basics!B58/30)=3,Basics!$A$58&"/ ","")&IF(TRUNC(Basics!B59/30)=3,Basics!$A$59&"/ ","")&IF(TRUNC(Basics!B66/30)=3,Basics!$A$66&"/ ","")&IF(TRUNC(Basics!B61/30)=3,Basics!$A$61&"/ ","")&IF(TRUNC(Basics!B65/30)=3,Basics!$A$65&"/ ","")&IF(TRUNC(Basics!B62/30)=3,Basics!$A$62&"/ ","")&IF(TRUNC(Basics!B63/30)=3,Basics!$A$63&"/ ","")&IF(TRUNC(Basics!B64/30)=3,Basics!$A$64&"/ ","") -> Ketu/ Sun/ Mercury/
B4: =K3 -> Ketu/ Sun/ Mercury/ | D4: Rashi | F4: =H4 -> Rahu/ Mars/ | H4: =IF(TRUNC(Basics!B67/30)=9,Basics!$A$67&"/ ","")&IF(TRUNC(Basics!B60/30)=9,Basics!$A$60&"/ ","")&IF(TRUNC(Basics!B58/30)=9,Basics!$A$58&"/ ","")&IF(TRUNC(Basics!B59/30)=9,Basics!$A$59&"/ ","")&IF(TRUNC(Basics!B66/30)=9,Basics!$A$66&"/ ","")&IF(TRUNC(Basics!B61/30)=9,Basics!$A$61&"/ ","")&IF(TRUNC(Basics!B65/30)=9,Basics!$A$65&"/ ","")&IF(TRUNC(Basics!B62/30)=9,Basics!$A$62&"/ ","")&IF(TRUNC(Basics!B63/30)=9,Basics!$A$63&"/ ","")&IF(TRUNC(Basics!B64/30)=9,Basics!$A$64&"/ ","") -> Rahu/ Mars/ | J4: D1 | K4: =IF(TRUNC(Basics!B67/30)=4,Basics!$A$67&"/ ","")&IF(TRUNC(Basics!B60/30)=4,Basics!$A$60&"/ ","")&IF(TRUNC(Basics!B58/30)=4,Basics!$A$58&"/ ","")&IF(TRUNC(Basics!B59/30)=4,Basics!$A$59&"/ ","")&IF(TRUNC(Basics!B66/30)=4,Basics!$A$66&"/ ","")&IF(TRUNC(Basics!B61/30)=4,Basics!$A$61&"/ ","")&IF(TRUNC(Basics!B65/30)=4,Basics!$A$65&"/ ","")&IF(TRUNC(Basics!B62/30)=4,Basics!$A$62&"/ ","")&IF(TRUNC(Basics!B63/30)=4,Basics!$A$63&"/ ","")&IF(TRUNC(Basics!B64/30)=4,Basics!$A$64&"/ ","") -> Asc/
B5: =K4 -> Asc/ | C5: * * * | D5: =J5 | E5: * * * | F5: =H5 | H5: =IF(TRUNC(Basics!B67/30)=8,Basics!$A$67&"/ ","")&IF(TRUNC(Basics!B60/30)=8,Basics!$A$60&"/ ","")&IF(TRUNC(Basics!B58/30)=8,Basics!$A$58&"/ ","")&IF(TRUNC(Basics!B59/30)=8,Basics!$A$59&"/ ","")&IF(TRUNC(Basics!B66/30)=8,Basics!$A$66&"/ ","")&IF(TRUNC(Basics!B61/30)=8,Basics!$A$61&"/ ","")&IF(TRUNC(Basics!B65/30)=8,Basics!$A$65&"/ ","")&IF(TRUNC(Basics!B62/30)=8,Basics!$A$62&"/ ","")&IF(TRUNC(Basics!B63/30)=8,Basics!$A$63&"/ ","")&IF(TRUNC(Basics!B64/30)=8,Basics!$A$64&"/ ","") | I5: =IF(TRUNC(Basics!B67/30)=7,Basics!$A$67&"/ ","")&IF(TRUNC(Basics!B60/30)=7,Basics!$A$60&"/ ","")&IF(TRUNC(Basics!B58/30)=7,Basics!$A$58&"/ ","")&IF(TRUNC(Basics!B59/30)=7,Basics!$A$59&"/ ","")&IF(TRUNC(Basics!B66/30)=7,Basics!$A$66&"/ ","")&IF(TRUNC(Basics!B61/30)=7,Basics!$A$61&"/ ","")&IF(TRUNC(Basics!B65/30)=7,Basics!$A$65&"/ ","")&IF(TRUNC(Basics!B62/30)=7,Basics!$A$62&"/ ","")&IF(TRUNC(Basics!B63/30)=7,Basics!$A$63&"/ ","")&IF(TRUNC(Basics!B64/30)=7,Basics!$A$64&"/ ","") -> Jupiter/ | J5: =IF(TRUNC(Basics!B67/30)=6,Basics!$A$67&"/ ","")&IF(TRUNC(Basics!B60/30)=6,Basics!$A$60&"/ ","")&IF(TRUNC(Basics!B58/30)=6,Basics!$A$58&"/ ","")&IF(TRUNC(Basics!B59/30)=6,Basics!$A$59&"/ ","")&IF(TRUNC(Basics!B66/30)=6,Basics!$A$66&"/ ","")&IF(TRUNC(Basics!B61/30)=6,Basics!$A$61&"/ ","")&IF(TRUNC(Basics!B65/30)=6,Basics!$A$65&"/ ","")&IF(TRUNC(Basics!B62/30)=6,Basics!$A$62&"/ ","")&IF(TRUNC(Basics!B63/30)=6,Basics!$A$63&"/ ","")&IF(TRUNC(Basics!B64/30)=6,Basics!$A$64&"/ ","") | K5: =IF(TRUNC(Basics!B67/30)=5,Basics!$A$67&"/ ","")&IF(TRUNC(Basics!B60/30)=5,Basics!$A$60&"/ ","")&IF(TRUNC(Basics!B58/30)=5,Basics!$A$58&"/ ","")&IF(TRUNC(Basics!B59/30)=5,Basics!$A$59&"/ ","")&IF(TRUNC(Basics!B66/30)=5,Basics!$A$66&"/ ","")&IF(TRUNC(Basics!B61/30)=5,Basics!$A$61&"/ ","")&IF(TRUNC(Basics!B65/30)=5,Basics!$A$65&"/ ","")&IF(TRUNC(Basics!B62/30)=5,Basics!$A$62&"/ ","")&IF(TRUNC(Basics!B63/30)=5,Basics!$A$63&"/ ","")&IF(TRUNC(Basics!B64/30)=5,Basics!$A$64&"/ ","")
B6: * * * | C6: =K5 | D6: =J5 | E6: =I5 -> Jupiter/ | F6: * * *

Sheet Sp.Nakshatra
B1: Special Nakshatras From | D1: =INT(MoonDeg*0.075)+1 -> 4 | H1: =IF(D1>21,D1-1,D1) -> 4
A2: Nakshatra Name | B2: Sanskrit | C2: Ref: | D2: Number | E2: 28 Nx | F2: Lords | G2: * | I2: 27 Nx | J2: Lords | K2: Navamsa House | L2: Pada
A3: Janma/Pritvi | B3: Janma | C3: 1 | D3: =MOD(C3+D$1+26,28)+1 -> 4 | E3: =INDEX(NaxNames28,D3) -> Rohini | F3: =INDEX(NakshatraTbl,D3,3) -> Moon | G3: * | H3: =MOD(C3+H$1+25,27)+1 -> 4 | I3: =VLOOKUP(H3,NakshatraInfo,2) -> Rohini | J3: =VLOOKUP(H3,NakshatraInfo,4) -> Moon
A4: Jaati | B4: जाति jāti | C4: 4 | D4: =MOD(C4+D$1+26,28)+1 -> 7 | E4: =INDEX(NaxNames28,D4) -> Punarvasu | F4: =INDEX(NakshatraTbl,D4,3) -> Jupiter | G4: * | H4: =MOD(C4+H$1+25,27)+1 -> 7 | I4: =VLOOKUP(H4,NakshatraInfo,2) -> Punarvasu | J4: =VLOOKUP(H4,NakshatraInfo,4) -> Jupiter
A5: Naidhana | B5: नैधन naidhana | C5: 7 | D5: =MOD(C5+D$1+26,28)+1 -> 10 | E5: =INDEX(NaxNames28,D5) -> Magha | F5: =INDEX(NakshatraTbl,D5,3) -> Ketu | G5: * | H5: =MOD(C5+H$1+25,27)+1 -> 10 | I5: =VLOOKUP(H5,NakshatraInfo,2) -> Magha | J5: =VLOOKUP(H5,NakshatraInfo,4) -> Ketu
A6: Mātṛi /King | B6: मतृ matṛ | C6: 8 | D6: =MOD(C6+D$1+26,28)+1 -> 11 | E6: =INDEX(NaxNames28,D6) -> P. Phalguni | F6: =INDEX(NakshatraTbl,D6,3) -> Venus | G6: * | H6: =MOD(C6+H$1+25,27)+1 -> 11 | I6: =VLOOKUP(H6,NakshatraInfo,2) -> Purva Phalguni | J6: =VLOOKUP(H6,NakshatraInfo,4) -> Venus
A7: Karma/Dvija/Dwijanma | B7: कर्म karma | C7: 10 | D7: =MOD(C7+D$1+26,28)+1 -> 13 | E7: =INDEX(NaxNames28,D7) -> Hasta | F7: =INDEX(NakshatraTbl,D7,3) -> Moon | G7: * | H7: =MOD(C7+H$1+25,27)+1 -> 13 | I7: =VLOOKUP(H7,NakshatraInfo,2) -> Hasta | J7: =VLOOKUP(H7,NakshatraInfo,4) -> Moon | K7: 10
A8: Income??/Needs Chastity | C8: 11 | D8: =MOD(C8+D$1+26,28)+1 -> 14 | E8: =INDEX(NaxNames28,D8) -> Chitra | F8: =INDEX(NakshatraTbl,D8,3) -> Mars | G8: * | H8: =MOD(C8+H$1+25,27)+1 -> 14 | I8: =VLOOKUP(H8,NakshatraInfo,2) -> Chitra | J8: =VLOOKUP(H8,NakshatraInfo,4) -> Mars
A9: Desha | B9: देश deśa | C9: 12 | D9: =MOD(C9+D$1+26,28)+1 -> 15 | E9: =INDEX(NaxNames28,D9) -> Swati | F9: =INDEX(NakshatraTbl,D9,3) -> Rahu | G9: * | H9: - | I9: - | J9: - | K9: 12
A10: Assistant/Raajya/Destiny | B10: राज्य rājya | C10: 13 | D10: =MOD(C10+D$1+26,28)+1 -> 16 | E10: =INDEX(NaxNames28,D10) -> Vishaka | F10: =INDEX(NakshatraTbl,D10,3) -> Jupiter | G10: * | H10: =MOD(C10+H$1+25,27)+1 -> 16 | I10: =VLOOKUP(H10,NakshatraInfo,2) -> Vishakha | J10: =VLOOKUP(H10,NakshatraInfo,4) -> Jupiter | K10: 1
A11: DNA?? | C11: 14 | D11: =MOD(C11+D$1+26,28)+1 -> 17 | E11: =INDEX(NaxNames28,D11) -> Anuradha | F11: =INDEX(NakshatraTbl,D11,3) -> Sat | G11: * | H11: =MOD(C11+H$1+25,27)+1 -> 17 | I11: =VLOOKUP(H11,NakshatraInfo,2) -> Anuradha | J11: =VLOOKUP(H11,NakshatraInfo,4) -> Sat
A12: New Start ?? Self | C12: 15 | D12: =MOD(C12+D$1+26,28)+1 -> 18 | E12: =INDEX(NaxNames28,D12) -> Jyeshta | F12: =INDEX(NakshatraTbl,D12,3) -> Merc | G12: * | H12: =MOD(C12+H$1+25,27)+1 -> 18
A13: Sanghaatika/Kundalini | B13: सङ्गटिक saṅgāṭika | C13: 16 | D13: =MOD(C13+D$1+26,28)+1 -> 19 | E13: =INDEX(NaxNames28,D13) -> Moola | F13: =INDEX(NakshatraTbl,D13,3) -> Ketu | G13: * | H13: =MOD(C13+H$1+25,27)+1 -> 19 | I13: =VLOOKUP(H13,NakshatraInfo,2) -> Mula | J13: =VLOOKUP(H13,NakshatraInfo,4) -> Ketu | K13: 4
A14: Chandra Ashtama (Follower) | B14: Ashtama Nakshatra | C14: 17 | D14: - | E14: - | F14: - | G14: * | H14: =MOD(C14+H$1+25,27)+1 -> 20 | I14: =VLOOKUP(H14,NakshatraInfo,2) -> Purva Ashadha | J14: =VLOOKUP(H14,NakshatraInfo,4) -> Venus
A15: Samudaayika | B15: समुदायिक samudāyika | C15: 18 | D15: =MOD(C15+D$1+26,28)+1 -> 21 | E15: =INDEX(NaxNames28,D15) -> U. Ashada | F15: =INDEX(NakshatraTbl,D15,3) -> Sun | G15: * | H15: =MOD(C15+H$1+25,27)+1 -> 21 | I15: =VLOOKUP(H15,NakshatraInfo,2) -> Uttara Ashadha | J15: =VLOOKUP(H15,NakshatraInfo,4) -> Sun | K15: 6
A16: Aadhana/Father | B16: आधन ādhana | C16: 19 | D16: =MOD(C16+D$1+26,28)+1 -> 22 | E16: =INDEX(NaxNames28,D16) -> Abhjit | F16: =INDEX(NakshatraTbl,D16,3) -> Sun | G16: * | H16: =MOD(C16+H$1+25,27)+1 -> 22 | I16: =VLOOKUP(H16,NakshatraInfo,2) -> Shravan | J16: =VLOOKUP(H16,NakshatraInfo,4) -> Moon | K16: 7
A17: How you write Like Ganesha Guru Word/Recollect | C17: 20 | D17: =MOD(C17+D$1+26,28)+1 -> 23 | E17: =INDEX(NaxNames28,D17) -> Sravana | F17: =INDEX(NakshatraTbl,D17,3) -> Moon | G17: * | H17: =MOD(C17+H$1+25,27)+1 -> 23 | I17: =VLOOKUP(H17,NakshatraInfo,2) -> Dhanistha | J17: =VLOOKUP(H17,NakshatraInfo,4) -> Mars
A18: Takes to Spirituality/Transformation?? | C18: 21 | D18: =MOD(C18+D$1+26,28)+1 -> 24 | E18: =INDEX(NaxNames28,D18) -> Dhanishta | F18: =INDEX(NakshatraTbl,D18,3) -> Mars | G18: * | H18: =MOD(C18+H$1+25,27)+1 -> 24 | I18: =VLOOKUP(H18,NakshatraInfo,2) -> Satabishak | J18: =VLOOKUP(H18,NakshatraInfo,4) -> Rahu
A19: Vainashika | B19: वैनशिक vainaśika | C19: 22 | D19: =MOD(C19+D$1+26,28)+1 -> 25 | E19: =INDEX(NaxNames28,D19) -> Shatabhishaj | F19: =INDEX(NakshatraTbl,D19,3) -> Rahu | G19: * | H19: =MOD(C19+H$1+25,27)+1 -> 25 | I19: =VLOOKUP(H19,NakshatraInfo,2) -> Purva Bhadrapad | J19: =VLOOKUP(H19,NakshatraInfo,4) -> Jupiter | K19: 10
A20: Initiations | C20: 23 | D20: =MOD(C20+D$1+26,28)+1 -> 26 | E20: =INDEX(NaxNames28,D20) -> P. Bhadra | F20: =INDEX(NakshatraTbl,D20,3) -> Jupiter | H20: =MOD(C20+H$1+25,27)+1 -> 26
A21: Iccha Mṛityu/Sati | C21: 24 | D21: =MOD(C21+D$1+26,28)+1 -> 27 | E21: =INDEX(NaxNames28,D21) -> U. Bhadra | F21: =INDEX(NakshatraTbl,D21,3) -> Sat | H21: =MOD(C21+H$1+25,27)+1 -> 27
A22: Maanasa/Jaati(?)/Vayu | B22: मानस mānasa | C22: 25 | D22: =MOD(C22+D$1+26,28)+1 -> 28 | E22: =INDEX(NaxNames28,D22) -> Revati | F22: =INDEX(NakshatraTbl,D22,3) -> Merc | G22: * | H22: =MOD(C22+H$1+25,27)+1 -> 1 | I22: =VLOOKUP(H22,NakshatraInfo,2) -> Ashvini | J22: =VLOOKUP(H22,NakshatraInfo,4) -> Ketu | K22: 1
A23: Brahma(?)/Desha(?)/Agni | C23: 26 | D23: =MOD(C23+D$1+26,28)+1 -> 1 | E23: =INDEX(NaxNames28,D23) -> Ashwini | F23: =INDEX(NakshatraTbl,D23,3) -> Ketu | G23: * | H23: - | I23: - | J23: -
A24: Vishnu/Aakaasha | C24: 27 | D24: =MOD(C24+D$1+26,28)+1 -> 2 | E24: =INDEX(NaxNames28,D24) -> Bharani | F24: =INDEX(NakshatraTbl,D24,3) -> Venus | G24: * | H24: =MOD(C24+H$1+25,27)+1 -> 3 | I24: =VLOOKUP(H24,NakshatraInfo,2) -> Kritika | J24: =VLOOKUP(H24,NakshatraInfo,4) -> Sun | K24: 3
A25: Abhisheka/Jala | B25: अभिशेक abhiśeka | C25: 28 | D25: =MOD(C25+D$1+26,28)+1 -> 3 | E25: =INDEX(NaxNames28,D25) -> Krittika | F25: =INDEX(NakshatraTbl,D25,3) -> Sun | G25: * | H25: - | I25: - | J25: - | K25: 3
A27: Special Nakshatras From Sun | B27: =INT(SunDeg*0.075)+1 -> 7 | D27: =INDEX(NaxNames28,B27) -> Punarvasu
A28: Role | B28: Meaning | C28: Ref: | D28: Nax # | F28: 27 Nx | G28: Lords | I28: 28 Nx
A29: Vidyunmukha | B29: mouth of lightning | C29: 5 | D29: =MOD(C29+B$27+25,27)+1 -> 11 | E29: =INDEX(NakshatraTbl,D29,1) -> Purva Phalguni | G29: =INDEX(NakshatraTbl,D29,3) -> Venus | H29: =MOD(C29+B$27+26,28)+1 -> 11 | I29: =INDEX(NaxNames28,H29) -> P. Phalguni
A30: Shula | B30: sharp and piercing | C30: 8 | D30: =MOD(C30+B$27+25,27)+1 -> 14 | E30: =INDEX(NakshatraTbl,D30,1) -> Chitra | G30: =INDEX(NakshatraTbl,D30,3) -> Mars | H30: =MOD(C30+B$27+26,28)+1 -> 14 | I30: =INDEX(NaxNames28,H30) -> Chitra
A31: Sannipata | B31: trouble creator like Saturn | C31: 14 | D31: =MOD(C31+B$27+25,27)+1 -> 20 | E31: =INDEX(NakshatraTbl,D31,1) -> Purva Ashadha | G31: =INDEX(NakshatraTbl,D31,3) -> Venus | H31: =MOD(C31+B$27+26,28)+1 -> 20 | I31: =INDEX(NaxNames28,H31) -> P. Ashada
A32: Ketu | B32: unpredictable | C32: 18 | D32: =MOD(C32+B$27+25,27)+1 -> 24 | E32: =INDEX(NakshatraTbl,D32,1) -> Dhanistha | G32: =INDEX(NakshatraTbl,D32,3) -> Mars | H32: =MOD(C32+B$27+26,28)+1 -> 24 | I32: =INDEX(NaxNames28,H32) -> Dhanishta
A33: Ulka | B33: fireball | C33: 21 | D33: =MOD(C33+B$27+25,27)+1 -> 27 | E33: =INDEX(NakshatraTbl,D33,1) -> Uttara Bhadrapad | G33: =INDEX(NakshatraTbl,D33,3) -> Sat | H33: =MOD(C33+B$27+26,28)+1 -> 27 | I33: =INDEX(NaxNames28,H33) -> U. Bhadra
A34: Kampa | B34: shiver | C34: 22 | D34: =MOD(C34+B$27+25,27)+1 -> 1 | E34: =INDEX(NakshatraTbl,D34,1) -> Ashvini | G34: =INDEX(NakshatraTbl,D34,3) -> Ketu | H34: =MOD(C34+B$27+26,28)+1 -> 28 | I34: =INDEX(NaxNames28,H34) -> Revati
A35: Vajraka | B35: lighning | C35: 23 | D35: =MOD(C35+B$27+25,27)+1 -> 2 | E35: =INDEX(NakshatraTbl,D35,1) -> Bharani | G35: =INDEX(NakshatraTbl,D35,3) -> Venus | H35: =MOD(C35+B$27+26,28)+1 -> 1 | I35: =INDEX(NaxNames28,H35) -> Ashwini
A36: Nirghata | B36: deadly | C36: 24 | D36: =MOD(C36+B$27+25,27)+1 -> 3 | E36: =INDEX(NakshatraTbl,D36,1) -> Kritika | G36: =INDEX(NakshatraTbl,D36,3) -> Sun | H36: =MOD(C36+B$27+26,28)+1 -> 2 | I36: =INDEX(NaxNames28,H36) -> Bharani
A39: Navatara | B39: Kaaraka | C39: # | D39: Ruler | E39: Deha | F39: Navatara 1 | G39: Use 1st Level | H39: Manasa | I39: Navatara 2 | J39: Use 2 | K39: Atma | L39: Navatara 3 | M39: Use 3 | N39: Ruler_ | O39: #2
A40: Janma | B40: Moon | C40: 1 | D40: =VLOOKUP(E40,NakshatraInfo,4) -> Moon | E40: =D1 -> 4 | F40: =VLOOKUP(E40,NakshatraInfo,2) -> Rohini | G40: Janma | H40: =MOD(E48,27)+1 -> 13 | I40: =VLOOKUP(H40,NakshatraInfo,2) -> Hasta | J40: Karma | K40: =MOD(H48,27)+1 -> 22 | L40: =VLOOKUP(K40,NakshatraInfo,2) -> Shravan | M40: Pita/Guru | N40: =VLOOKUP(K40,NakshatraInfo,4) -> Moon | O40: 1
A41: Sampat | B41: Mars | C41: 2 | D41: =VLOOKUP(E41,NakshatraInfo,4) -> Mars | E41: =MOD(E40,27)+1 -> 5 | F41: =VLOOKUP(E41,NakshatraInfo,2) -> Mrigashira | G41: Dhana-Dhaanya | H41: =MOD(H40,27)+1 -> 14 | I41: =VLOOKUP(H41,NakshatraInfo,2) -> Chitra | J41: Vivaaha | K41: =MOD(K40,27)+1 -> 23 | L41: =VLOOKUP(K41,NakshatraInfo,2) -> Dhanistha | M41: Aaraadhana/Bhaagya | N41: =VLOOKUP(K41,NakshatraInfo,4) -> Mars | O41: 2
A42: Vipat | B42: Rahu | C42: 3 | D42: =VLOOKUP(E42,NakshatraInfo,4) -> Rahu | E42: =MOD(E41,27)+1 -> 6 | F42: =VLOOKUP(E42,NakshatraInfo,2) -> Ardra | G42: Kashta-Durbhaagya | H42: =MOD(H41,27)+1 -> 15 | I42: =VLOOKUP(H42,NakshatraInfo,2) -> Swati | J42: Durbalata | K42: =MOD(K41,27)+1 -> 24 | L42: =VLOOKUP(K42,NakshatraInfo,2) -> Satabishak | M42: Dishaa/Patha | N42: =VLOOKUP(K42,NakshatraInfo,4) -> Rahu | O42: 3
A43: Kshema/Jaati | B43: Jupiter | C43: 4 | D43: =VLOOKUP(E43,NakshatraInfo,4) -> Jupiter | E43: =MOD(E42,27)+1 -> 7 | F43: =VLOOKUP(E43,NakshatraInfo,2) -> Punarvasu | G43: Aashraya-Raksha | H43: =MOD(H42,27)+1 -> 16 | I43: =VLOOKUP(H43,NakshatraInfo,2) -> Vishakha | J43: Suraksha | K43: =MOD(K42,27)+1 -> 25 | L43: =VLOOKUP(K43,NakshatraInfo,2) -> Purva Bhadrapad | M43: Devaalaya/Garbha Griha | N43: =VLOOKUP(K43,NakshatraInfo,4) -> Jupiter | O43: 4
A44: Pratyari | B44: Saturn | C44: 5 | D44: =VLOOKUP(E44,NakshatraInfo,4) -> Sat | E44: =MOD(E43,27)+1 -> 8 | F44: =VLOOKUP(E44,NakshatraInfo,2) -> Pushya | G44: Sangharsha-Anadhar | H44: =MOD(H43,27)+1 -> 17 | I44: =VLOOKUP(H44,NakshatraInfo,2) -> Anuradha | J44: Chunauti/Challenge | K44: =MOD(K43,27)+1 -> 26 | L44: =VLOOKUP(K44,NakshatraInfo,2) -> Uttara Bhadrapad | M44: Kasauti/Test | N44: =VLOOKUP(K44,NakshatraInfo,4) -> Sat | O44: 5
A45: Saadhaka | B45: Mercury | C45: 6 | D45: =VLOOKUP(E45,NakshatraInfo,4) -> Merc | E45: =MOD(E44,27)+1 -> 9 | F45: =VLOOKUP(E45,NakshatraInfo,2) -> Ashlesha | G45: Sampurna Siddhi | H45: =MOD(H44,27)+1 -> 18 | I45: =VLOOKUP(H45,NakshatraInfo,2) -> Jyeshtha | J45: Uparjan/Produce/Earn | K45: =MOD(K44,27)+1 -> 27 | L45: =VLOOKUP(K45,NakshatraInfo,2) -> Revati | M45: Siddhi/Aushadhi | N45: =VLOOKUP(K45,NakshatraInfo,4) -> Merc | O45: 6
A46: Naidhana/Vadha | B46: Ketu | C46: 7 | D46: =VLOOKUP(E46,NakshatraInfo,4) -> Ketu | E46: =MOD(E45,27)+1 -> 10 | F46: =VLOOKUP(E46,NakshatraInfo,2) -> Magha | G46: Vadhik-Ghatak | H46: =MOD(H45,27)+1 -> 19 | I46: =VLOOKUP(H46,NakshatraInfo,2) -> Mula | J46: Malla Yuddha | K46: =MOD(K45,27)+1 -> 1 | L46: =VLOOKUP(K46,NakshatraInfo,2) -> Ashvini | M46: Sanyaasa/Mrityu | N46: =VLOOKUP(K46,NakshatraInfo,4) -> Ketu | O46: 7
A47: Mitra | B47: Venus | C47: 8 | D47: =VLOOKUP(E47,NakshatraInfo,4) -> Venus | E47: =MOD(E46,27)+1 -> 11 | F47: =VLOOKUP(E47,NakshatraInfo,2) -> Purva Phalguni | G47: Sahaayaka/Helper | H47: =MOD(H46,27)+1 -> 20 | I47: =VLOOKUP(H47,NakshatraInfo,2) -> Purva Ashadha | J47: Saha Karmi/Co-Workger | K47: =MOD(K46,27)+1 -> 2 | L47: =VLOOKUP(K47,NakshatraInfo,2) -> Bharani | M47: Sangha Bandhu/Relative | N47: =VLOOKUP(K47,NakshatraInfo,4) -> Venus | O47: 8
A48: Parama Mitra | B48: Sun | C48: 9 | D48: =VLOOKUP(E48,NakshatraInfo,4) -> Sun | E48: =MOD(E47,27)+1 -> 12 | F48: =VLOOKUP(E48,NakshatraInfo,2) -> Uttara Phalguni | G48: Samrakshaka | H48: =MOD(H47,27)+1 -> 21 | I48: =VLOOKUP(H48,NakshatraInfo,2) -> Uttara Ashadha | J48: Adhi Naayaka | K48: =MOD(K47,27)+1 -> 3 | L48: =VLOOKUP(K48,NakshatraInfo,2) -> Kritika | M48: Raajya Abhisheka/Lakshya | N48: =VLOOKUP(K48,NakshatraInfo,4) -> Sun | O48: 9
A51: Grahas' | B51: Nakshatra | C51: Nx#
B52: =INDEX(NakshatraTbl,C52,1) -> Revati | C52: 28

Sheet Ayush
B1: Degree | E1: Pinda (sun) | H1: Nisarga(Moon) | K1: Amsha (Lagna Lord) | M1: Samudaya Ashtakavarga (Saturn) | N1: Rashmi (Mercury) | Q1: Kaalachakra(Venus) | R1: BhinnaAshtakvarga (Mars) | S1: Nakshatraja (Jupiter)
A2: Graha | B2: Jataka | C2: Debility | D2: Distance | E2: Maana | F2: Correction | G2: Age-P | H2: Maana2 | I2: Correction3 | J2: Age-N | K2: D9 | L2: Correction5 | M2: Age-A | N2: MaanaR | O2: Age-R | P2: Factor | Q2: Age-K | R2: Age-B | S2: Age-Nx
A3: Sun | B3: =INDIRECT(A3) -> 92.399203 | C3: =SunDeb -> 190 | D3: =(1-COS((360+B3-C3)/180*PI()))/2 -> 0.56613509 | E3: 19 | G3: =(1-COS((360+B3-C3)/180*PI()))/2*E3 -> 10.756567 | H3: 1 | J3: =(1-COS((360+B3-C3)/180*PI()))/2*H3 -> 0.56613509 | K3: =MOD(B3/3.333,12) -> 3.7225331 | M3: =Ashtakavarga!P30 -> 8.0383294 | N3: 10 | O3: =N3*$D3*Table19[[#This Row],[Factor]] -> 5.6613509 | P3: 1
A4: Moon | B4: =INDIRECT(A4) -> 53.015944 | C4: =MoonDeb -> 213 | D4: =(1-COS((360+B4-C4)/180*PI()))/2 -> 0.9697987 | E4: 25 | G4: =(1-COS((360+B4-C4)/180*PI()))/2*E4 -> 24.244968 | H4: 2 | J4: =(1-COS((360+B4-C4)/180*PI()))/2*H4 -> 1.9395974 | K4: =MOD(B4/3.333,12) -> 3.906374 | M4: =Ashtakavarga!P31 -> 20.049281 | N4: 9 | O4: =N4*$D4*Table19[[#This Row],[Factor]] -> 26.184565 | P4: 3
A5: Mars | B5: =INDIRECT(A5) -> 298.10866 | C5: =MarsDeb -> 118 | D5: =(1-COS((360+B5-C5)/180*PI()))/2 -> 0.9999991 | E5: 15 | G5: =(1-COS((360+B5-C5)/180*PI()))/2*E5 -> 14.999987 | H5: 9 | J5: =(1-COS((360+B5-C5)/180*PI()))/2*H5 -> 8.9999919 | K5: =MOD(B5/3.333,12) -> 5.4415433 | M5: =Ashtakavarga!P32 -> 20.043805 | N5: 5 | O5: =N5*$D5*Table19[[#This Row],[Factor]] -> 14.999987 | P5: 3
A6: Mercury | B6: =INDIRECT(A6) -> 117.12979 | C6: =MercDeb -> 345 | D6: =(1-COS((360+B6-C6)/180*PI()))/2 -> 0.83540613 | E6: 12 | G6: =(1-COS((360+B6-C6)/180*PI()))/2*E6 -> 10.024874 | H6: 20 | J6: =(1-COS((360+B6-C6)/180*PI()))/2*H6 -> 16.708123 | K6: =MOD(B6/3.333,12) -> 11.14245 | M6: =Ashtakavarga!P33 -> 14.124571 | N6: 5 | O6: =N6*$D6*Table19[[#This Row],[Factor]] -> 4.1770306 | P6: 1
A7: Jupiter | B7: =INDIRECT(A7) -> 213.19717 | C7: =JupDeb -> 275 | D7: =(1-COS((360+B7-C7)/180*PI()))/2 -> 0.26374634 | E7: 15 | G7: =(1-COS((360+B7-C7)/180*PI()))/2*E7 -> 3.9561952 | H7: 18 | J7: =(1-COS((360+B7-C7)/180*PI()))/2*H7 -> 4.7474342 | K7: =MOD(B7/3.333,12) -> 3.9655491 | M7: =Ashtakavarga!P34 -> 4.0971924 | N7: 7 | O7: =N7*$D7*Table19[[#This Row],[Factor]] -> 2.4554785 | P7: 1.33
A8: Venus | B8: =INDIRECT(A8) -> 81.540603 | C8: =VenuDeb -> 177 | D8: =(1-COS((360+B8-C8)/180*PI()))/2 -> 0.54757017 | E8: 21 | G8: =(1-COS((360+B8-C8)/180*PI()))/2*E8 -> 11.498974 | H8: 20 | J8: =(1-COS((360+B8-C8)/180*PI()))/2*H8 -> 10.951403 | K8: =MOD(B8/3.333,12) -> 0.4646273 | M8: =Ashtakavarga!P35 -> 14.069814 | N8: 8 | O8: =N8*$D8*Table19[[#This Row],[Factor]] -> 5.8261466 | P8: 1.33
A9: Saturn | B9: =INDIRECT(A9) -> 39.885211 | C9: =SatDeb -> 20 | D9: =(1-COS((360+B9-C9)/180*PI()))/2 -> 0.029812024 | E9: 20 | G9: =(1-COS((360+B9-C9)/180*PI()))/2*E9 -> 0.59624047 | H9: 50 | J9: =(1-COS((360+B9-C9)/180*PI()))/2*H9 -> 1.4906012 | K9: =MOD(B9/3.333,12) -> 11.96676 | M9: =Ashtakavarga!P36 -> 8.0876101 | N9: 5 | O9: =N9*$D9*Table19[[#This Row],[Factor]] -> 0.19824996 | P9: 1.33
A10: Lagna | B10: =INDIRECT(A10) -> 136.71152 | D10: =(1-COS((360+B10-C10)/180*PI()))/2 -> 0.8639553 | E10: - | H10: - | K10: =MOD(B10/3.333,12) -> 5.0175568 | M10: =Ashtakavarga!P37 -> 12.088979 | P10: =O10 -> 0
A11: Total | E11: =SUM(E3:E9) -> 127 | G11: =SUM(G3:G9) -> 76.077804 | H11: =SUM(H3:H9) -> 120 | J11: =SUM(J3:J9) -> 45.403286 | K11: =SUM(K3:K10) -> 45.627394 | M11: =SUM(M3:M10) -> 100.59958 | N11: =SUM(N3:N9) -> 49 | O11: =SUM(O3:O9) -> 59.502808 | P11: =SUM(P3:P9) -> 11.99 | Q11: ='KalaChakra Dasa'!L31 -> 100
D16: Equate to Solar
A17: Year | B17: Days | C17: Ratio | D17: Example | E17: =E11 -> 127
A18: Solar | B18: 365.2425 | C18: =B18/B18 -> 1 | E18: =E17*C18 -> 127
A19: Nakshatra | B19: =27.33*12 -> 327.96 | C19: =B18/B19 -> 1.11368 | E19: =E17/C19 -> 114.03635
A20: Paksha | B20: =29.5*12 -> 354 | C20: =B18/B20 -> 1.0317585 | E20: =E17/C20 -> 123.09082
A21: Savana | B21: 360 | C21: =B18/B21 -> 1.0145625 | E21: =E17/C21 -> 125.17711

Sheet Shadbala
B2: Graha | C2: Deg* | D2: Sthana Bala (8) | Q2: Dik Bala | R2: Kaala Bala | AA2: Naisarga Bala | AB2: Ayana (Ghatika L) | AC2: Drig Bala | AD2: Yuddha | AE2: Cheshta Bala (7th House)
D3: Uccha(1) (Akaasha) | E3: Sapta Vargaja(5.25) (Vaayu) | M3: Oja-Yugma(0.5)-Ojas/Agni | N3: Kendradi(1) (Jala) | O3: Dreshkana(0.25) (Pritvi) | P3: Total Staana Bala | R3: Natonnata(1) (Varanada Lagna) | S3: Paksha(1) (Lagna) | T3: Tribhaga(1) (Hora L) | U3: Horaadi | Z3: Total Kaala
E4: D1 | F4: D2 | G4: D3 | H4: D7 | I4: D9 | J4: D12 | K4: D30 | L4: Total | U4: Varsha(.25) | V4: Masa(.5) | W4: Dina(0.75) | X4: Hora(1) | Y4: Total Horaadi
B5: =Basics!A8 -> Sun | C5: =Basics!G8 -> 92.399203 | D5: =(1-COS((360+C5-SunDeb)/180*PI()))/2 -> 0.56613509 | E5: =ACOS(1-2*D5)*180/PI()/3/60 -> 0.54222665 | AA5: =7/7 -> 1
B6: =Basics!A9 -> Moon | C6: =Basics!G9 -> 53.015944 | D6: =(1-COS((360+C6-MoonDeb)/180*PI()))/2 -> 0.9697987 | E6: =ACOS(1-2*D6)*180/PI()/3/60 -> 0.88880031 | AA6: =6/7 -> 0.85714286
B7: =Basics!A10 -> Mars | C7: =Basics!G10 -> 298.10866 | D7: =(1-COS((360+C7-MarsDeb)/180*PI()))/2 -> 0.9999991 | E7: =ACOS(1-2*D7)*180/PI()/3/60 -> 0.99939631 | AA7: =5/7 -> 0.71428571
B8: =Basics!A11 -> Mercury | C8: =Basics!G11 -> 117.12979 | D8: =(1-COS((360+C8-MercDeb)/180*PI()))/2 -> 0.83540613 | E8: =ACOS(1-2*D8)*180/PI()/3/60 -> 0.73405437 | AA8: =4/7 -> 0.57142857
B9: =Basics!A12 -> Jupiter | C9: =Basics!G12 -> 213.19717 | D9: =(1-COS((360+C9-JupDeb)/180*PI()))/2 -> 0.26374634 | E9: =ACOS(1-2*D9)*180/PI()/3/60 -> 0.34334903 | AA9: =3/7 -> 0.42857143
B10: =Basics!A13 -> Venus | C10: =Basics!G13 -> 81.540603 | D10: =(1-COS((360+C10-VenuDeb)/180*PI()))/2 -> 0.54757017 | E10: =ACOS(1-2*D10)*180/PI()/3/60 -> 0.53032998 | AA10: =2/7 -> 0.28571429
B11: =Basics!A14 -> Saturn | C11: =Basics!G14 -> 39.885211 | D11: =(1-COS((360+C11-SatDeb)/180*PI()))/2 -> 0.029812024 | E11: =ACOS(1-2*D11)*180/PI()/3/60 -> 0.1104734 | AA11: =1/7 -> 0.14285714
G13: Graha Guna | K13: Sum
C14: Sphuta Deg | G14: G# | H14: Gx | I14: GD9 | J14: GD30
B15: =Basics!A7 -> Lagna | C15: =Basics!G7 -> 136.71152 | E15: =+ROUNDUP(Moon/13.333,0)+ROUNDUP(JanmaGhatika,0)+ROUNDUP(Lagna/30,0) -> 17
B16: =Basics!A8 -> Sun | C16: =Basics!G8 -> 92.399203 | E16: =INDEX(NakshatraTbl,INT(C16*0.075)+1,3) -> Jupiter | F16: =MOD(ROUNDUP(C16/13.3333333333,0)*1*ROUNDUP(MOD(C16,30)/3.33333,0)+ROUNDUP(Moon/13.333,0)+ROUNDUP(JanmaGhatika,0)+ROUNDUP(Lagna/30,0)+11,12)+1 -> 12 | G16: 1 | H16: =ROUNDUP(C16/13.3333333333,0) -> 7 | I16: =ROUNDUP(MOD(C16,30)/3.33333,0) -> 1 | J16: =ROUNDUP(MOD(C16,30),0) -> 3 | K16: =G16*H16*J16 -> 21 | L16: =MOD(K16+$E$15,12) -> 2
B17: =Basics!A9 -> Moon | C17: =Basics!G9 -> 53.015944 | E17: =INDEX(NakshatraTbl,INT(C17*0.075)+1,3) -> Moon | F17: =MOD(ROUNDUP(C17/13.3333333333,0)*2*ROUNDUP(MOD(C17,30)/3.33333,0)+ROUNDUP(Moon/13.333,0)+ROUNDUP(JanmaGhatika,0)+ROUNDUP(Lagna/30,0)+11,12)+1 -> 1 | G17: 2 | H17: =ROUNDUP(C17/13.3333333333,0) -> 4 | I17: =ROUNDUP(MOD(C17,30)/3.33333,0) -> 7 | J17: =ROUNDUP(MOD(C17,30),0) -> 24 | K17: =G17*H17*J17 -> 192 | L17: =MOD(K17+$E$15,12) -> 5
B18: =Basics!A10 -> Mars | C18: =Basics!G10 -> 298.10866 | E18: =INDEX(NakshatraTbl,INT(C18*0.075)+1,3) -> Moon | F18: =MOD(ROUNDUP(C18/13.3333333333,0)*3*ROUNDUP(MOD(C18,30)/3.33333,0)+ROUNDUP(Moon/13.333,0)+ROUNDUP(JanmaGhatika,0)+ROUNDUP(Lagna/30,0)+11,12)+1 -> 2 | G18: 3 | H18: =ROUNDUP(C18/13.3333333333,0) -> 23 | I18: =ROUNDUP(MOD(C18,30)/3.33333,0) -> 9 | J18: =ROUNDUP(MOD(C18,30),0) -> 29 | K18: =G18*H18*J18 -> 2001 | L18: =MOD(K18+$E$15,12) -> 2
B19: =Basics!A11 -> Mercury | C19: =Basics!G11 -> 117.12979 | E19: =INDEX(NakshatraTbl,INT(C19*0.075)+1,3) -> Merc | F19: =MOD(ROUNDUP(C19/13.3333333333,0)*4*ROUNDUP(MOD(C19,30)/3.33333,0)+ROUNDUP(Moon/13.333,0)+ROUNDUP(JanmaGhatika,0)+ROUNDUP(Lagna/30,0)+11,12)+1 -> 5 | G19: 4 | H19: =ROUNDUP(C19/13.3333333333,0) -> 9 | I19: =ROUNDUP(MOD(C19,30)/3.33333,0) -> 9 | J19: =ROUNDUP(MOD(C19,30),0) -> 28 | K19: =G19*H19*J19 -> 1008 | L19: =MOD(K19+$E$15,12) -> 5
B20: =Basics!A12 -> Jupiter | C20: =Basics!G12 -> 213.19717 | E20: =INDEX(NakshatraTbl,INT(C20*0.075)+1,3) -> Jupiter | F20: =MOD(ROUNDUP(C20/13.3333333333,0)*5*ROUNDUP(MOD(C20,30)/3.33333,0)+ROUNDUP(Moon/13.333,0)+ROUNDUP(JanmaGhatika,0)+ROUNDUP(Lagna/30,0),12) -> 1 | G20: 5 | H20: =ROUNDUP(C20/13.3333333333,0) -> 16 | I20: =ROUNDUP(MOD(C20,30)/3.33333,0) -> 1 | J20: =ROUNDUP(MOD(C20,30),0) -> 4 | K20: =G20*H20*J20 -> 320 | L20: =MOD(K20+$E$15,12) -> 1
B21: =Basics!A13 -> Venus | C21: =Basics!G13 -> 81.540603 | E21: =INDEX(NakshatraTbl,INT(C21*0.075)+1,3) -> Jupiter | F21: =MOD(ROUNDUP(C21/13.3333333333,0)*6*ROUNDUP(MOD(C21,30)/3.33333,0)+ROUNDUP(Moon/13.333,0)+ROUNDUP(JanmaGhatika,0)+ROUNDUP(Lagna/30,0)+11,12)+1 -> 11 | G21: 6 | H21: =ROUNDUP(C21/13.3333333333,0) -> 7 | I21: =ROUNDUP(MOD(C21,30)/3.33333,0) -> 7 | J21: =ROUNDUP(MOD(C21,30),0) -> 22 | K21: =G21*H21*J21 -> 924 | L21: =MOD(K21+$E$15,12) -> 5
B22: =Basics!A14 -> Saturn | C22: =Basics!G14 -> 39.885211 | E22: =INDEX(NakshatraTbl,INT(C22*0.075)+1,3) -> Sun | F22: =MOD(ROUNDUP(C22/13.3333333333,0)*7*ROUNDUP(MOD(C22,30)/3.33333,0)+ROUNDUP(Moon/13.333,0)+ROUNDUP(JanmaGhatika,0)+ROUNDUP(Lagna/30,0)+11,12)+1 -> 8 | G22: 7 | H22: =ROUNDUP(C22/13.3333333333,0) -> 3 | I22: =ROUNDUP(MOD(C22,30)/3.33333,0) -> 3 | J22: =ROUNDUP(MOD(C22,30),0) -> 10 | K22: =G22*H22*J22 -> 210 | L22: =MOD(K22+$E$15,12) -> 11
B23: =Basics!A15 -> Rahu | C23: =Basics!G15 -> 291.96724 | E23: =INDEX(NakshatraTbl,INT(C23*0.075)+1,3) -> Sun | F23: =MOD(ROUNDUP(C23/13.3333333333,0)*8*ROUNDUP(MOD(C23,30)/3.33333,0)+ROUNDUP(Moon/13.333,0)+ROUNDUP(JanmaGhatika,0)+ROUNDUP(Lagna/30,0)+11,12)+1 -> 1 | G23: 8 | H23: =ROUNDUP(C23/13.3333333333,0) -> 22 | I23: =ROUNDUP(MOD(C23,30)/3.33333,0) -> 7 | J23: =ROUNDUP(MOD(C23,30),0) -> 22 | K23: =G23*H23*J23 -> 3872 | L23: =MOD(K23+$E$15,12) -> 1
B24: =Basics!A16 -> Ketu | C24: =Basics!G16 -> 111.96724 | E24: =INDEX(NakshatraTbl,INT(C24*0.075)+1,3) -> Merc | F24: =MOD(ROUNDUP(C24/13.3333333333,0)*9*ROUNDUP(MOD(C24,30)/3.33333,0)+ROUNDUP(Moon/13.333,0)+ROUNDUP(JanmaGhatika,0)+ROUNDUP(Lagna/30,0)+11,12)+1 -> 8 | G24: 9 | H24: =ROUNDUP(C24/13.3333333333,0) -> 9 | I24: =ROUNDUP(MOD(C24,30)/3.33333,0) -> 7 | J24: =ROUNDUP(MOD(C24,30),0) -> 22 | K24: =G24*H24*J24 -> 1782 | L24: =MOD(K24+$E$15,12) -> 11

Sheet Vimshottari
A1: Planet | B1: Vimsottari Years | C1: Vimsottari Seq | D1: Use Forward Table? | E1: TRUE | F1: Graha | G1: Solar Years | H1: Sequence | I1: Sol Days/Deg | J1: Sol Days/Min | K1: Sol Days/Sec | L1: Dasa Days/Min
A2: =IF($E$1,F2,D2) -> Ketu | B2: =IF($E$1,G2,E2) -> 7 | C2: =H2 -> 0 | D2: Mercury | E2: =VimFactor*17 -> 17 | F2: Ketu | G2: 7 | H2: 0 | I2: =G2*360/13.33333333 -> 189 | J2: =G2*360/800 -> 3.15 | K2: =J2/60 -> 0.0525 | L2: =G2*360/(MoonPeriod/27*24*60) -> 1.7294021
A3: =IF($E$1,F3,D3) -> Venus | B3: =IF($E$1,G3,E3) -> 20 | C3: =H3 -> 1 | D3: Saturn | E3: =VimFactor*19 -> 19 | F3: Venus | G3: 20 | H3: 1 | I3: =G3*360/13.33333333 -> 540 | J3: =G3*360/800 -> 9 | K3: =J3/60 -> 0.15 | L3: =G3*360/(MoonPeriod/27*24*60) -> 4.9411487
A4: =IF($E$1,F4,D4) -> Sun | B4: =IF($E$1,G4,E4) -> 6 | C4: =H4 -> 2 | D4: Jupiter | E4: =VimFactor*16 -> 16 | F4: Sun | G4: 6 | H4: 2 | I4: =G4*360/13.33333333 -> 162 | J4: =G4*360/800 -> 2.7 | K4: =J4/60 -> 0.045 | L4: =G4*360/(MoonPeriod/27*24*60) -> 1.4823446
A5: =IF($E$1,F5,D5) -> Moon | B5: =IF($E$1,G5,E5) -> 10 | C5: =H5 -> 3 | D5: Rahu | E5: =VimFactor*18 -> 18 | F5: Moon | G5: 10 | H5: 3 | I5: =G5*360/13.33333333 -> 270 | J5: =G5*360/800 -> 4.5 | K5: =J5/60 -> 0.075 | L5: =G5*360/(MoonPeriod/27*24*60) -> 2.4705744
A6: =IF($E$1,F6,D6) -> Mars | B6: =IF($E$1,G6,E6) -> 7 | C6: =H6 -> 4 | D6: Mars | E6: =VimFactor*7 -> 7 | F6: Mars | G6: 7 | H6: 4 | I6: =G6*360/13.33333333 -> 189 | J6: =G6*360/800 -> 3.15 | K6: =J6/60 -> 0.0525 | L6: =G6*360/(MoonPeriod/27*24*60) -> 1.7294021
A7: =IF($E$1,F7,D7) -> Rahu | B7: =IF($E$1,G7,E7) -> 18 | C7: =H7 -> 5 | D7: Moon | E7: =VimFactor*10 -> 10 | F7: Rahu | G7: 18 | H7: 5 | I7: =G7*360/13.33333333 -> 486 | J7: =G7*360/800 -> 8.1 | K7: =J7/60 -> 0.135 | L7: =G7*360/(MoonPeriod/27*24*60) -> 4.4470339
A8: =IF($E$1,F8,D8) -> Jupiter | B8: =IF($E$1,G8,E8) -> 16 | C8: =H8 -> 6 | D8: Sun | E8: =VimFactor*6 -> 6 | F8: Jupiter | G8: 16 | H8: 6 | I8: =G8*360/13.33333333 -> 432 | J8: =G8*360/800 -> 7.2 | K8: =J8/60 -> 0.12 | L8: =G8*360/(MoonPeriod/27*24*60) -> 3.952919
A9: =IF($E$1,F9,D9) -> Saturn | B9: =IF($E$1,G9,E9) -> 19 | C9: =H9 -> 7 | D9: Venus | E9: =VimFactor*20 -> 20 | F9: Saturn | G9: 19 | H9: 7 | I9: =G9*360/13.33333333 -> 513 | J9: =G9*360/800 -> 8.55 | K9: =J9/60 -> 0.1425 | L9: =G9*360/(MoonPeriod/27*24*60) -> 4.6940913
A10: =IF($E$1,F10,D10) -> Mercury | B10: =IF($E$1,G10,E10) -> 17 | C10: =H10 -> 8 | D10: Ketu | E10: =VimFactor*7 -> 7 | F10: Mercury | G10: 17 | H10: 8 | I10: =G10*360/13.33333333 -> 459 | J10: =G10*360/800 -> 7.65 | K10: =J10/60 -> 0.1275 | L10: =G10*360/(MoonPeriod/27*24*60) -> 4.1999764
A12: Vimsottari Calculation 1 | F12: Moon Speed | G12: =DATA!L4 -> 27.321582 | H12: Dasa Sensitivity Days/Min
A13: =Basics!A9 -> Moon | B13: Vimsottari Dasa | H13: =E15*360/(G12/27*24*60) -> 2.4705744
A14: Vimsottari Degree | B14: =VLOOKUP(A13,ChartInfo,7,0) -> 53.015944 | G14: Sol Days/Deg | H14: Sol Days/Min | I14: Sol Days/Sec
A15: Starting Dasa | B15: =INDEX(DasaYears,D15+1,1) -> Moon | D15: =MOD(FLOOR(B14/StarDeg,1),9) -> 3 | E15: =INDEX(DasaYears,MOD(FLOOR(B14/StarDeg,1),9)+1,2) -> 10 | G15: =E15*360/13.33333333 -> 270 | H15: =E15*360/800 -> 4.5 | I15: =H15/60 -> 0.075
A16: Balance Of Dasa | B16: =((StarDeg-MOD(B14,StarDeg))/StarDeg)*E15 -> 0.23804167
A17: Dasa Past | E17: =((MOD(B14,StarDeg))/StarDeg)*E15 -> 9.7619583
A18: =INDEX(DasaYears,MOD(D15,9)+1,1) -> Moon | B18: =DoB+G18 -> 26133.384 | G18: 0 | H18: <-Corrections Days
I19: Maha | L19: Antar | O19: Praty | R19: Suksma | U19: Praana
A20: Order | B20: Name | C20: Insert Arrow | D20: Maha daśā | F20: Solar Age | G20: Mark Arrow Below | H20: Antardasas of | I20: =VLOOKUP(">",VimMahaDasa,2,0) -> Saturn | J20: =I30 -> 48135.622 | K20: Pratyantar of | L20: =VLOOKUP(">",VimAD,2,0) -> Moon | M20: =L30 -> 42121.092 | N20: Sukshma | O20: =VLOOKUP(">",VimPD,2,0) -> Sun | P20: =O30 -> 42121.092 | Q20: Praana | R20: =VLOOKUP(">",VimSD,2,0) -> Sun | S20: =R30 -> 42093.622 | T20: Deha | U20: =VLOOKUP(">",VimPAD,2,0) -> Jupiter | V20: =U30 -> 42092.863
A21: 1 | B21: Janma | D21: =INDEX(DasaYears,MOD(D15,9)+1,1) -> Moon | E21: =DoB-DaysInYear*E17 -> 22567.781 | F21: =(SunDeg-360*E17)/360 -> -9.5052939 | H21: =INDEX(DasaYears,MOD(VLOOKUP(VLOOKUP(">",VimMahaDasa,2),DasaYears,3,0)+IF(VLOOKUP(""&VLOOKUP(">",VimMahaDasa,2)&"",ChartInfo,11),-1,0),9)+1,1) -> Sun | I21: =VLOOKUP(">",VimMahaDasa,3,0) -> 41195.78 | K21: =INDEX(DasaYears,MOD(VLOOKUP(L20,DasaYears,3,0)+IF(VLOOKUP(L20,ChartInfo,11,0),-1,0),9)+1,1) -> Moon | L21: =VLOOKUP(">",VimAD,3,0) -> 41542.772 | M21: > | N21: =INDEX(DasaYears,MOD(VLOOKUP(O20,DasaYears,3,0)+IF(VLOOKUP(O20,ChartInfo,11,0),-1,0),9)+1,1) -> Sun | O21: =VLOOKUP(">",VimPD,3,0) -> 42092.176 | Q21: =INDEX(DasaYears,MOD(VLOOKUP(R20,DasaYears,3,0)+IF(VLOOKUP(R20,ChartInfo,11,0),-1,0),9)+1,1) -> Sun | R21: =VLOOKUP(">",VimSD,3,0) -> 42092.176 | T21: =INDEX(DasaYears,MOD(VLOOKUP(U20,DasaYears,3,0)+IF(VLOOKUP(U20,ChartInfo,11,0),-1,0),9)+1,1) -> Rahu | U21: =VLOOKUP(">",VimPAD,3,0) -> 42092.67
A22: 2 | B22: Sampat | D22: =INDEX(DasaYears,MOD($D$15+1,9)+1,1) -> Mars | E22: =B18+(B16*DaysInYear) -> 26220.33 | F22: =(SunDeg+(B16*360)) -> 178.0942 | G22: > | H22: =INDEX(DasaYears,(MOD(VLOOKUP(H21,DasaYears,3,0)+IF(VLOOKUP(VLOOKUP(">",VimMahaDasa,2,0),ChartInfo,11),-1,1),9)+1),1) -> Moon | I22: =I21+(VLOOKUP($I$20,DasaYears,2,0)*VLOOKUP(H21,DasaYears,2,0)/VimTotal)*DaysInYear -> 41542.772 | K22: =INDEX(DasaYears,(MOD(VLOOKUP(K21,DasaYears,3,0)+IF(VLOOKUP($L$20,ChartInfo,11,0),-1,1),9)+1),1) -> Mars | L22: =L21+DaysInYear*VLOOKUP($I$20,DasaYears,2,0)*VLOOKUP($L$20,DasaYears,2,0)/120*VLOOKUP(K21,DasaYears,2,0)/120 -> 41590.965 | N22: =INDEX(DasaYears,(MOD(VLOOKUP(N21,DasaYears,3,0)+IF(VLOOKUP($L$20,ChartInfo,11,0),-1,1),9)+1),1) -> Moon | O22: =O21+DaysInYear*VLOOKUP($I$20,DasaYears,2,0)*VLOOKUP($L$20,DasaYears,2,0)/120*VLOOKUP(N21,DasaYears,2,0)/120*VLOOKUP($O$20,DasaYears,2,0)/120 -> 42093.622 | Q22: =INDEX(DasaYears,(MOD(VLOOKUP(Q21,DasaYears,3,0)+IF(VLOOKUP($L$20,ChartInfo,11,0),-1,1),9)+1),1) -> Moon | R22: =R21+DaysInYear*VLOOKUP($I$20,DasaYears,2,0)*VLOOKUP($L$20,DasaYears,2,0)/120*VLOOKUP(Q21,DasaYears,2,0)/120*VLOOKUP($O$20,DasaYears,2,0)/120*VLOOKUP($R$20,DasaYears,2,0)/120 -> 42092.248 | T22: =INDEX(DasaYears,(MOD(VLOOKUP(T21,DasaYears,3,0)+IF(VLOOKUP($L$20,ChartInfo,11,0),-1,1),9)+1),1) -> Jupiter | U22: =U21+DaysInYear*VLOOKUP($I$20,DasaYears,2,0)*VLOOKUP($L$20,DasaYears,2,0)/120*VLOOKUP(T21,DasaYears,2,0)/120*VLOOKUP($O$20,DasaYears,2,0)/120*VLOOKUP($R$20,DasaYears,2,0)/120*VLOOKUP($U$20,DasaYears,2,0)/120 -> 42092.699
A23: 3 | B23: Vipat | D23: =INDEX(DasaYears,MOD($D$15+2,9)+1,1) -> Rahu | E23: =E22+DaysInYear*VLOOKUP(D22,DasaYears,2,0) -> 28777.114 | F23: =F22+360*VLOOKUP(D22,DasaYears,2,0) -> 2698.0942 | H23: =INDEX(DasaYears,(MOD(VLOOKUP(H22,DasaYears,3,0)+IF(VLOOKUP(VLOOKUP(">",VimMahaDasa,2,0),ChartInfo,11),-1,1),9)+1),1) -> Mars | I23: =I22+(VLOOKUP($I$20,DasaYears,2,0)*VLOOKUP(H22,DasaYears,2,0)/VimTotal)*DaysInYear -> 42121.092 | K23: =INDEX(DasaYears,(MOD(VLOOKUP(K22,DasaYears,3,0)+IF(VLOOKUP($L$20,ChartInfo,11,0),-1,1),9)+1),1) -> Rahu | L23: =L22+DaysInYear*VLOOKUP($I$20,DasaYears,2,0)*VLOOKUP($L$20,DasaYears,2,0)/120*VLOOKUP(K22,DasaYears,2,0)/120 -> 41624.701 | N23: =INDEX(DasaYears,(MOD(VLOOKUP(N22,DasaYears,3,0)+IF(VLOOKUP($L$20,ChartInfo,11,0),-1,1),9)+1),1) -> Mars | O23: =O22+DaysInYear*VLOOKUP($I$20,DasaYears,2,0)*VLOOKUP($L$20,DasaYears,2,0)/120*VLOOKUP(N22,DasaYears,2,0)/120*VLOOKUP($O$20,DasaYears,2,0)/120 -> 42096.032 | Q23: =INDEX(DasaYears,(MOD(VLOOKUP(Q22,DasaYears,3,0)+IF(VLOOKUP($L$20,ChartInfo,11,0),-1,1),9)+1),1) -> Mars | R23: =R22+DaysInYear*VLOOKUP($I$20,DasaYears,2,0)*VLOOKUP($L$20,DasaYears,2,0)/120*VLOOKUP(Q22,DasaYears,2,0)/120*VLOOKUP($O$20,DasaYears,2,0)/120*VLOOKUP($R$20,DasaYears,2,0)/120 -> 42092.369 | T23: =INDEX(DasaYears,(MOD(VLOOKUP(T22,DasaYears,3,0)+IF(VLOOKUP($L$20,ChartInfo,11,0),-1,1),9)+1),1) -> Saturn | U23: =U22+DaysInYear*VLOOKUP($I$20,DasaYears,2,0)*VLOOKUP($L$20,DasaYears,2,0)/120*VLOOKUP(T22,DasaYears,2,0)/120*VLOOKUP($O$20,DasaYears,2,0)/120*VLOOKUP($R$20,DasaYears,2,0)/120*VLOOKUP($U$20,DasaYears,2,0)/120 -> 42092.725
A24: 4 | B24: Kshema | D24: =INDEX(DasaYears,MOD($D$15+3,9)+1,1) -> Jupiter | E24: =E23+DaysInYear*VLOOKUP(D23,DasaYears,2,0) -> 35351.702 | F24: =F23+360*VLOOKUP(D23,DasaYears,2,0) -> 9178.0942 | H24: =INDEX(DasaYears,(MOD(VLOOKUP(H23,DasaYears,3,0)+IF(VLOOKUP(VLOOKUP(">",VimMahaDasa,2,0),ChartInfo,11),-1,1),9)+1),1) -> Rahu | I24: =I23+(VLOOKUP($I$20,DasaYears,2,0)*VLOOKUP(H23,DasaYears,2,0)/VimTotal)*DaysInYear -> 42525.916 | K24: =INDEX(DasaYears,(MOD(VLOOKUP(K23,DasaYears,3,0)+IF(VLOOKUP($L$20,ChartInfo,11,0),-1,1),9)+1),1) -> Jupiter | L24: =L23+DaysInYear*VLOOKUP($I$20,DasaYears,2,0)*VLOOKUP($L$20,DasaYears,2,0)/120*VLOOKUP(K23,DasaYears,2,0)/120 -> 41711.449 | N24: =INDEX(DasaYears,(MOD(VLOOKUP(N23,DasaYears,3,0)+IF(VLOOKUP($L$20,ChartInfo,11,0),-1,1),9)+1),1) -> Rahu | O24: =O23+DaysInYear*VLOOKUP($I$20,DasaYears,2,0)*VLOOKUP($L$20,DasaYears,2,0)/120*VLOOKUP(N23,DasaYears,2,0)/120*VLOOKUP($O$20,DasaYears,2,0)/120 -> 42097.718 | Q24: =INDEX(DasaYears,(MOD(VLOOKUP(Q23,DasaYears,3,0)+IF(VLOOKUP($L$20,ChartInfo,11,0),-1,1),9)+1),1) -> Rahu | R24: =R23+DaysInYear*VLOOKUP($I$20,DasaYears,2,0)*VLOOKUP($L$20,DasaYears,2,0)/120*VLOOKUP(Q23,DasaYears,2,0)/120*VLOOKUP($O$20,DasaYears,2,0)/120*VLOOKUP($R$20,DasaYears,2,0)/120 -> 42092.453 | T24: =INDEX(DasaYears,(MOD(VLOOKUP(T23,DasaYears,3,0)+IF(VLOOKUP($L$20,ChartInfo,11,0),-1,1),9)+1),1) -> Mercury | U24: =U23+DaysInYear*VLOOKUP($I$20,DasaYears,2,0)*VLOOKUP($L$20,DasaYears,2,0)/120*VLOOKUP(T23,DasaYears,2,0)/120*VLOOKUP($O$20,DasaYears,2,0)/120*VLOOKUP($R$20,DasaYears,2,0)/120*VLOOKUP($U$20,DasaYears,2,0)/120 -> 42092.755
A25: 5 | B25: Pratyak | C25: > | D25: =INDEX(DasaYears,MOD($D$15+4,9)+1,1) -> Saturn | E25: =E24+DaysInYear*VLOOKUP(D24,DasaYears,2,0) -> 41195.78 | F25: =F24+360*VLOOKUP(D24,DasaYears,2,0) -> 14938.094 | G25: > | H25: =INDEX(DasaYears,(MOD(VLOOKUP(H24,DasaYears,3,0)+IF(VLOOKUP(VLOOKUP(">",VimMahaDasa,2,0),ChartInfo,11),-1,1),9)+1),1) -> Jupiter | I25: =I24+(VLOOKUP($I$20,DasaYears,2,0)*VLOOKUP(H24,DasaYears,2,0)/VimTotal)*DaysInYear -> 43566.893 | K25: =INDEX(DasaYears,(MOD(VLOOKUP(K24,DasaYears,3,0)+IF(VLOOKUP($L$20,ChartInfo,11,0),-1,1),9)+1),1) -> Saturn | L25: =L24+DaysInYear*VLOOKUP($I$20,DasaYears,2,0)*VLOOKUP($L$20,DasaYears,2,0)/120*VLOOKUP(K24,DasaYears,2,0)/120 -> 41788.558 | N25: =INDEX(DasaYears,(MOD(VLOOKUP(N24,DasaYears,3,0)+IF(VLOOKUP($L$20,ChartInfo,11,0),-1,1),9)+1),1) -> Jupiter | O25: =O24+DaysInYear*VLOOKUP($I$20,DasaYears,2,0)*VLOOKUP($L$20,DasaYears,2,0)/120*VLOOKUP(N24,DasaYears,2,0)/120*VLOOKUP($O$20,DasaYears,2,0)/120 -> 42102.056 | P25: > | Q25: =INDEX(DasaYears,(MOD(VLOOKUP(Q24,DasaYears,3,0)+IF(VLOOKUP($L$20,ChartInfo,11,0),-1,1),9)+1),1) -> Jupiter | R25: =R24+DaysInYear*VLOOKUP($I$20,DasaYears,2,0)*VLOOKUP($L$20,DasaYears,2,0)/120*VLOOKUP(Q24,DasaYears,2,0)/120*VLOOKUP($O$20,DasaYears,2,0)/120*VLOOKUP($R$20,DasaYears,2,0)/120 -> 42092.67 | T25: =INDEX(DasaYears,(MOD(VLOOKUP(T24,DasaYears,3,0)+IF(VLOOKUP($L$20,ChartInfo,11,0),-1,1),9)+1),1) -> Ketu | U25: =U24+DaysInYear*VLOOKUP($I$20,DasaYears,2,0)*VLOOKUP($L$20,DasaYears,2,0)/120*VLOOKUP(T24,DasaYears,2,0)/120*VLOOKUP($O$20,DasaYears,2,0)/120*VLOOKUP($R$20,DasaYears,2,0)/120*VLOOKUP($U$20,DasaYears,2,0)/120 -> 42092.783
A26: 6 | B26: Saadana | D26: =INDEX(DasaYears,MOD($D$15+5,9)+1,1) -> Mercury | E26: =E25+DaysInYear*VLOOKUP(D25,DasaYears,2,0) -> 48135.622 | F26: =F25+360*VLOOKUP(D25,DasaYears,2,0) -> 21778.094 | H26: =INDEX(DasaYears,(MOD(VLOOKUP(H25,DasaYears,3,0)+IF(VLOOKUP(VLOOKUP(">",VimMahaDasa,2,0),ChartInfo,11),-1,1),9)+1),1) -> Saturn | I26: =I25+(VLOOKUP($I$20,DasaYears,2,0)*VLOOKUP(H25,DasaYears,2,0)/VimTotal)*DaysInYear -> 44492.205 | K26: =INDEX(DasaYears,(MOD(VLOOKUP(K25,DasaYears,3,0)+IF(VLOOKUP($L$20,ChartInfo,11,0),-1,1),9)+1),1) -> Mercury | L26: =L25+DaysInYear*VLOOKUP($I$20,DasaYears,2,0)*VLOOKUP($L$20,DasaYears,2,0)/120*VLOOKUP(K25,DasaYears,2,0)/120 -> 41880.125 | N26: =INDEX(DasaYears,(MOD(VLOOKUP(N25,DasaYears,3,0)+IF(VLOOKUP($L$20,ChartInfo,11,0),-1,1),9)+1),1) -> Saturn | O26: =O25+DaysInYear*VLOOKUP($I$20,DasaYears,2,0)*VLOOKUP($L$20,DasaYears,2,0)/120*VLOOKUP(N25,DasaYears,2,0)/120*VLOOKUP($O$20,DasaYears,2,0)/120 -> 42105.911 | Q26: =INDEX(DasaYears,(MOD(VLOOKUP(Q25,DasaYears,3,0)+IF(VLOOKUP($L$20,ChartInfo,11,0),-1,1),9)+1),1) -> Saturn | R26: =R25+DaysInYear*VLOOKUP($I$20,DasaYears,2,0)*VLOOKUP($L$20,DasaYears,2,0)/120*VLOOKUP(Q25,DasaYears,2,0)/120*VLOOKUP($O$20,DasaYears,2,0)/120*VLOOKUP($R$20,DasaYears,2,0)/120 -> 42092.863 | T26: =INDEX(DasaYears,(MOD(VLOOKUP(T25,DasaYears,3,0)+IF(VLOOKUP($L$20,ChartInfo,11,0),-1,1),9)+1),1) -> Venus | U26: =U25+DaysInYear*VLOOKUP($I$20,DasaYears,2,0)*VLOOKUP($L$20,DasaYears,2,0)/120*VLOOKUP(T25,DasaYears,2,0)/120*VLOOKUP($O$20,DasaYears,2,0)/120*VLOOKUP($R$20,DasaYears,2,0)/120*VLOOKUP($U$20,DasaYears,2,0)/120 -> 42092.794
A27: 7 | B27: Naidana | D27: =INDEX(DasaYears,MOD($D$15+6,9)+1,1) -> Ketu | E27: =E26+DaysInYear*VLOOKUP(D26,DasaYears,2,0) -> 54344.955 | F27: =F26+360*VLOOKUP(D26,DasaYears,2,0) -> 27898.094 | H27: =INDEX(DasaYears,(MOD(VLOOKUP(H26,DasaYears,3,0)+IF(VLOOKUP(VLOOKUP(">",VimMahaDasa,2,0),ChartInfo,11),-1,1),9)+1),1) -> Mercury | I27: =I26+(VLOOKUP($I$20,DasaYears,2,0)*VLOOKUP(H26,DasaYears,2,0)/VimTotal)*DaysInYear -> 45591.013 | K27: =INDEX(DasaYears,(MOD(VLOOKUP(K26,DasaYears,3,0)+IF(VLOOKUP($L$20,ChartInfo,11,0),-1,1),9)+1),1) -> Ketu | L27: =L26+DaysInYear*VLOOKUP($I$20,DasaYears,2,0)*VLOOKUP($L$20,DasaYears,2,0)/120*VLOOKUP(K26,DasaYears,2,0)/120 -> 41962.054 | N27: =INDEX(DasaYears,(MOD(VLOOKUP(N26,DasaYears,3,0)+IF(VLOOKUP($L$20,ChartInfo,11,0),-1,1),9)+1),1) -> Mercury | O27: =O26+DaysInYear*VLOOKUP($I$20,DasaYears,2,0)*VLOOKUP($L$20,DasaYears,2,0)/120*VLOOKUP(N26,DasaYears,2,0)/120*VLOOKUP($O$20,DasaYears,2,0)/120 -> 42110.49 | P27: > | Q27: =INDEX(DasaYears,(MOD(VLOOKUP(Q26,DasaYears,3,0)+IF(VLOOKUP($L$20,ChartInfo,11,0),-1,1),9)+1),1) -> Mercury | R27: =R26+DaysInYear*VLOOKUP($I$20,DasaYears,2,0)*VLOOKUP($L$20,DasaYears,2,0)/120*VLOOKUP(Q26,DasaYears,2,0)/120*VLOOKUP($O$20,DasaYears,2,0)/120*VLOOKUP($R$20,DasaYears,2,0)/120 -> 42093.092 | T27: =INDEX(DasaYears,(MOD(VLOOKUP(T26,DasaYears,3,0)+IF(VLOOKUP($L$20,ChartInfo,11,0),-1,1),9)+1),1) -> Sun | U27: =U26+DaysInYear*VLOOKUP($I$20,DasaYears,2,0)*VLOOKUP($L$20,DasaYears,2,0)/120*VLOOKUP(T26,DasaYears,2,0)/120*VLOOKUP($O$20,DasaYears,2,0)/120*VLOOKUP($R$20,DasaYears,2,0)/120*VLOOKUP($U$20,DasaYears,2,0)/120 -> 42092.826
A28: 8 | B28: Mitra | D28: =INDEX(DasaYears,MOD($D$15+7,9)+1,1) -> Venus | E28: =E27+DaysInYear*VLOOKUP(D27,DasaYears,2,0) -> 56901.739 | F28: =F27+360*VLOOKUP(D27,DasaYears,2,0) -> 30418.094 | G28: > | H28: =INDEX(DasaYears,(MOD(VLOOKUP(H27,DasaYears,3,0)+IF(VLOOKUP(VLOOKUP(">",VimMahaDasa,2,0),ChartInfo,11),-1,1),9)+1),1) -> Ketu | I28: =I27+(VLOOKUP($I$20,DasaYears,2,0)*VLOOKUP(H27,DasaYears,2,0)/VimTotal)*DaysInYear -> 46574.158 | K28: =INDEX(DasaYears,(MOD(VLOOKUP(K27,DasaYears,3,0)+IF(VLOOKUP($L$20,ChartInfo,11,0),-1,1),9)+1),1) -> Venus | L28: =L27+DaysInYear*VLOOKUP($I$20,DasaYears,2,0)*VLOOKUP($L$20,DasaYears,2,0)/120*VLOOKUP(K27,DasaYears,2,0)/120 -> 41995.789 | M28: > | N28: =INDEX(DasaYears,(MOD(VLOOKUP(N27,DasaYears,3,0)+IF(VLOOKUP($L$20,ChartInfo,11,0),-1,1),9)+1),1) -> Ketu | O28: =O27+DaysInYear*VLOOKUP($I$20,DasaYears,2,0)*VLOOKUP($L$20,DasaYears,2,0)/120*VLOOKUP(N27,DasaYears,2,0)/120*VLOOKUP($O$20,DasaYears,2,0)/120 -> 42114.586 | P28: > | Q28: =INDEX(DasaYears,(MOD(VLOOKUP(Q27,DasaYears,3,0)+IF(VLOOKUP($L$20,ChartInfo,11,0),-1,1),9)+1),1) -> Ketu | R28: =R27+DaysInYear*VLOOKUP($I$20,DasaYears,2,0)*VLOOKUP($L$20,DasaYears,2,0)/120*VLOOKUP(Q27,DasaYears,2,0)/120*VLOOKUP($O$20,DasaYears,2,0)/120*VLOOKUP($R$20,DasaYears,2,0)/120 -> 42093.297 | T28: =INDEX(DasaYears,(MOD(VLOOKUP(T27,DasaYears,3,0)+IF(VLOOKUP($L$20,ChartInfo,11,0),-1,1),9)+1),1) -> Moon | U28: =U27+DaysInYear*VLOOKUP($I$20,DasaYears,2,0)*VLOOKUP($L$20,DasaYears,2,0)/120*VLOOKUP(T27,DasaYears,2,0)/120*VLOOKUP($O$20,DasaYears,2,0)/120*VLOOKUP($R$20,DasaYears,2,0)/120*VLOOKUP($U$20,DasaYears,2,0)/120 -> 42092.836
A29: 9 | B29: Paramitra | C29: > | D29: =INDEX(DasaYears,MOD($D$15+8,9)+1,1) -> Sun | E29: =E28+DaysInYear*VLOOKUP(D28,DasaYears,2,0) -> 64206.837 | F29: =F28+360*VLOOKUP(D28,DasaYears,2,0) -> 37618.094 | G29: > | H29: =INDEX(DasaYears,(MOD(VLOOKUP(H28,DasaYears,3,0)+IF(VLOOKUP(VLOOKUP(">",VimMahaDasa,2,0),ChartInfo,11),-1,1),9)+1),1) -> Venus | I29: =I28+(VLOOKUP($I$20,DasaYears,2,0)*VLOOKUP(H28,DasaYears,2,0)/VimTotal)*DaysInYear -> 46978.982 | J29: > | K29: =INDEX(DasaYears,(MOD(VLOOKUP(K28,DasaYears,3,0)+IF(VLOOKUP($L$20,ChartInfo,11,0),-1,1),9)+1),1) -> Sun | L29: =L28+DaysInYear*VLOOKUP($I$20,DasaYears,2,0)*VLOOKUP($L$20,DasaYears,2,0)/120*VLOOKUP(K28,DasaYears,2,0)/120 -> 42092.176 | M29: > | N29: =INDEX(DasaYears,(MOD(VLOOKUP(N28,DasaYears,3,0)+IF(VLOOKUP($L$20,ChartInfo,11,0),-1,1),9)+1),1) -> Venus | O29: =O28+DaysInYear*VLOOKUP($I$20,DasaYears,2,0)*VLOOKUP($L$20,DasaYears,2,0)/120*VLOOKUP(N28,DasaYears,2,0)/120*VLOOKUP($O$20,DasaYears,2,0)/120 -> 42116.273 | P29: > | Q29: =INDEX(DasaYears,(MOD(VLOOKUP(Q28,DasaYears,3,0)+IF(VLOOKUP($L$20,ChartInfo,11,0),-1,1),9)+1),1) -> Venus | R29: =R28+DaysInYear*VLOOKUP($I$20,DasaYears,2,0)*VLOOKUP($L$20,DasaYears,2,0)/120*VLOOKUP(Q28,DasaYears,2,0)/120*VLOOKUP($O$20,DasaYears,2,0)/120*VLOOKUP($R$20,DasaYears,2,0)/120 -> 42093.381 | T29: =INDEX(DasaYears,(MOD(VLOOKUP(T28,DasaYears,3,0)+IF(VLOOKUP($L$20,ChartInfo,11,0),-1,1),9)+1),1) -> Mars | U29: =U28+DaysInYear*VLOOKUP($I$20,DasaYears,2,0)*VLOOKUP($L$20,DasaYears,2,0)/120*VLOOKUP(T28,DasaYears,2,0)/120*VLOOKUP($O$20,DasaYears,2,0)/120*VLOOKUP($R$20,DasaYears,2,0)/120*VLOOKUP($U$20,DasaYears,2,0)/120 -> 42092.852
D30: =INDEX(DasaYears,MOD(D15+9,9)+1,1) -> Moon | E30: =E29+DaysInYear*VLOOKUP(D29,DasaYears,2,0) -> 66398.366 | F30: =F29+360*VLOOKUP(D29,DasaYears,2,0) -> 39778.094 | I30: =I29+(VLOOKUP($I$20,DasaYears,2,0)*VLOOKUP(H29,DasaYears,2,0)/VimTotal)*DaysInYear -> 48135.622 | L30: =L29+DaysInYear*VLOOKUP($I$20,DasaYears,2,0)*VLOOKUP($L$20,DasaYears,2,0)/120*VLOOKUP(K29,DasaYears,2,0)/120 -> 42121.092 | O30: =O29+DaysInYear*VLOOKUP($I$20,DasaYears,2,0)*VLOOKUP($L$20,DasaYears,2,0)/120*VLOOKUP(N29,DasaYears,2,0)/120*VLOOKUP($O$20,DasaYears,2,0)/120 -> 42121.092 | R30: =R29+DaysInYear*VLOOKUP($I$20,DasaYears,2,0)*VLOOKUP($L$20,DasaYears,2,0)/120*VLOOKUP(Q29,DasaYears,2,0)/120*VLOOKUP($O$20,DasaYears,2,0)/120*VLOOKUP($R$20,DasaYears,2,0)/120 -> 42093.622 | U30: =U29+DaysInYear*VLOOKUP($I$20,DasaYears,2,0)*VLOOKUP($L$20,DasaYears,2,0)/120*VLOOKUP(T29,DasaYears,2,0)/120*VLOOKUP($O$20,DasaYears,2,0)/120*VLOOKUP($R$20,DasaYears,2,0)/120*VLOOKUP($U$20,DasaYears,2,0)/120 -> 42092.863
H31: Duration | I31: =I30-I21 -> 6939.8426 | K31: Duration | L31: =L30-L21 -> 578.32022 | N31: Duration | O31: =O30-O21 -> 28.916011 | Q31: Duration | R31: =R30-R21 -> 1.4458005 | T31: Duration | U31: =U30-U21 -> 0.19277341
H32: 1st/4Part | I32: =I21 -> 41195.78 | K32: 1st Part | L32: =L21 -> 41542.772 | N32: 1st Part | O32: =O21 -> 42092.176 | Q32: 1st Part | R32: =R21 -> 42092.176 | T32: 1st Part | U32: =U21 -> 42092.67
H33: 2nd/4Part | I33: =I32+I31/4 -> 42930.74 | K33: 2nd Part | L33: =L32+L31/4 -> 41687.352 | N33: 2nd Part | O33: =O32+O31/4 -> 42099.405 | Q33: 2nd Part | R33: =R32+R31/4 -> 42092.538 | T33: 2nd Part | U33: =U32+U31/4 -> 42092.718
H34: 3rd/4Part | I34: =I33+I31/4 -> 44665.701 | K34: 3rd Part | L34: =L33+L31/4 -> 41831.932 | N34: 3rd Part | O34: =O33+O31/4 -> 42106.634 | Q34: 3rd Part | R34: =R33+R31/4 -> 42092.899 | T34: 3rd Part | U34: =U33+U31/4 -> 42092.767
H35: 4th/4Part | I35: =I34+I31/4 -> 46400.662 | K35: 4th Part | L35: =L34+L31/4 -> 41976.512 | N35: 4th Part | O35: =O34+O31/4 -> 42113.863 | Q35: 4th Part | R35: =R34+R31/4 -> 42093.26 | T35: 4th Part | U35: =U34+U31/4 -> 42092.815
A38: Rashi Bhukti Vimshottari | C38: =I20 -> Saturn | E38: Rashi Bhukti | F38: Progress frwd | G38: Ashtakavarga of | H38: =IF(C38="Rahu","Saturn",IF(C38="Ketu","Ketu",C38)) -> Saturn | I38: Saturn | J38: Jupiter | K38: Mars | L38: Sun | M38: Venus | N38: Mercury | O38: Moon | P38: Lagna
D39: Start Sign | E39: =INT(VLOOKUP(I20,ChartInfo,7,0)/30+0.9999999) -> 2 | F39: =NOT(VLOOKUP(I20,ChartInfo,11,0)) -> 1 | G39: AV Score | H39: Portion | I39: =VLOOKUP($H$38&"-"&I$38,AllPAV,$E40+3,0) -> * | J39: =VLOOKUP($H$38&"-"&J$38,AllPAV,$E40+3,0) -> * | K39: =VLOOKUP($H$38&"-"&K$38,AllPAV,$E40+3,0) -> 1 | L39: =VLOOKUP($H$38&"-"&L$38,AllPAV,$E40+3,0) -> 1 | M39: =VLOOKUP($H$38&"-"&M$38,AllPAV,$E40+3,0) -> 1 | N39: =VLOOKUP($H$38&"-"&N$38,AllPAV,$E40+3,0) -> 1 | O39: =VLOOKUP($H$38&"-"&O$38,AllPAV,$E40+3,0) -> * | P39: =VLOOKUP($H$38&"-"&P$38,AllPAV,$E40+3,0) -> 1
E40: =MOD(E39+12-IF($F$39,1,2),12)+1 -> 2 | F40: =INDEX(RsTbl,E40) -> Ta | G40: =VLOOKUP($H$38,BAV,E40+2,0) -> 5 | H40: 1/12 | I40: =I21 -> 41195.78 | J40: =I40+$I$31/12/8 -> 41268.07 | K40: =J40+$I$31/12/8 -> 41340.36 | L40: =K40+$I$31/12/8 -> 41412.65 | M40: =L40+$I$31/12/8 -> 41484.94 | N40: =M40+$I$31/12/8 -> 41557.23 | O40: =N40+$I$31/12/8 -> 41629.52 | P40: =O40+$I$31/12/8 -> 41701.81 | Q40: =P40+$I$31/12/8 -> 41774.1
I41: =VLOOKUP($H$38&"-"&I$38,AllPAV,$E42+3,0) -> * | J41: =VLOOKUP($H$38&"-"&J$38,AllPAV,$E42+3,0) -> * | K41: =VLOOKUP($H$38&"-"&K$38,AllPAV,$E42+3,0) -> 1 | L41: =VLOOKUP($H$38&"-"&L$38,AllPAV,$E42+3,0) -> * | M41: =VLOOKUP($H$38&"-"&M$38,AllPAV,$E42+3,0) -> * | N41: =VLOOKUP($H$38&"-"&N$38,AllPAV,$E42+3,0) -> 1 | O41: =VLOOKUP($H$38&"-"&O$38,AllPAV,$E42+3,0) -> * | P41: =VLOOKUP($H$38&"-"&P$38,AllPAV,$E42+3,0) -> 1
E42: =MOD(E40+12-IF($F$39,0,2),12)+1 -> 3 | F42: =INDEX(RsTbl,E42) -> Ge | G42: =VLOOKUP($H$38,BAV,E42+2,0) -> 3 | H42: 2/12 | I42: =I40+$I$31/12 -> 41774.1 | J42: =I42+$I$31/12/8 -> 41846.39 | K42: =J42+$I$31/12/8 -> 41918.68 | L42: =K42+$I$31/12/8 -> 41990.97 | M42: =L42+$I$31/12/8 -> 42063.26 | N42: =M42+$I$31/12/8 -> 42135.55 | O42: =N42+$I$31/12/8 -> 42207.84 | P42: =O42+$I$31/12/8 -> 42280.13 | Q42: =P42+$I$31/12/8 -> 42352.42
I43: =VLOOKUP($H$38&"-"&I$38,AllPAV,$E44+3,0) -> 1 | J43: =VLOOKUP($H$38&"-"&J$38,AllPAV,$E44+3,0) -> * | K43: =VLOOKUP($H$38&"-"&K$38,AllPAV,$E44+3,0) -> * | L43: =VLOOKUP($H$38&"-"&L$38,AllPAV,$E44+3,0) -> 1 | M43: =VLOOKUP($H$38&"-"&M$38,AllPAV,$E44+3,0) -> * | N43: =VLOOKUP($H$38&"-"&N$38,AllPAV,$E44+3,0) -> * | O43: =VLOOKUP($H$38&"-"&O$38,AllPAV,$E44+3,0) -> 1 | P43: =VLOOKUP($H$38&"-"&P$38,AllPAV,$E44+3,0) -> *
E44: =MOD(E42+12-IF($F$39,0,2),12)+1 -> 4 | F44: =INDEX(RsTbl,E44) -> Cn | G44: =VLOOKUP($H$38,BAV,E44+2,0) -> 3 | H44: 3/12 | I44: =I42+$I$31/12 -> 42352.42 | J44: =I44+$I$31/12/8 -> 42424.71 | K44: =J44+$I$31/12/8 -> 42497 | L44: =K44+$I$31/12/8 -> 42569.29 | M44: =L44+$I$31/12/8 -> 42641.58 | N44: =M44+$I$31/12/8 -> 42713.87 | O44: =N44+$I$31/12/8 -> 42786.16 | P44: =O44+$I$31/12/8 -> 42858.45 | Q44: =P44+$I$31/12/8 -> 42930.74
I45: =VLOOKUP($H$38&"-"&I$38,AllPAV,$E46+3,0) -> * | J45: =VLOOKUP($H$38&"-"&J$38,AllPAV,$E46+3,0) -> * | K45: =VLOOKUP($H$38&"-"&K$38,AllPAV,$E46+3,0) -> * | L45: =VLOOKUP($H$38&"-"&L$38,AllPAV,$E46+3,0) -> 1 | M45: =VLOOKUP($H$38&"-"&M$38,AllPAV,$E46+3,0) -> * | N45: =VLOOKUP($H$38&"-"&N$38,AllPAV,$E46+3,0) -> * | O45: =VLOOKUP($H$38&"-"&O$38,AllPAV,$E46+3,0) -> * | P45: =VLOOKUP($H$38&"-"&P$38,AllPAV,$E46+3,0) -> 1
E46: =MOD(E44+12-IF($F$39,0,2),12)+1 -> 5 | F46: =INDEX(RsTbl,E46) -> Le | G46: =VLOOKUP($H$38,BAV,E46+2,0) -> 2 | H46: 4/12 | I46: =I44+$I$31/12 -> 42930.74 | J46: =I46+$I$31/12/8 -> 43003.03 | K46: =J46+$I$31/12/8 -> 43075.321 | L46: =K46+$I$31/12/8 -> 43147.611 | M46: =L46+$I$31/12/8 -> 43219.901 | N46: =M46+$I$31/12/8 -> 43292.191 | O46: =N46+$I$31/12/8 -> 43364.481 | P46: =O46+$I$31/12/8 -> 43436.771 | Q46: =P46+$I$31/12/8 -> 43509.061
I47: =VLOOKUP($H$38&"-"&I$38,AllPAV,$E48+3,0) -> 1 | J47: =VLOOKUP($H$38&"-"&J$38,AllPAV,$E48+3,0) -> 1 | K47: =VLOOKUP($H$38&"-"&K$38,AllPAV,$E48+3,0) -> * | L47: =VLOOKUP($H$38&"-"&L$38,AllPAV,$E48+3,0) -> * | M47: =VLOOKUP($H$38&"-"&M$38,AllPAV,$E48+3,0) -> * | N47: =VLOOKUP($H$38&"-"&N$38,AllPAV,$E48+3,0) -> * | O47: =VLOOKUP($H$38&"-"&O$38,AllPAV,$E48+3,0) -> * | P47: =VLOOKUP($H$38&"-"&P$38,AllPAV,$E48+3,0) -> *
E48: =MOD(E46+12-IF($F$39,0,2),12)+1 -> 6 | F48: =INDEX(RsTbl,E48) -> Vi | G48: =VLOOKUP($H$38,BAV,E48+2,0) -> 2 | H48: 5/12 | I48: =I46+$I$31/12 -> 43509.061 | J48: =I48+$I$31/12/8 -> 43581.351 | K48: =J48+$I$31/12/8 -> 43653.641 | L48: =K48+$I$31/12/8 -> 43725.931 | M48: =L48+$I$31/12/8 -> 43798.221 | N48: =M48+$I$31/12/8 -> 43870.511 | O48: =N48+$I$31/12/8 -> 43942.801 | P48: =O48+$I$31/12/8 -> 44015.091 | Q48: =P48+$I$31/12/8 -> 44087.381
I49: =VLOOKUP($H$38&"-"&I$38,AllPAV,$E50+3,0) -> 1 | J49: =VLOOKUP($H$38&"-"&J$38,AllPAV,$E50+3,0) -> 1 | K49: =VLOOKUP($H$38&"-"&K$38,AllPAV,$E50+3,0) -> 1 | L49: =VLOOKUP($H$38&"-"&L$38,AllPAV,$E50+3,0) -> 1 | M49: =VLOOKUP($H$38&"-"&M$38,AllPAV,$E50+3,0) -> * | N49: =VLOOKUP($H$38&"-"&N$38,AllPAV,$E50+3,0) -> * | O49: =VLOOKUP($H$38&"-"&O$38,AllPAV,$E50+3,0) -> 1 | P49: =VLOOKUP($H$38&"-"&P$38,AllPAV,$E50+3,0) -> 1
E50: =MOD(E48+12-IF($F$39,0,2),12)+1 -> 7 | F50: =INDEX(RsTbl,E50) -> Li | G50: =VLOOKUP($H$38,BAV,E50+2,0) -> 6 | H50: 6/12 | I50: =I48+$I$31/12 -> 44087.381 | J50: =I50+$I$31/12/8 -> 44159.671 | K50: =J50+$I$31/12/8 -> 44231.961 | L50: =K50+$I$31/12/8 -> 44304.251 | M50: =L50+$I$31/12/8 -> 44376.541 | N50: =M50+$I$31/12/8 -> 44448.831 | O50: =N50+$I$31/12/8 -> 44521.121 | P50: =O50+$I$31/12/8 -> 44593.411 | Q50: =P50+$I$31/12/8 -> 44665.701
I51: =VLOOKUP($H$38&"-"&I$38,AllPAV,$E52+3,0) -> * | J51: =VLOOKUP($H$38&"-"&J$38,AllPAV,$E52+3,0) -> * | K51: =VLOOKUP($H$38&"-"&K$38,AllPAV,$E52+3,0) -> 1 | L51: =VLOOKUP($H$38&"-"&L$38,AllPAV,$E52+3,0) -> * | M51: =VLOOKUP($H$38&"-"&M$38,AllPAV,$E52+3,0) -> 1 | N51: =VLOOKUP($H$38&"-"&N$38,AllPAV,$E52+3,0) -> * | O51: =VLOOKUP($H$38&"-"&O$38,AllPAV,$E52+3,0) -> * | P51: =VLOOKUP($H$38&"-"&P$38,AllPAV,$E52+3,0) -> 1
E52: =MOD(E50+12-IF($F$39,0,2),12)+1 -> 8 | F52: =INDEX(RsTbl,E52) -> Sc | G52: =VLOOKUP($H$38,BAV,E52+2,0) -> 3 | H52: 7/12 | I52: =I50+$I$31/12 -> 44665.701 | J52: =I52+$I$31/12/8 -> 44737.991 | K52: =J52+$I$31/12/8 -> 44810.281 | L52: =K52+$I$31/12/8 -> 44882.571 | M52: =L52+$I$31/12/8 -> 44954.861 | N52: =M52+$I$31/12/8 -> 45027.151 | O52: =N52+$I$31/12/8 -> 45099.441 | P52: =O52+$I$31/12/8 -> 45171.731 | Q52: =P52+$I$31/12/8 -> 45244.021
I53: =VLOOKUP($H$38&"-"&I$38,AllPAV,$E54+3,0) -> * | J53: =VLOOKUP($H$38&"-"&J$38,AllPAV,$E54+3,0) -> * | K53: =VLOOKUP($H$38&"-"&K$38,AllPAV,$E54+3,0) -> 1 | L53: =VLOOKUP($H$38&"-"&L$38,AllPAV,$E54+3,0) -> * | M53: =VLOOKUP($H$38&"-"&M$38,AllPAV,$E54+3,0) -> * | N53: =VLOOKUP($H$38&"-"&N$38,AllPAV,$E54+3,0) -> 1 | O53: =VLOOKUP($H$38&"-"&O$38,AllPAV,$E54+3,0) -> * | P53: =VLOOKUP($H$38&"-"&P$38,AllPAV,$E54+3,0) -> *
E54: =MOD(E52+12-IF($F$39,0,2),12)+1 -> 9 | F54: =INDEX(RsTbl,E54) -> Sg | G54: =VLOOKUP($H$38,BAV,E54+2,0) -> 2 | H54: 8/12 | I54: =I52+$I$31/12 -> 45244.021 | J54: =I54+$I$31/12/8 -> 45316.311 | K54: =J54+$I$31/12/8 -> 45388.601 | L54: =K54+$I$31/12/8 -> 45460.891 | M54: =L54+$I$31/12/8 -> 45533.181 | N54: =M54+$I$31/12/8 -> 45605.471 | O54: =N54+$I$31/12/8 -> 45677.761 | P54: =O54+$I$31/12/8 -> 45750.051 | Q54: =P54+$I$31/12/8 -> 45822.342
I55: =VLOOKUP($H$38&"-"&I$38,AllPAV,$E56+3,0) -> * | J55: =VLOOKUP($H$38&"-"&J$38,AllPAV,$E56+3,0) -> * | K55: =VLOOKUP($H$38&"-"&K$38,AllPAV,$E56+3,0) -> * | L55: =VLOOKUP($H$38&"-"&L$38,AllPAV,$E56+3,0) -> 1 | M55: =VLOOKUP($H$38&"-"&M$38,AllPAV,$E56+3,0) -> * | N55: =VLOOKUP($H$38&"-"&N$38,AllPAV,$E56+3,0) -> * | O55: =VLOOKUP($H$38&"-"&O$38,AllPAV,$E56+3,0) -> * | P55: =VLOOKUP($H$38&"-"&P$38,AllPAV,$E56+3,0) -> 1
E56: =MOD(E54+12-IF($F$39,0,2),12)+1 -> 10 | F56: =INDEX(RsTbl,E56) -> Cp | G56: =VLOOKUP($H$38,BAV,E56+2,0) -> 2 | H56: 9/12 | I56: =I54+$I$31/12 -> 45822.342 | J56: =I56+$I$31/12/8 -> 45894.632 | K56: =J56+$I$31/12/8 -> 45966.922 | L56: =K56+$I$31/12/8 -> 46039.212 | M56: =L56+$I$31/12/8 -> 46111.502 | N56: =M56+$I$31/12/8 -> 46183.792 | O56: =N56+$I$31/12/8 -> 46256.082 | P56: =O56+$I$31/12/8 -> 46328.372 | Q56: =P56+$I$31/12/8 -> 46400.662
I57: =VLOOKUP($H$38&"-"&I$38,AllPAV,$E58+3,0) -> * | J57: =VLOOKUP($H$38&"-"&J$38,AllPAV,$E58+3,0) -> * | K57: =VLOOKUP($H$38&"-"&K$38,AllPAV,$E58+3,0) -> * | L57: =VLOOKUP($H$38&"-"&L$38,AllPAV,$E58+3,0) -> 1 | M57: =VLOOKUP($H$38&"-"&M$38,AllPAV,$E58+3,0) -> * | N57: =VLOOKUP($H$38&"-"&N$38,AllPAV,$E58+3,0) -> 1 | O57: =VLOOKUP($H$38&"-"&O$38,AllPAV,$E58+3,0) -> * | P57: =VLOOKUP($H$38&"-"&P$38,AllPAV,$E58+3,0) -> *
E58: =MOD(E56+12-IF($F$39,0,2),12)+1 -> 11 | F58: =INDEX(RsTbl,E58) -> Aq | G58: =VLOOKUP($H$38,BAV,E58+2,0) -> 2 | H58: 10/12 | I58: =I56+$I$31/12 -> 46400.662 | J58: =I58+$I$31/12/8 -> 46472.952 | K58: =J58+$I$31/12/8 -> 46545.242 | L58: =K58+$I$31/12/8 -> 46617.532 | M58: =L58+$I$31/12/8 -> 46689.822 | N58: =M58+$I$31/12/8 -> 46762.112 | O58: =N58+$I$31/12/8 -> 46834.402 | P58: =O58+$I$31/12/8 -> 46906.692 | Q58: =P58+$I$31/12/8 -> 46978.982
I59: =VLOOKUP($H$38&"-"&I$38,AllPAV,$E60+3,0) -> 1 | J59: =VLOOKUP($H$38&"-"&J$38,AllPAV,$E60+3,0) -> 1 | K59: =VLOOKUP($H$38&"-"&K$38,AllPAV,$E60+3,0) -> 1 | L59: =VLOOKUP($H$38&"-"&L$38,AllPAV,$E60+3,0) -> * | M59: =VLOOKUP($H$38&"-"&M$38,AllPAV,$E60+3,0) -> * | N59: =VLOOKUP($H$38&"-"&N$38,AllPAV,$E60+3,0) -> 1 | O59: =VLOOKUP($H$38&"-"&O$38,AllPAV,$E60+3,0) -> 1 | P59: =VLOOKUP($H$38&"-"&P$38,AllPAV,$E60+3,0) -> *
E60: =MOD(E58+12-IF($F$39,0,2),12)+1 -> 12 | F60: =INDEX(RsTbl,E60) -> Pi | G60: =VLOOKUP($H$38,BAV,E60+2,0) -> 5 | H60: 11/12 | I60: =I58+$I$31/12 -> 46978.982 | J60: =I60+$I$31/12/8 -> 47051.272 | K60: =J60+$I$31/12/8 -> 47123.562 | L60: =K60+$I$31/12/8 -> 47195.852 | M60: =L60+$I$31/12/8 -> 47268.142 | N60: =M60+$I$31/12/8 -> 47340.432 | O60: =N60+$I$31/12/8 -> 47412.722 | P60: =O60+$I$31/12/8 -> 47485.012 | Q60: =P60+$I$31/12/8 -> 47557.302
I61: =VLOOKUP($H$38&"-"&I$38,AllPAV,$E62+3,0) -> * | J61: =VLOOKUP($H$38&"-"&J$38,AllPAV,$E62+3,0) -> 1 | K61: =VLOOKUP($H$38&"-"&K$38,AllPAV,$E62+3,0) -> * | L61: =VLOOKUP($H$38&"-"&L$38,AllPAV,$E62+3,0) -> 1 | M61: =VLOOKUP($H$38&"-"&M$38,AllPAV,$E62+3,0) -> 1 | N61: =VLOOKUP($H$38&"-"&N$38,AllPAV,$E62+3,0) -> 1 | O61: =VLOOKUP($H$38&"-"&O$38,AllPAV,$E62+3,0) -> * | P61: =VLOOKUP($H$38&"-"&P$38,AllPAV,$E62+3,0) -> *
E62: =MOD(E60+12-IF($F$39,0,2),12)+1 -> 1 | F62: =INDEX(RsTbl,E62) -> Ar | G62: =VLOOKUP($H$38,BAV,E62+2,0) -> 4 | H62: 12/12 | I62: =I60+$I$31/12 -> 47557.302 | J62: =I62+$I$31/12/8 -> 47629.592 | K62: =J62+$I$31/12/8 -> 47701.882 | L62: =K62+$I$31/12/8 -> 47774.172 | M62: =L62+$I$31/12/8 -> 47846.462 | N62: =M62+$I$31/12/8 -> 47918.752 | O62: =N62+$I$31/12/8 -> 47991.042 | P62: =O62+$I$31/12/8 -> 48063.332 | Q62: =P62+$I$31/12/8 -> 48135.622
A63: Breakup of MahaDasa | B63: 4 | C63: =VLOOKUP(B63,VimshottariDasa,2,0) -> Kshema
B64: Maha Dasa | D64: Antardasa/Bhukti | F64: Pratyantardasa
B65: =INDEX(DasaYears,MOD($D$15+$B$63-1,9)+1,1) -> Jupiter | C65: =VLOOKUP($B$63,VimshottariDasa,5,0) -> 35351.702 | D65: =INDEX(DasaYears,MOD(VLOOKUP(B65,DasaYears,3,0)+IF(VLOOKUP(B65,ChartInfo,11),-1,0),9)+1,1) -> #N/A | E65: =C65 -> 35351.702 | F65: =INDEX(DasaYears,MOD(VLOOKUP(D65,DasaYears,3,0)+IF(VLOOKUP(D65,ChartInfo,11),-1,0),9)+1,1) -> #N/A | G65: =E65 -> 35351.702
B66: =INDEX(DasaYears,MOD($D$15+$B$63-1,9)+1,1) -> Jupiter | D66: =INDEX(DasaYears,(MOD(VLOOKUP(D65,DasaYears,3,0)+IF(VLOOKUP(B66,ChartInfo,11),-1,1)*NOT(ISBLANK(E66)),9)+1),1) -> #N/A | F66: =INDEX(DasaYears,(MOD(VLOOKUP(F65,DasaYears,3,0)+IF(VLOOKUP(D66,ChartInfo,11),-1,1)*ISBLANK(H66),9)+1),1) -> #N/A | G66: =G65+DaysInYear*VLOOKUP(B65,DasaYears,2,0)*VLOOKUP(D65,DasaYears,2,0)/120*VLOOKUP(F65,DasaYears,2,0)/120 -> #N/A
B67: =INDEX(DasaYears,MOD($D$15+$B$63-1,9)+1,1) -> Jupiter | D67: =INDEX(DasaYears,(MOD(VLOOKUP(D66,DasaYears,3,0)+IF(VLOOKUP(B67,ChartInfo,11),-1,1)*NOT(ISBLANK(E67)),9)+1),1) -> #N/A | F67: =INDEX(DasaYears,(MOD(VLOOKUP(F66,DasaYears,3,0)+IF(VLOOKUP(D67,ChartInfo,11),-1,1)*ISBLANK(H67),9)+1),1) -> #N/A | G67: =G66+DaysInYear*VLOOKUP(B66,DasaYears,2,0)*VLOOKUP(D66,DasaYears,2,0)/120*VLOOKUP(F66,DasaYears,2,0)/120 -> #N/A
B68: =INDEX(DasaYears,MOD($D$15+$B$63-1,9)+1,1) -> Jupiter | D68: =INDEX(DasaYears,(MOD(VLOOKUP(D67,DasaYears,3,0)+IF(VLOOKUP(B68,ChartInfo,11),-1,1)*NOT(ISBLANK(E68)),9)+1),1) -> #N/A | F68: =INDEX(DasaYears,(MOD(VLOOKUP(F67,DasaYears,3,0)+IF(VLOOKUP(D68,ChartInfo,11),-1,1)*ISBLANK(H68),9)+1),1) -> #N/A | G68: =G67+DaysInYear*VLOOKUP(B67,DasaYears,2,0)*VLOOKUP(D67,DasaYears,2,0)/120*VLOOKUP(F67,DasaYears,2,0)/120 -> #N/A
B69: =INDEX(DasaYears,MOD($D$15+$B$63-1,9)+1,1) -> Jupiter | D69: =INDEX(DasaYears,(MOD(VLOOKUP(D68,DasaYears,3,0)+IF(VLOOKUP(B69,ChartInfo,11),-1,1)*NOT(ISBLANK(E69)),9)+1),1) -> #N/A | F69: =INDEX(DasaYears,(MOD(VLOOKUP(F68,DasaYears,3,0)+IF(VLOOKUP(D69,ChartInfo,11),-1,1)*ISBLANK(H69),9)+1),1) -> #N/A | G69: =G68+DaysInYear*VLOOKUP(B68,DasaYears,2,0)*VLOOKUP(D68,DasaYears,2,0)/120*VLOOKUP(F68,DasaYears,2,0)/120 -> #N/A
B70: =INDEX(DasaYears,MOD($D$15+$B$63-1,9)+1,1) -> Jupiter | D70: =INDEX(DasaYears,(MOD(VLOOKUP(D69,DasaYears,3,0)+IF(VLOOKUP(B70,ChartInfo,11),-1,1)*NOT(ISBLANK(E70)),9)+1),1) -> #N/A | F70: =INDEX(DasaYears,(MOD(VLOOKUP(F69,DasaYears,3,0)+IF(VLOOKUP(D70,ChartInfo,11),-1,1)*ISBLANK(H70),9)+1),1) -> #N/A | G70: =G69+DaysInYear*VLOOKUP(B69,DasaYears,2,0)*VLOOKUP(D69,DasaYears,2,0)/120*VLOOKUP(F69,DasaYears,2,0)/120 -> #N/A
B71: =INDEX(DasaYears,MOD($D$15+$B$63-1,9)+1,1) -> Jupiter | D71: =INDEX(DasaYears,(MOD(VLOOKUP(D70,DasaYears,3,0)+IF(VLOOKUP(B71,ChartInfo,11),-1,1)*NOT(ISBLANK(E71)),9)+1),1) -> #N/A | F71: =INDEX(DasaYears,(MOD(VLOOKUP(F70,DasaYears,3,0)+IF(VLOOKUP(D71,ChartInfo,11),-1,1)*ISBLANK(H71),9)+1),1) -> #N/A | G71: =G70+DaysInYear*VLOOKUP(B70,DasaYears,2,0)*VLOOKUP(D70,DasaYears,2,0)/120*VLOOKUP(F70,DasaYears,2,0)/120 -> #N/A
B72: =INDEX(DasaYears,MOD($D$15+$B$63-1,9)+1,1) -> Jupiter | D72: =INDEX(DasaYears,(MOD(VLOOKUP(D71,DasaYears,3,0)+IF(VLOOKUP(B72,ChartInfo,11),-1,1)*NOT(ISBLANK(E72)),9)+1),1) -> #N/A | F72: =INDEX(DasaYears,(MOD(VLOOKUP(F71,DasaYears,3,0)+IF(VLOOKUP(D72,ChartInfo,11),-1,1)*ISBLANK(H72),9)+1),1) -> #N/A | G72: =G71+DaysInYear*VLOOKUP(B71,DasaYears,2,0)*VLOOKUP(D71,DasaYears,2,0)/120*VLOOKUP(F71,DasaYears,2,0)/120 -> #N/A
B73: =INDEX(DasaYears,MOD($D$15+$B$63-1,9)+1,1) -> Jupiter | D73: =INDEX(DasaYears,(MOD(VLOOKUP(D72,DasaYears,3,0)+IF(VLOOKUP(B73,ChartInfo,11),-1,1)*NOT(ISBLANK(E73)),9)+1),1) -> #N/A | F73: =INDEX(DasaYears,(MOD(VLOOKUP(F72,DasaYears,3,0)+IF(VLOOKUP(D73,ChartInfo,11),-1,1)*ISBLANK(H73),9)+1),1) -> #N/A | G73: =G72+DaysInYear*VLOOKUP(B72,DasaYears,2,0)*VLOOKUP(D72,DasaYears,2,0)/120*VLOOKUP(F72,DasaYears,2,0)/120 -> #N/A
B74: =INDEX(DasaYears,MOD($D$15+$B$63-1,9)+1,1) -> Jupiter | D74: =INDEX(DasaYears,(MOD(VLOOKUP(D73,DasaYears,3,0)+IF(VLOOKUP(B74,ChartInfo,11),-1,1)*NOT(ISBLANK(E74)),9)+1),1) -> #N/A | E74: =E65+(VLOOKUP(B65,DasaYears,2,0)*VLOOKUP(D65,DasaYears,2,0)/VimTotal)*DaysInYear -> #N/A | F74: =INDEX(DasaYears,(MOD(VLOOKUP(F73,DasaYears,3,0)+IF(VLOOKUP(D74,ChartInfo,11),-1,1)*ISBLANK(H74),9)+1),1) -> #N/A | G74: =G73+DaysInYear*VLOOKUP(B73,DasaYears,2,0)*VLOOKUP(D73,DasaYears,2,0)/120*VLOOKUP(F73,DasaYears,2,0)/120 -> #N/A
B75: =INDEX(DasaYears,MOD($D$15+$B$63-1,9)+1,1) -> Jupiter | D75: =INDEX(DasaYears,(MOD(VLOOKUP(D74,DasaYears,3,0)+IF(VLOOKUP(B75,ChartInfo,11),-1,1)*NOT(ISBLANK(E75)),9)+1),1) -> #N/A | F75: =INDEX(DasaYears,(MOD(VLOOKUP(F74,DasaYears,3,0)+IF(VLOOKUP(D75,ChartInfo,11),-1,1)*ISBLANK(H75),9)+1),1) -> #N/A | G75: =G74+DaysInYear*VLOOKUP(B74,DasaYears,2,0)*VLOOKUP(D74,DasaYears,2,0)/120*VLOOKUP(F74,DasaYears,2,0)/120 -> #N/A
B76: =INDEX(DasaYears,MOD($D$15+$B$63-1,9)+1,1) -> Jupiter | D76: =INDEX(DasaYears,(MOD(VLOOKUP(D75,DasaYears,3,0)+IF(VLOOKUP(B76,ChartInfo,11),-1,1)*NOT(ISBLANK(E76)),9)+1),1) -> #N/A | F76: =INDEX(DasaYears,(MOD(VLOOKUP(F75,DasaYears,3,0)+IF(VLOOKUP(D76,ChartInfo,11),-1,1)*ISBLANK(H76),9)+1),1) -> #N/A | G76: =G75+DaysInYear*VLOOKUP(B75,DasaYears,2,0)*VLOOKUP(D75,DasaYears,2,0)/120*VLOOKUP(F75,DasaYears,2,0)/120 -> #N/A
B77: =INDEX(DasaYears,MOD($D$15+$B$63-1,9)+1,1) -> Jupiter | D77: =INDEX(DasaYears,(MOD(VLOOKUP(D76,DasaYears,3,0)+IF(VLOOKUP(B77,ChartInfo,11),-1,1)*NOT(ISBLANK(E77)),9)+1),1) -> #N/A | F77: =INDEX(DasaYears,(MOD(VLOOKUP(F76,DasaYears,3,0)+IF(VLOOKUP(D77,ChartInfo,11),-1,1)*ISBLANK(H77),9)+1),1) -> #N/A | G77: =G76+DaysInYear*VLOOKUP(B76,DasaYears,2,0)*VLOOKUP(D76,DasaYears,2,0)/120*VLOOKUP(F76,DasaYears,2,0)/120 -> #N/A
B78: =INDEX(DasaYears,MOD($D$15+$B$63-1,9)+1,1) -> Jupiter | D78: =INDEX(DasaYears,(MOD(VLOOKUP(D77,DasaYears,3,0)+IF(VLOOKUP(B78,ChartInfo,11),-1,1)*NOT(ISBLANK(E78)),9)+1),1) -> #N/A | F78: =INDEX(DasaYears,(MOD(VLOOKUP(F77,DasaYears,3,0)+IF(VLOOKUP(D78,ChartInfo,11),-1,1)*ISBLANK(H78),9)+1),1) -> #N/A | G78: =G77+DaysInYear*VLOOKUP(B77,DasaYears,2,0)*VLOOKUP(D77,DasaYears,2,0)/120*VLOOKUP(F77,DasaYears,2,0)/120 -> #N/A
B79: =INDEX(DasaYears,MOD($D$15+$B$63-1,9)+1,1) -> Jupiter | D79: =INDEX(DasaYears,(MOD(VLOOKUP(D78,DasaYears,3,0)+IF(VLOOKUP(B79,ChartInfo,11),-1,1)*NOT(ISBLANK(E79)),9)+1),1) -> #N/A | F79: =INDEX(DasaYears,(MOD(VLOOKUP(F78,DasaYears,3,0)+IF(VLOOKUP(D79,ChartInfo,11),-1,1)*ISBLANK(H79),9)+1),1) -> #N/A | G79: =G78+DaysInYear*VLOOKUP(B78,DasaYears,2,0)*VLOOKUP(D78,DasaYears,2,0)/120*VLOOKUP(F78,DasaYears,2,0)/120 -> #N/A
B80: =INDEX(DasaYears,MOD($D$15+$B$63-1,9)+1,1) -> Jupiter | D80: =INDEX(DasaYears,(MOD(VLOOKUP(D79,DasaYears,3,0)+IF(VLOOKUP(B80,ChartInfo,11),-1,1)*NOT(ISBLANK(E80)),9)+1),1) -> #N/A | F80: =INDEX(DasaYears,(MOD(VLOOKUP(F79,DasaYears,3,0)+IF(VLOOKUP(D80,ChartInfo,11),-1,1)*ISBLANK(H80),9)+1),1) -> #N/A | G80: =G79+DaysInYear*VLOOKUP(B79,DasaYears,2,0)*VLOOKUP(D79,DasaYears,2,0)/120*VLOOKUP(F79,DasaYears,2,0)/120 -> #N/A
B81: =INDEX(DasaYears,MOD($D$15+$B$63-1,9)+1,1) -> Jupiter | D81: =INDEX(DasaYears,(MOD(VLOOKUP(D80,DasaYears,3,0)+IF(VLOOKUP(B81,ChartInfo,11),-1,1)*NOT(ISBLANK(E81)),9)+1),1) -> #N/A | F81: =INDEX(DasaYears,(MOD(VLOOKUP(F80,DasaYears,3,0)+IF(VLOOKUP(D81,ChartInfo,11),-1,1)*ISBLANK(H81),9)+1),1) -> #N/A | G81: =G80+DaysInYear*VLOOKUP(B80,DasaYears,2,0)*VLOOKUP(D80,DasaYears,2,0)/120*VLOOKUP(F80,DasaYears,2,0)/120 -> #N/A
B82: =INDEX(DasaYears,MOD($D$15+$B$63-1,9)+1,1) -> Jupiter | D82: =INDEX(DasaYears,(MOD(VLOOKUP(D81,DasaYears,3,0)+IF(VLOOKUP(B82,ChartInfo,11),-1,1)*NOT(ISBLANK(E82)),9)+1),1) -> #N/A | F82: =INDEX(DasaYears,(MOD(VLOOKUP(F81,DasaYears,3,0)+IF(VLOOKUP(D82,ChartInfo,11),-1,1)*ISBLANK(H82),9)+1),1) -> #N/A | G82: =G81+DaysInYear*VLOOKUP(B81,DasaYears,2,0)*VLOOKUP(D81,DasaYears,2,0)/120*VLOOKUP(F81,DasaYears,2,0)/120 -> #N/A
B83: =INDEX(DasaYears,MOD($D$15+$B$63-1,9)+1,1) -> Jupiter | D83: =INDEX(DasaYears,(MOD(VLOOKUP(D82,DasaYears,3,0)+IF(VLOOKUP(B83,ChartInfo,11),-1,1)*NOT(ISBLANK(E83)),9)+1),1) -> #N/A | E83: =E74+(VLOOKUP(B74,DasaYears,2,0)*VLOOKUP(D74,DasaYears,2,0)/VimTotal)*DaysInYear -> #N/A | F83: =INDEX(DasaYears,(MOD(VLOOKUP(F82,DasaYears,3,0)+IF(VLOOKUP(D83,ChartInfo,11),-1,1)*ISBLANK(H83),9)+1),1) -> #N/A | G83: =G82+DaysInYear*VLOOKUP(B82,DasaYears,2,0)*VLOOKUP(D82,DasaYears,2,0)/120*VLOOKUP(F82,DasaYears,2,0)/120 -> #N/A
B84: =INDEX(DasaYears,MOD($D$15+$B$63-1,9)+1,1) -> Jupiter | D84: =INDEX(DasaYears,(MOD(VLOOKUP(D83,DasaYears,3,0)+IF(VLOOKUP(B84,ChartInfo,11),-1,1)*NOT(ISBLANK(E84)),9)+1),1) -> #N/A | F84: =INDEX(DasaYears,(MOD(VLOOKUP(F83,DasaYears,3,0)+IF(VLOOKUP(D84,ChartInfo,11),-1,1)*ISBLANK(H84),9)+1),1) -> #N/A | G84: =G83+DaysInYear*VLOOKUP(B83,DasaYears,2,0)*VLOOKUP(D83,DasaYears,2,0)/120*VLOOKUP(F83,DasaYears,2,0)/120 -> #N/A
B85: =INDEX(DasaYears,MOD($D$15+$B$63-1,9)+1,1) -> Jupiter | D85: =INDEX(DasaYears,(MOD(VLOOKUP(D84,DasaYears,3,0)+IF(VLOOKUP(B85,ChartInfo,11),-1,1)*NOT(ISBLANK(E85)),9)+1),1) -> #N/A | F85: =INDEX(DasaYears,(MOD(VLOOKUP(F84,DasaYears,3,0)+IF(VLOOKUP(D85,ChartInfo,11),-1,1)*ISBLANK(H85),9)+1),1) -> #N/A | G85: =G84+DaysInYear*VLOOKUP(B84,DasaYears,2,0)*VLOOKUP(D84,DasaYears,2,0)/120*VLOOKUP(F84,DasaYears,2,0)/120 -> #N/A
B86: =INDEX(DasaYears,MOD($D$15+$B$63-1,9)+1,1) -> Jupiter | D86: =INDEX(DasaYears,(MOD(VLOOKUP(D85,DasaYears,3,0)+IF(VLOOKUP(B86,ChartInfo,11),-1,1)*NOT(ISBLANK(E86)),9)+1),1) -> #N/A | F86: =INDEX(DasaYears,(MOD(VLOOKUP(F85,DasaYears,3,0)+IF(VLOOKUP(D86,ChartInfo,11),-1,1)*ISBLANK(H86),9)+1),1) -> #N/A | G86: =G85+DaysInYear*VLOOKUP(B85,DasaYears,2,0)*VLOOKUP(D85,DasaYears,2,0)/120*VLOOKUP(F85,DasaYears,2,0)/120 -> #N/A
B87: =INDEX(DasaYears,MOD($D$15+$B$63-1,9)+1,1) -> Jupiter | D87: =INDEX(DasaYears,(MOD(VLOOKUP(D86,DasaYears,3,0)+IF(VLOOKUP(B87,ChartInfo,11),-1,1)*NOT(ISBLANK(E87)),9)+1),1) -> #N/A | F87: =INDEX(DasaYears,(MOD(VLOOKUP(F86,DasaYears,3,0)+IF(VLOOKUP(D87,ChartInfo,11),-1,1)*ISBLANK(H87),9)+1),1) -> #N/A | G87: =G86+DaysInYear*VLOOKUP(B86,DasaYears,2,0)*VLOOKUP(D86,DasaYears,2,0)/120*VLOOKUP(F86,DasaYears,2,0)/120 -> #N/A
B88: =INDEX(DasaYears,MOD($D$15+$B$63-1,9)+1,1) -> Jupiter | D88: =INDEX(DasaYears,(MOD(VLOOKUP(D87,DasaYears,3,0)+IF(VLOOKUP(B88,ChartInfo,11),-1,1)*NOT(ISBLANK(E88)),9)+1),1) -> #N/A | F88: =INDEX(DasaYears,(MOD(VLOOKUP(F87,DasaYears,3,0)+IF(VLOOKUP(D88,ChartInfo,11),-1,1)*ISBLANK(H88),9)+1),1) -> #N/A | G88: =G87+DaysInYear*VLOOKUP(B87,DasaYears,2,0)*VLOOKUP(D87,DasaYears,2,0)/120*VLOOKUP(F87,DasaYears,2,0)/120 -> #N/A
B89: =INDEX(DasaYears,MOD($D$15+$B$63-1,9)+1,1) -> Jupiter | D89: =INDEX(DasaYears,(MOD(VLOOKUP(D88,DasaYears,3,0)+IF(VLOOKUP(B89,ChartInfo,11),-1,1)*NOT(ISBLANK(E89)),9)+1),1) -> #N/A | F89: =INDEX(DasaYears,(MOD(VLOOKUP(F88,DasaYears,3,0)+IF(VLOOKUP(D89,ChartInfo,11),-1,1)*ISBLANK(H89),9)+1),1) -> #N/A | G89: =G88+DaysInYear*VLOOKUP(B88,DasaYears,2,0)*VLOOKUP(D88,DasaYears,2,0)/120*VLOOKUP(F88,DasaYears,2,0)/120 -> #N/A
B90: =INDEX(DasaYears,MOD($D$15+$B$63-1,9)+1,1) -> Jupiter | D90: =INDEX(DasaYears,(MOD(VLOOKUP(D89,DasaYears,3,0)+IF(VLOOKUP(B90,ChartInfo,11),-1,1)*NOT(ISBLANK(E90)),9)+1),1) -> #N/A | F90: =INDEX(DasaYears,(MOD(VLOOKUP(F89,DasaYears,3,0)+IF(VLOOKUP(D90,ChartInfo,11),-1,1)*ISBLANK(H90),9)+1),1) -> #N/A | G90: =G89+DaysInYear*VLOOKUP(B89,DasaYears,2,0)*VLOOKUP(D89,DasaYears,2,0)/120*VLOOKUP(F89,DasaYears,2,0)/120 -> #N/A
B91: =INDEX(DasaYears,MOD($D$15+$B$63-1,9)+1,1) -> Jupiter | D91: =INDEX(DasaYears,(MOD(VLOOKUP(D90,DasaYears,3,0)+IF(VLOOKUP(B91,ChartInfo,11),-1,1)*NOT(ISBLANK(E91)),9)+1),1) -> #N/A | F91: =INDEX(DasaYears,(MOD(VLOOKUP(F90,DasaYears,3,0)+IF(VLOOKUP(D91,ChartInfo,11),-1,1)*ISBLANK(H91),9)+1),1) -> #N/A | G91: =G90+DaysInYear*VLOOKUP(B90,DasaYears,2,0)*VLOOKUP(D90,DasaYears,2,0)/120*VLOOKUP(F90,DasaYears,2,0)/120 -> #N/A
B92: =INDEX(DasaYears,MOD($D$15+$B$63-1,9)+1,1) -> Jupiter | D92: =INDEX(DasaYears,(MOD(VLOOKUP(D91,DasaYears,3,0)+IF(VLOOKUP(B92,ChartInfo,11),-1,1)*NOT(ISBLANK(E92)),9)+1),1) -> #N/A | E92: =E83+(VLOOKUP(B83,DasaYears,2,0)*VLOOKUP(D83,DasaYears,2,0)/VimTotal)*DaysInYear -> #N/A | F92: =INDEX(DasaYears,(MOD(VLOOKUP(F91,DasaYears,3,0)+IF(VLOOKUP(D92,ChartInfo,11),-1,1)*ISBLANK(H92),9)+1),1) -> #N/A | G92: =G91+DaysInYear*VLOOKUP(B91,DasaYears,2,0)*VLOOKUP(D91,DasaYears,2,0)/120*VLOOKUP(F91,DasaYears,2,0)/120 -> #N/A
B93: =INDEX(DasaYears,MOD($D$15+$B$63-1,9)+1,1) -> Jupiter | D93: =INDEX(DasaYears,(MOD(VLOOKUP(D92,DasaYears,3,0)+IF(VLOOKUP(B93,ChartInfo,11),-1,1)*NOT(ISBLANK(E93)),9)+1),1) -> #N/A | F93: =INDEX(DasaYears,(MOD(VLOOKUP(F92,DasaYears,3,0)+IF(VLOOKUP(D93,ChartInfo,11),-1,1)*ISBLANK(H93),9)+1),1) -> #N/A | G93: =G92+DaysInYear*VLOOKUP(B92,DasaYears,2,0)*VLOOKUP(D92,DasaYears,2,0)/120*VLOOKUP(F92,DasaYears,2,0)/120 -> #N/A
B94: =INDEX(DasaYears,MOD($D$15+$B$63-1,9)+1,1) -> Jupiter | D94: =INDEX(DasaYears,(MOD(VLOOKUP(D93,DasaYears,3,0)+IF(VLOOKUP(B94,ChartInfo,11),-1,1)*NOT(ISBLANK(E94)),9)+1),1) -> #N/A | F94: =INDEX(DasaYears,(MOD(VLOOKUP(F93,DasaYears,3,0)+IF(VLOOKUP(D94,ChartInfo,11),-1,1)*ISBLANK(H94),9)+1),1) -> #N/A | G94: =G93+DaysInYear*VLOOKUP(B93,DasaYears,2,0)*VLOOKUP(D93,DasaYears,2,0)/120*VLOOKUP(F93,DasaYears,2,0)/120 -> #N/A
B95: =INDEX(DasaYears,MOD($D$15+$B$63-1,9)+1,1) -> Jupiter | D95: =INDEX(DasaYears,(MOD(VLOOKUP(D94,DasaYears,3,0)+IF(VLOOKUP(B95,ChartInfo,11),-1,1)*NOT(ISBLANK(E95)),9)+1),1) -> #N/A | F95: =INDEX(DasaYears,(MOD(VLOOKUP(F94,DasaYears,3,0)+IF(VLOOKUP(D95,ChartInfo,11),-1,1)*ISBLANK(H95),9)+1),1) -> #N/A | G95: =G94+DaysInYear*VLOOKUP(B94,DasaYears,2,0)*VLOOKUP(D94,DasaYears,2,0)/120*VLOOKUP(F94,DasaYears,2,0)/120 -> #N/A
B96: =INDEX(DasaYears,MOD($D$15+$B$63-1,9)+1,1) -> Jupiter | D96: =INDEX(DasaYears,(MOD(VLOOKUP(D95,DasaYears,3,0)+IF(VLOOKUP(B96,ChartInfo,11),-1,1)*NOT(ISBLANK(E96)),9)+1),1) -> #N/A | F96: =INDEX(DasaYears,(MOD(VLOOKUP(F95,DasaYears,3,0)+IF(VLOOKUP(D96,ChartInfo,11),-1,1)*ISBLANK(H96),9)+1),1) -> #N/A | G96: =G95+DaysInYear*VLOOKUP(B95,DasaYears,2,0)*VLOOKUP(D95,DasaYears,2,0)/120*VLOOKUP(F95,DasaYears,2,0)/120 -> #N/A
B97: =INDEX(DasaYears,MOD($D$15+$B$63-1,9)+1,1) -> Jupiter | D97: =INDEX(DasaYears,(MOD(VLOOKUP(D96,DasaYears,3,0)+IF(VLOOKUP(B97,ChartInfo,11),-1,1)*NOT(ISBLANK(E97)),9)+1),1) -> #N/A | F97: =INDEX(DasaYears,(MOD(VLOOKUP(F96,DasaYears,3,0)+IF(VLOOKUP(D97,ChartInfo,11),-1,1)*ISBLANK(H97),9)+1),1) -> #N/A | G97: =G96+DaysInYear*VLOOKUP(B96,DasaYears,2,0)*VLOOKUP(D96,DasaYears,2,0)/120*VLOOKUP(F96,DasaYears,2,0)/120 -> #N/A
B98: =INDEX(DasaYears,MOD($D$15+$B$63-1,9)+1,1) -> Jupiter | D98: =INDEX(DasaYears,(MOD(VLOOKUP(D97,DasaYears,3,0)+IF(VLOOKUP(B98,ChartInfo,11),-1,1)*NOT(ISBLANK(E98)),9)+1),1) -> #N/A | F98: =INDEX(DasaYears,(MOD(VLOOKUP(F97,DasaYears,3,0)+IF(VLOOKUP(D98,ChartInfo,11),-1,1)*ISBLANK(H98),9)+1),1) -> #N/A | G98: =G97+DaysInYear*VLOOKUP(B97,DasaYears,2,0)*VLOOKUP(D97,DasaYears,2,0)/120*VLOOKUP(F97,DasaYears,2,0)/120 -> #N/A
A99: > | B99: =INDEX(DasaYears,MOD($D$15+$B$63-1,9)+1,1) -> Jupiter | D99: =INDEX(DasaYears,(MOD(VLOOKUP(D98,DasaYears,3,0)+IF(VLOOKUP(B99,ChartInfo,11),-1,1)*NOT(ISBLANK(E99)),9)+1),1) -> #N/A | F99: =INDEX(DasaYears,(MOD(VLOOKUP(F98,DasaYears,3,0)+IF(VLOOKUP(D99,ChartInfo,11),-1,1)*ISBLANK(H99),9)+1),1) -> #N/A | G99: =G98+DaysInYear*VLOOKUP(B98,DasaYears,2,0)*VLOOKUP(D98,DasaYears,2,0)/120*VLOOKUP(F98,DasaYears,2,0)/120 -> #N/A
B100: =INDEX(DasaYears,MOD($D$15+$B$63-1,9)+1,1) -> Jupiter | D100: =INDEX(DasaYears,(MOD(VLOOKUP(D99,DasaYears,3,0)+IF(VLOOKUP(B100,ChartInfo,11),-1,1)*NOT(ISBLANK(E100)),9)+1),1) -> #N/A | F100: =INDEX(DasaYears,(MOD(VLOOKUP(F99,DasaYears,3,0)+IF(VLOOKUP(D100,ChartInfo,11),-1,1)*ISBLANK(H100),9)+1),1) -> #N/A | G100: =G99+DaysInYear*VLOOKUP(B99,DasaYears,2,0)*VLOOKUP(D99,DasaYears,2,0)/120*VLOOKUP(F99,DasaYears,2,0)/120 -> #N/A
B101: =INDEX(DasaYears,MOD($D$15+$B$63-1,9)+1,1) -> Jupiter | D101: =INDEX(DasaYears,(MOD(VLOOKUP(D100,DasaYears,3,0)+IF(VLOOKUP(B101,ChartInfo,11),-1,1)*NOT(ISBLANK(E101)),9)+1),1) -> #N/A | E101: =E92+(VLOOKUP(B92,DasaYears,2,0)*VLOOKUP(D92,DasaYears,2,0)/VimTotal)*DaysInYear -> #N/A | F101: =INDEX(DasaYears,(MOD(VLOOKUP(F100,DasaYears,3,0)+IF(VLOOKUP(D101,ChartInfo,11),-1,1)*ISBLANK(H101),9)+1),1) -> #N/A | G101: =G100+DaysInYear*VLOOKUP(B100,DasaYears,2,0)*VLOOKUP(D100,DasaYears,2,0)/120*VLOOKUP(F100,DasaYears,2,0)/120 -> #N/A
B102: =INDEX(DasaYears,MOD($D$15+$B$63-1,9)+1,1) -> Jupiter | D102: =INDEX(DasaYears,(MOD(VLOOKUP(D101,DasaYears,3,0)+IF(VLOOKUP(B102,ChartInfo,11),-1,1)*NOT(ISBLANK(E102)),9)+1),1) -> #N/A | F102: =INDEX(DasaYears,(MOD(VLOOKUP(F101,DasaYears,3,0)+IF(VLOOKUP(D102,ChartInfo,11),-1,1)*ISBLANK(H102),9)+1),1) -> #N/A | G102: =G101+DaysInYear*VLOOKUP(B101,DasaYears,2,0)*VLOOKUP(D101,DasaYears,2,0)/120*VLOOKUP(F101,DasaYears,2,0)/120 -> #N/A
B103: =INDEX(DasaYears,MOD($D$15+$B$63-1,9)+1,1) -> Jupiter | D103: =INDEX(DasaYears,(MOD(VLOOKUP(D102,DasaYears,3,0)+IF(VLOOKUP(B103,ChartInfo,11),-1,1)*NOT(ISBLANK(E103)),9)+1),1) -> #N/A | F103: =INDEX(DasaYears,(MOD(VLOOKUP(F102,DasaYears,3,0)+IF(VLOOKUP(D103,ChartInfo,11),-1,1)*ISBLANK(H103),9)+1),1) -> #N/A | G103: =G102+DaysInYear*VLOOKUP(B102,DasaYears,2,0)*VLOOKUP(D102,DasaYears,2,0)/120*VLOOKUP(F102,DasaYears,2,0)/120 -> #N/A
...

Sheet Vimshottari@Date
A1: Vimshottari seed | N1: =jhora #REF! -> #NAME? | O1: =jhora #REF! -> #NAME?
A2: =Basics!A9 -> Moon | N2: =jhora #REF! -> #NAME? | O2: =jhora #REF! -> #NAME?
A3: Vimsottari Degree | B3: =VLOOKUP(A2,ChartInfo,7,0) -> 53.015944 | N3: =JHora!B4 -> 37926 | O3: =JHora!C4 -> Bought Car D16
A4: Starting Dasa | B4: =INDEX(DasaYears,D4+1,1) -> Moon | D4: =MOD(FLOOR(B3/StarDeg,1),9) -> 3 | E4: =INDEX(DasaYears,MOD(FLOOR(B3/StarDeg,1),9)+1,2) -> 10 | N4: =JHora!B5 -> 38779 | O4: =JHora!C5 -> Marriage D9
A5: Balance Of Dasa | B5: =((StarDeg-MOD(B3,StarDeg))/StarDeg)*E4 -> 0.23804167 | I5: =MATCH(C16,ChartInfo,0) -> #VALUE! | N5: =JHora!B6 -> 41694 | O5: =JHora!C6 -> Bought Car D16
A6: Dasa Past | E6: =((MOD(B3,StarDeg))/StarDeg)*E4-F6/DaysInYear -> 9.7619583 | F6: 0 | G6: =Vimshottari!H18 -> <-Corrections Days | I6: =VLOOKUP(C16,ChartInfo,11,0) -> 0 | N6: =JHora!B7 -> 0 | O6: =JHora!C7 -> 0
A7: Calculate Retrograde? | B7: =TRUE() -> TRUE | I7: =IF(VLOOKUP(C16,ChartInfo,11,0),1,0)*B17 -> 0 | N7: =JHora!B8 -> 0 | O7: =JHora!C8 -> 0
A8: DaysInYear | B8: =DaysInYear -> 365.25487 | N8: =JHora!B9 -> 0 | O8: =JHora!C9 -> 0
N9: =JHora!B10 -> 0 | O9: =JHora!C10 -> 0
B10: Birth Dasa | C10: Dasa | D10: Antar/Bhukti | E10: Pratyantar | F10: Sookshma | G10: Praana | H10: Deha | I10: On Date | J10: Event Remarks | K10: Show? | N10: =JHora!B11 -> 0 | O10: =JHora!C11 -> 0
A11: Start Date | B11: =DoB-$E$6*DaysInYear -> 22567.781 | C11: =B11+B13*INDEX(INDEX(VimFrac,,VLOOKUP(B16,PlanetData,3,0)+1),MATCH(B14,INDEX(VimFrac,,VLOOKUP(B16,PlanetData,3,0)+1),1)) -> 41195.78 | D11: =C11+C13*INDEX(INDEX(VimFrac,0,9*C17+VLOOKUP(C16,PlanetData,3,0)+1),IF(C17,1,0)+MATCH(C14,INDEX(VimFrac,0,9*C17+VLOOKUP(C16,PlanetData,3,0)+1),IF(C17,-1,1))) -> 45764.51 | E11: =D11+D13*INDEX(INDEX(VimFrac,0,9*D17+VLOOKUP(D16,PlanetData,3,0)+1),IF(D17,1,0)+MATCH(D14,INDEX(VimFrac,0,9*D17+VLOOKUP(D16,PlanetData,3,0)+1),IF(D17,-1,1))) -> 45909.571 | F11: =E11+E13*INDEX(INDEX(VimFrac,0,9*E17+VLOOKUP(E16,PlanetData,3,0)+1),IF(E17,1,0)+MATCH(E14,INDEX(VimFrac,0,9*E17+VLOOKUP(E16,PlanetData,3,0)+1),IF(E17,-1,1))) -> 45950.194 | G11: =F11+F13*INDEX(INDEX(VimFrac,0,9*F17+VLOOKUP(F16,PlanetData,3,0)+1),IF(F17,1,0)+MATCH(F14,INDEX(VimFrac,0,9*F17+VLOOKUP(F16,PlanetData,3,0)+1),IF(F17,-1,1))) -> 45951.341 | H11: =G11+G13*INDEX(INDEX(VimFrac,0,9*G17+VLOOKUP(G16,PlanetData,3,0)+1),IF(G17,1,0)+MATCH(G14,INDEX(VimFrac,0,9*G17+VLOOKUP(G16,PlanetData,3,0)+1),IF(G17,-1,1))) -> 45951.401 | J11: =J12 -> Now() The current dasa | K11: 1 | N11: =JHora!B12 -> 0 | O11: =JHora!C12 -> 0
A12: End Date | B12: =B11+B13 -> 66398.366 | C12: =B11+B13*INDEX(INDEX(VimFrac,,VLOOKUP(B16,PlanetData,3,0)+1),MATCH(B14,INDEX(VimFrac,,VLOOKUP(B16,PlanetData,3,0)+1),1)+1) -> 48135.622 | D12: =C11+C13*INDEX(INDEX(VimFrac,0,9*C17+VLOOKUP(C16,PlanetData,3,0)+1),IF(C17,0,1)+MATCH(C14,INDEX(VimFrac,0,9*C17+VLOOKUP(C16,PlanetData,3,0)+1),IF(C17,-1,1))) -> 46169.334 | E12: =D11+D13*INDEX(INDEX(VimFrac,0,9*D17+VLOOKUP(D16,PlanetData,3,0)+1),IF(D17,0,1)+MATCH(D14,INDEX(VimFrac,0,9*D17+VLOOKUP(D16,PlanetData,3,0)+1),IF(D17,-1,1))) -> 45966.922 | F12: =E11+E13*INDEX(INDEX(VimFrac,0,9*E17+VLOOKUP(E16,PlanetData,3,0)+1),IF(E17,0,1)+MATCH(E14,INDEX(VimFrac,0,9*E17+VLOOKUP(E16,PlanetData,3,0)+1),IF(E17,-1,1))) -> 45957.841 | G12: =F11+F13*INDEX(INDEX(VimFrac,0,9*F17+VLOOKUP(F16,PlanetData,3,0)+1),IF(F17,0,1)+MATCH(F14,INDEX(VimFrac,0,9*F17+VLOOKUP(F16,PlanetData,3,0)+1),IF(F17,-1,1))) -> 45951.788 | H12: =G11+G13*INDEX(INDEX(VimFrac,0,9*G17+VLOOKUP(G16,PlanetData,3,0)+1),IF(G17,0,1)+MATCH(G14,INDEX(VimFrac,0,9*G17+VLOOKUP(G16,PlanetData,3,0)+1),IF(G17,-1,1))) -> 45951.475 | J12: =J16 -> Now() The current dasa | K12: 1 | N12: =JHora!B13 -> 0 | O12: =JHora!C13 -> 0
A13: Cycle Duration Days | B13: =120*DaysInYear -> 43830.585 | C13: =C12-C11 -> 6939.8426 | D13: =D12-D11 -> 404.82415 | E13: =E12-E11 -> 57.350088 | F13: =F12-F11 -> 7.6466784 | G13: =G12-G11 -> 0.44605624 | H13: =H12-H11 -> 0.074342707 | K13: 0
A14: %Frac Past in Cyc | B14: =(I16-B11)/(B12-B11) -> 0.53350145 | C14: =(I16-C11)/(C12-C11) -> 0.6852723 | D14: =(I16-D11)/(D12-D11) -> 0.46181085 | E14: =(I16-E11)/(E12-E11) -> 0.73042955 | F14: =(I16-F11)/(F12-F11) -> 0.16572159 | G14: =(I16-G11)/(G12-G11) -> 0.26951293 | H14: =(I16-H11)/(H12-H11) -> 0.8170776 | K14: 0
A15: Dasa# @ Given time | C15: =MOD(VLOOKUP(B16,PlanetData,3,0)+MATCH(B14,INDEX(VimFrac,,VLOOKUP(B16,PlanetData,3,0)+1),1)-1,9) -> 8 | D15: =MOD(VLOOKUP(C16,PlanetData,3,0)+MATCH(C14,INDEX(VimFrac,0,9*C17+VLOOKUP(C16,PlanetData,3,0)+1),IF(C17,-1,1))-1,9) -> 5 | E15: =MOD(VLOOKUP(D16,PlanetData,3,0)+MATCH(D14,INDEX(VimFrac,0,9*D17+VLOOKUP(D16,PlanetData,3,0)+1),IF(D17,-1,1))-1,9) -> 0 | F15: =MOD(VLOOKUP(E16,PlanetData,3,0)+MATCH(E14,INDEX(VimFrac,0,9*E17+VLOOKUP(E16,PlanetData,3,0)+1),IF(E17,-1,1))-1,9) -> 7 | G15: =MOD(VLOOKUP(F16,PlanetData,3,0)+MATCH(F14,INDEX(VimFrac,0,9*F17+VLOOKUP(F16,PlanetData,3,0)+1),IF(F17,-1,1))-1,9) -> 5 | H15: =MOD(VLOOKUP(G16,PlanetData,3,0)+MATCH(G14,INDEX(VimFrac,0,9*G17+VLOOKUP(G16,PlanetData,3,0)+1),IF(G17,-1,1))-1,9) -> 2 | I15: =StarDeg*(C15-1)+(D15-1)*POWER(StarDeg,2)/120+(E15-1)*POWER(StarDeg,3)/POWER(120,2)+(F15-1)*POWER(StarDeg,4)/POWER(120,3)+(G15-1)*POWER(StarDeg,5)/POWER(120,4)+(H15-1)*POWER(StarDeg,6)/POWER(120,5) -> 99.212744 | K15: 0
A16: Dasa @ Given time | B16: =$B$4 -> Moon | C16: =INDEX(DasaYears,IF(C15=0,9,C15),1) -> Saturn | D16: =INDEX(DasaYears,IF(D15=0,9,D15),1) -> Mars | E16: =INDEX(DasaYears,IF(E15=0,9,E15),1) -> Mercury | F16: =INDEX(DasaYears,IF(F15=0,9,F15),1) -> Jupiter | G16: =INDEX(DasaYears,IF(G15=0,9,G15),1) -> Mars | H16: =INDEX(DasaYears,IF(H15=0,9,H15),1) -> Venus | I16: =NOW() -> 45951.462 | J16: Now() The current dasa | K16: 1 | N16: =JHora!B17 -> 0 | O16: =JHora!C17 -> 0
A17: Calculate Retrograde? | B17: =$B$7 -> TRUE | C17: =IF(VLOOKUP(C16,ChartInfo,11,0),1,0)*B17 -> 0 | D17: =IF(VLOOKUP(D16,ChartInfo,11,0),1,0)*B17 -> 1 | E17: =IF(VLOOKUP(E16,ChartInfo,11,0),1,0)*B17 -> 0 | F17: =IF(VLOOKUP(F16,ChartInfo,11,0),1,0)*B17 -> 1 | G17: =IF(VLOOKUP(G16,ChartInfo,11,0),1,0)*B17 -> 1 | H17: =IF(VLOOKUP(H16,ChartInfo,11,0),1,0)*B17 -> 0 | K17: 0
K18: 1 | N18: =JHora!B19 -> 0 | O18: =JHora!C19 -> 0
A19: Start Date | B19: =DoB-$E$6*DaysInYear -> 22567.781 | C19: =B19+B21*INDEX(INDEX(VimFrac,,VLOOKUP(B24,PlanetData,3,0)+1),MATCH(B22,INDEX(VimFrac,,VLOOKUP(B24,PlanetData,3,0)+1),1)) -> 22567.781 | D19: =C19+C21*INDEX(INDEX(VimFrac,0,9*C25+VLOOKUP(C24,PlanetData,3,0)+1),IF(C25,1,0)+MATCH(C22,INDEX(VimFrac,0,9*C25+VLOOKUP(C24,PlanetData,3,0)+1),IF(C25,-1,1))) -> 26037.703 | E19: =D19+D21*INDEX(INDEX(VimFrac,0,9*D25+VLOOKUP(D24,PlanetData,3,0)+1),IF(D25,1,0)+MATCH(D22,INDEX(VimFrac,0,9*D25+VLOOKUP(D24,PlanetData,3,0)+1),IF(D25,-1,1))) -> 26124.451 | F19: =E19+E21*INDEX(INDEX(VimFrac,0,9*E25+VLOOKUP(E24,PlanetData,3,0)+1),IF(E25,1,0)+MATCH(E22,INDEX(VimFrac,0,9*E25+VLOOKUP(E24,PlanetData,3,0)+1),IF(E25,-1,1))) -> 26129.029 | G19: =F19+F21*INDEX(INDEX(VimFrac,0,9*F25+VLOOKUP(F24,PlanetData,3,0)+1),IF(F25,1,0)+MATCH(F22,INDEX(VimFrac,0,9*F25+VLOOKUP(F24,PlanetData,3,0)+1),IF(F25,-1,1))) -> 26132.477 | H19: =G19+G21*INDEX(INDEX(VimFrac,0,9*G25+VLOOKUP(G24,PlanetData,3,0)+1),IF(G25,1,0)+MATCH(G22,INDEX(VimFrac,0,9*G25+VLOOKUP(G24,PlanetData,3,0)+1),IF(G25,-1,1))) -> 26132.942 | J19: =J24 -> Born in CIM Stores | K19: =K11+1 -> 2 | N19: =JHora!B20 -> 0 | O19: =JHora!C20 -> 0
A20: End Date | B20: =B19+B21 -> 66398.366 | C20: =B19+B21*INDEX(INDEX(VimFrac,,VLOOKUP(B24,PlanetData,3,0)+1),MATCH(B22,INDEX(VimFrac,,VLOOKUP(B24,PlanetData,3,0)+1),1)+1) -> 26220.33 | D20: =C19+C21*INDEX(INDEX(VimFrac,0,9*C25+VLOOKUP(C24,PlanetData,3,0)+1),IF(C25,0,1)+MATCH(C22,INDEX(VimFrac,0,9*C25+VLOOKUP(C24,PlanetData,3,0)+1),IF(C25,-1,1))) -> 26220.33 | E20: =D19+D21*INDEX(INDEX(VimFrac,0,9*D25+VLOOKUP(D24,PlanetData,3,0)+1),IF(D25,0,1)+MATCH(D22,INDEX(VimFrac,0,9*D25+VLOOKUP(D24,PlanetData,3,0)+1),IF(D25,-1,1))) -> 26153.367 | F20: =E19+E21*INDEX(INDEX(VimFrac,0,9*E25+VLOOKUP(E24,PlanetData,3,0)+1),IF(E25,0,1)+MATCH(E22,INDEX(VimFrac,0,9*E25+VLOOKUP(E24,PlanetData,3,0)+1),IF(E25,-1,1))) -> 26133.125 | G20: =F19+F21*INDEX(INDEX(VimFrac,0,9*F25+VLOOKUP(F24,PlanetData,3,0)+1),IF(F25,0,1)+MATCH(F22,INDEX(VimFrac,0,9*F25+VLOOKUP(F24,PlanetData,3,0)+1),IF(F25,-1,1))) -> 26133.125 | H20: =G19+G21*INDEX(INDEX(VimFrac,0,9*G25+VLOOKUP(G24,PlanetData,3,0)+1),IF(G25,0,1)+MATCH(G22,INDEX(VimFrac,0,9*G25+VLOOKUP(G24,PlanetData,3,0)+1),IF(G25,-1,1))) -> 26133.039 | J20: =J24 -> Born in CIM Stores | K20: =K12+1 -> 2 | N20: =JHora!B21 -> 0 | O20: =JHora!C21 -> 0
A21: Cycle Duration Days | B21: =120*DaysInYear -> 43830.585 | C21: =C20-C19 -> 3652.5487 | D21: =D20-D19 -> 182.62744 | E21: =E20-E19 -> 28.916011 | F21: =F20-F19 -> 4.0964349 | G21: =G20-G19 -> 0.64860219 | H21: =H20-H19 -> 0.097290328 | K21: =K13 -> 0
A22: %Frac Past in Cyc | B22: =(I24-B19)/(B20-B19) -> 0.081340888 | C22: =(I24-C19)/(C20-C19) -> 0.97609066 | D22: =(I24-D19)/(D20-D19) -> 0.52181324 | E22: =(I24-E19)/(E20-E19) -> 0.29566257 | F22: =(I24-F19)/(F20-F19) -> 0.96938281 | G22: =(I24-G19)/(G20-G19) -> 0.80662829 | H22: =(I24-H19)/(H20-H19) -> 0.59974412 | K22: =K14 -> 0
A23: Dasa# @ Given time | C23: =MOD(VLOOKUP(B24,PlanetData,3,0)+MATCH(B22,INDEX(VimFrac,,VLOOKUP(B24,PlanetData,3,0)+1),1)-1,9) -> 4 | D23: =MOD(VLOOKUP(C24,PlanetData,3,0)+MATCH(C22,INDEX(VimFrac,0,9*C25+VLOOKUP(C24,PlanetData,3,0)+1),IF(C25,-1,1))-1,9) -> 3 | E23: =MOD(VLOOKUP(D24,PlanetData,3,0)+MATCH(D22,INDEX(VimFrac,0,9*D25+VLOOKUP(D24,PlanetData,3,0)+1),IF(D25,-1,1))-1,9) -> 8 | F23: =MOD(VLOOKUP(E24,PlanetData,3,0)+MATCH(E22,INDEX(VimFrac,0,9*E25+VLOOKUP(E24,PlanetData,3,0)+1),IF(E25,-1,1))-1,9) -> 0 | G23: =MOD(VLOOKUP(F24,PlanetData,3,0)+MATCH(F22,INDEX(VimFrac,0,9*F25+VLOOKUP(F24,PlanetData,3,0)+1),IF(F25,-1,1))-1,9) -> 8 | H23: =MOD(VLOOKUP(G24,PlanetData,3,0)+MATCH(G22,INDEX(VimFrac,0,9*G25+VLOOKUP(G24,PlanetData,3,0)+1),IF(G25,-1,1))-1,9) -> 6 | K23: =K15 -> 0
A24: Dasa @ Given time | B24: =$B$4 -> Moon | C24: =INDEX(DasaYears,IF(C23=0,9,C23),1) -> Moon | D24: =INDEX(DasaYears,IF(D23=0,9,D23),1) -> Sun | E24: =INDEX(DasaYears,IF(E23=0,9,E23),1) -> Saturn | F24: =INDEX(DasaYears,IF(F23=0,9,F23),1) -> Mercury | G24: =INDEX(DasaYears,IF(G23=0,9,G23),1) -> Saturn | H24: =INDEX(DasaYears,IF(H23=0,9,H23),1) -> Rahu | I24: =INDIRECT("'JHora'!$B$"&($K24)) -> 26133 | J24: =INDIRECT("'JHora'!$C$"&($K24)) -> Born in CIM Stores | K24: =K16+1 -> 2 | N24: =JHora!B25 -> 0 | O24: =JHora!C25 -> 0
A25: Calculate Retrograde? | B25: =$B$7 -> TRUE | C25: =IF(VLOOKUP(C24,ChartInfo,11,0),1,0)*B25 -> 0 | D25: =IF(VLOOKUP(D24,ChartInfo,11,0),1,0)*B25 -> 0 | E25: =IF(VLOOKUP(E24,ChartInfo,11,0),1,0)*B25 -> 0 | F25: =IF(VLOOKUP(F24,ChartInfo,11,0),1,0)*B25 -> 0 | G25: =IF(VLOOKUP(G24,ChartInfo,11,0),1,0)*B25 -> 0 | H25: =IF(VLOOKUP(H24,ChartInfo,11,0),1,0)*B25 -> 0 | K25: =K17 -> 0
K26: =K18+1 -> 2 | N26: =JHora!B27 -> 0 | O26: =JHora!C27 -> 0
A27: Start Date | B27: =DoB-$E$6*DaysInYear -> 22567.781 | C27: =B27+B29*INDEX(INDEX(VimFrac,,VLOOKUP(B32,PlanetData,3,0)+1),MATCH(B30,INDEX(VimFrac,,VLOOKUP(B32,PlanetData,3,0)+1),1)) -> 35351.702 | D27: =C27+C29*INDEX(INDEX(VimFrac,0,9*C33+VLOOKUP(C32,PlanetData,3,0)+1),IF(C33,1,0)+MATCH(C30,INDEX(VimFrac,0,9*C33+VLOOKUP(C32,PlanetData,3,0)+1),IF(C33,-1,1))) -> 36569.218 | E27: =D27+D29*INDEX(INDEX(VimFrac,0,9*D33+VLOOKUP(D32,PlanetData,3,0)+1),IF(D33,1,0)+MATCH(D30,INDEX(VimFrac,0,9*D33+VLOOKUP(D32,PlanetData,3,0)+1),IF(D33,-1,1))) -> 36711.262 | F27: =E27+E29*INDEX(INDEX(VimFrac,0,9*E33+VLOOKUP(E32,PlanetData,3,0)+1),IF(E33,1,0)+MATCH(E30,INDEX(VimFrac,0,9*E33+VLOOKUP(E32,PlanetData,3,0)+1),IF(E33,-1,1))) -> 36721.002 | G27: =F27+F29*INDEX(INDEX(VimFrac,0,9*F33+VLOOKUP(F32,PlanetData,3,0)+1),IF(F33,1,0)+MATCH(F30,INDEX(VimFrac,0,9*F33+VLOOKUP(F32,PlanetData,3,0)+1),IF(F33,-1,1))) -> 36722.896 | H27: =G27+G29*INDEX(INDEX(VimFrac,0,9*G33+VLOOKUP(G32,PlanetData,3,0)+1),IF(G33,1,0)+MATCH(G30,INDEX(VimFrac,0,9*G33+VLOOKUP(G32,PlanetData,3,0)+1),IF(G33,-1,1))) -> 36722.991 | J27: =J32 -> Joined SJC/SJVC | K27: =K19+1 -> 3 | N27: =JHora!B28 -> 0 | O27: =JHora!C28 -> 0
A28: End Date | B28: =B27+B29 -> 66398.366 | C28: =B27+B29*INDEX(INDEX(VimFrac,,VLOOKUP(B32,PlanetData,3,0)+1),MATCH(B30,INDEX(VimFrac,,VLOOKUP(B32,PlanetData,3,0)+1),1)+1) -> 41195.78 | D28: =C27+C29*INDEX(INDEX(VimFrac,0,9*C33+VLOOKUP(C32,PlanetData,3,0)+1),IF(C33,0,1)+MATCH(C30,INDEX(VimFrac,0,9*C33+VLOOKUP(C32,PlanetData,3,0)+1),IF(C33,-1,1))) -> 37056.225 | E28: =D27+D29*INDEX(INDEX(VimFrac,0,9*D33+VLOOKUP(D32,PlanetData,3,0)+1),IF(D33,0,1)+MATCH(D30,INDEX(VimFrac,0,9*D33+VLOOKUP(D32,PlanetData,3,0)+1),IF(D33,-1,1))) -> 36776.196 | F28: =E27+E29*INDEX(INDEX(VimFrac,0,9*E33+VLOOKUP(E32,PlanetData,3,0)+1),IF(E33,0,1)+MATCH(E30,INDEX(VimFrac,0,9*E33+VLOOKUP(E32,PlanetData,3,0)+1),IF(E33,-1,1))) -> 36724.79 | G28: =F27+F29*INDEX(INDEX(VimFrac,0,9*F33+VLOOKUP(F32,PlanetData,3,0)+1),IF(F33,0,1)+MATCH(F30,INDEX(VimFrac,0,9*F33+VLOOKUP(F32,PlanetData,3,0)+1),IF(F33,-1,1))) -> 36723.495 | H28: =G27+G29*INDEX(INDEX(VimFrac,0,9*G33+VLOOKUP(G32,PlanetData,3,0)+1),IF(G33,0,1)+MATCH(G30,INDEX(VimFrac,0,9*G33+VLOOKUP(G32,PlanetData,3,0)+1),IF(G33,-1,1))) -> 36723.076 | J28: =J32 -> Joined SJC/SJVC | K28: =K20+1 -> 3 | N28: =JHora!B29 -> 0 | O28: =JHora!C29 -> 0
A29: Cycle Duration Days | B29: =120*DaysInYear -> 43830.585 | C29: =C28-C27 -> 5844.078 | D29: =D28-D27 -> 487.0065 | E29: =E28-E27 -> 64.9342 | F29: =F28-F27 -> 3.7878283 | G29: =G28-G27 -> 0.59973948 | H29: =H28-H27 -> 0.084963093 | K29: =K21 -> 0
A30: %Frac Past in Cyc | B30: =(I32-B27)/(B28-B27) -> 0.322953 | C30: =(I32-C27)/(C28-C27) -> 0.23464748 | D30: =(I32-D27)/(D28-D27) -> 0.31576975 | E30: =(I32-E27)/(E28-E27) -> 0.1807731 | F30: =(I32-F27)/(F28-F27) -> 0.52753893 | G30: =(I32-G27)/(G28-G27) -> 0.17393006 | H30: =(I32-H27)/(H28-H27) -> 0.11009453 | K30: =K22 -> 0
A31: Dasa# @ Given time | C31: =MOD(VLOOKUP(B32,PlanetData,3,0)+MATCH(B30,INDEX(VimFrac,,VLOOKUP(B32,PlanetData,3,0)+1),1)-1,9) -> 7 | D31: =MOD(VLOOKUP(C32,PlanetData,3,0)+MATCH(C30,INDEX(VimFrac,0,9*C33+VLOOKUP(C32,PlanetData,3,0)+1),IF(C33,-1,1))-1,9) -> 4 | E31: =MOD(VLOOKUP(D32,PlanetData,3,0)+MATCH(D30,INDEX(VimFrac,0,9*D33+VLOOKUP(D32,PlanetData,3,0)+1),IF(D33,-1,1))-1,9) -> 7 | F31: =MOD(VLOOKUP(E32,PlanetData,3,0)+MATCH(E30,INDEX(VimFrac,0,9*E33+VLOOKUP(E32,PlanetData,3,0)+1),IF(E33,-1,1))-1,9) -> 5 | G31: =MOD(VLOOKUP(F32,PlanetData,3,0)+MATCH(F30,INDEX(VimFrac,0,9*F33+VLOOKUP(F32,PlanetData,3,0)+1),IF(F33,-1,1))-1,9) -> 8 | H31: =MOD(VLOOKUP(G32,PlanetData,3,0)+MATCH(G30,INDEX(VimFrac,0,9*G33+VLOOKUP(G32,PlanetData,3,0)+1),IF(G33,-1,1))-1,9) -> 0 | K31: =K23 -> 0
A32: Dasa @ Given time | B32: =$B$4 -> Moon | C32: =INDEX(DasaYears,IF(C31=0,9,C31),1) -> Jupiter | D32: =INDEX(DasaYears,IF(D31=0,9,D31),1) -> Moon | E32: =INDEX(DasaYears,IF(E31=0,9,E31),1) -> Jupiter | F32: =INDEX(DasaYears,IF(F31=0,9,F31),1) -> Mars | G32: =INDEX(DasaYears,IF(G31=0,9,G31),1) -> Saturn | H32: =INDEX(DasaYears,IF(H31=0,9,H31),1) -> Mercury | I32: =INDIRECT("'JHora'!$B$"&($K32)) -> 36723 | J32: =INDIRECT("'JHora'!$C$"&($K32)) -> Joined SJC/SJVC | K32: =K24+1 -> 3 | N32: =JHora!B33 -> 0 | O32: =JHora!C33 -> 0
A33: Calculate Retrograde? | B33: =$B$7 -> TRUE | C33: =IF(VLOOKUP(C32,ChartInfo,11,0),1,0)*B33 -> 1 | D33: =IF(VLOOKUP(D32,ChartInfo,11,0),1,0)*B33 -> 0 | E33: =IF(VLOOKUP(E32,ChartInfo,11,0),1,0)*B33 -> 1 | F33: =IF(VLOOKUP(F32,ChartInfo,11,0),1,0)*B33 -> 1 | G33: =IF(VLOOKUP(G32,ChartInfo,11,0),1,0)*B33 -> 0 | H33: =IF(VLOOKUP(H32,ChartInfo,11,0),1,0)*B33 -> 0 | K33: =K25 -> 0
K34: =K26+1 -> 3 | N34: =JHora!B35 -> 0 | O34: =JHora!C35 -> 0
A35: Start Date | B35: =DoB-$E$6*DaysInYear -> 22567.781 | C35: =B35+B37*INDEX(INDEX(VimFrac,,VLOOKUP(B40,PlanetData,3,0)+1),MATCH(B38,INDEX(VimFrac,,VLOOKUP(B40,PlanetData,3,0)+1),1)) -> 35351.702 | D35: =C35+C37*INDEX(INDEX(VimFrac,0,9*C41+VLOOKUP(C40,PlanetData,3,0)+1),IF(C41,1,0)+MATCH(C38,INDEX(VimFrac,0,9*C41+VLOOKUP(C40,PlanetData,3,0)+1),IF(C41,-1,1))) -> 37348.428 | E35: =D35+D37*INDEX(INDEX(VimFrac,0,9*D41+VLOOKUP(D40,PlanetData,3,0)+1),IF(D41,1,0)+MATCH(D38,INDEX(VimFrac,0,9*D41+VLOOKUP(D40,PlanetData,3,0)+1),IF(D41,-1,1))) -> 37843.552 | F35: =E35+E37*INDEX(INDEX(VimFrac,0,9*E41+VLOOKUP(E40,PlanetData,3,0)+1),IF(E41,1,0)+MATCH(E38,INDEX(VimFrac,0,9*E41+VLOOKUP(E40,PlanetData,3,0)+1),IF(E41,-1,1))) -> 37917.144 | G35: =F35+F37*INDEX(INDEX(VimFrac,0,9*F41+VLOOKUP(F40,PlanetData,3,0)+1),IF(F41,1,0)+MATCH(F38,INDEX(VimFrac,0,9*F41+VLOOKUP(F40,PlanetData,3,0)+1),IF(F41,-1,1))) -> 37924.81 | H35: =G35+G37*INDEX(INDEX(VimFrac,0,9*G41+VLOOKUP(G40,PlanetData,3,0)+1),IF(G41,1,0)+MATCH(G38,INDEX(VimFrac,0,9*G41+VLOOKUP(G40,PlanetData,3,0)+1),IF(G41,-1,1))) -> 37925.921 | J35: =J40 -> Bought Car D16 | K35: =K27+1 -> 4 | N35: =JHora!B36 -> 0 | O35: =JHora!C36 -> 0
A36: End Date | B36: =B35+B37 -> 66398.366 | C36: =B35+B37*INDEX(INDEX(VimFrac,,VLOOKUP(B40,PlanetData,3,0)+1),MATCH(B38,INDEX(VimFrac,,VLOOKUP(B40,PlanetData,3,0)+1),1)+1) -> 41195.78 | D36: =C35+C37*INDEX(INDEX(VimFrac,0,9*C41+VLOOKUP(C40,PlanetData,3,0)+1),IF(C41,0,1)+MATCH(C38,INDEX(VimFrac,0,9*C41+VLOOKUP(C40,PlanetData,3,0)+1),IF(C41,-1,1))) -> 38322.441 | E36: =D35+D37*INDEX(INDEX(VimFrac,0,9*D41+VLOOKUP(D40,PlanetData,3,0)+1),IF(D41,0,1)+MATCH(D38,INDEX(VimFrac,0,9*D41+VLOOKUP(D40,PlanetData,3,0)+1),IF(D41,-1,1))) -> 37973.42 | F36: =E35+E37*INDEX(INDEX(VimFrac,0,9*E41+VLOOKUP(E40,PlanetData,3,0)+1),IF(E41,0,1)+MATCH(E38,INDEX(VimFrac,0,9*E41+VLOOKUP(E40,PlanetData,3,0)+1),IF(E41,-1,1))) -> 37935.542 | G36: =F35+F37*INDEX(INDEX(VimFrac,0,9*F41+VLOOKUP(F40,PlanetData,3,0)+1),IF(F41,0,1)+MATCH(F38,INDEX(VimFrac,0,9*F41+VLOOKUP(F40,PlanetData,3,0)+1),IF(F41,-1,1))) -> 37926.343 | H36: =G35+G37*INDEX(INDEX(VimFrac,0,9*G41+VLOOKUP(G40,PlanetData,3,0)+1),IF(G41,0,1)+MATCH(G38,INDEX(VimFrac,0,9*G41+VLOOKUP(G40,PlanetData,3,0)+1),IF(G41,-1,1))) -> 37926.011 | J36: =J40 -> Bought Car D16 | K36: =K28+1 -> 4 | N36: =JHora!B37 -> 0 | O36: =JHora!C37 -> 0
A37: Cycle Duration Days | B37: =120*DaysInYear -> 43830.585 | C37: =C36-C35 -> 5844.078 | D37: =D36-D35 -> 974.01299 | E37: =E36-E35 -> 129.8684 | F37: =F36-F35 -> 18.398023 | G37: =G36-G35 -> 1.5331686 | H37: =H36-H35 -> 0.089434835 | K37: =K29 -> 0
A38: %Frac Past in Cyc | B38: =(I40-B35)/(B36-B35) -> 0.35039959 | C38: =(I40-C35)/(C36-C35) -> 0.44049689 | D38: =(I40-D35)/(D36-D35) -> 0.59298133 | E38: =(I40-E35)/(E36-E35) -> 0.63486 | F38: =(I40-F35)/(F36-F35) -> 0.48136468 | G38: =(I40-G35)/(G36-G35) -> 0.7763762 | H38: =(I40-H35)/(H36-H35) -> 0.88073492 | K38: =K30 -> 0
A39: Dasa# @ Given time | C39: =MOD(VLOOKUP(B40,PlanetData,3,0)+MATCH(B38,INDEX(VimFrac,,VLOOKUP(B40,PlanetData,3,0)+1),1)-1,9) -> 7 | D39: =MOD(VLOOKUP(C40,PlanetData,3,0)+MATCH(C38,INDEX(VimFrac,0,9*C41+VLOOKUP(C40,PlanetData,3,0)+1),IF(C41,-1,1))-1,9) -> 2 | E39: =MOD(VLOOKUP(D40,PlanetData,3,0)+MATCH(D38,INDEX(VimFrac,0,9*D41+VLOOKUP(D40,PlanetData,3,0)+1),IF(D41,-1,1))-1,9) -> 7 | F39: =MOD(VLOOKUP(E40,PlanetData,3,0)+MATCH(E38,INDEX(VimFrac,0,9*E41+VLOOKUP(E40,PlanetData,3,0)+1),IF(E41,-1,1))-1,9) -> 0 | G39: =MOD(VLOOKUP(F40,PlanetData,3,0)+MATCH(F38,INDEX(VimFrac,0,9*F41+VLOOKUP(F40,PlanetData,3,0)+1),IF(F41,-1,1))-1,9) -> 4 | H39: =MOD(VLOOKUP(G40,PlanetData,3,0)+MATCH(G38,INDEX(VimFrac,0,9*G41+VLOOKUP(G40,PlanetData,3,0)+1),IF(G41,-1,1))-1,9) -> 1 | K39: =K31 -> 0
A40: Dasa @ Given time | B40: =$B$4 -> Moon | C40: =INDEX(DasaYears,IF(C39=0,9,C39),1) -> Jupiter | D40: =INDEX(DasaYears,IF(D39=0,9,D39),1) -> Venus | E40: =INDEX(DasaYears,IF(E39=0,9,E39),1) -> Jupiter | F40: =INDEX(DasaYears,IF(F39=0,9,F39),1) -> Mercury | G40: =INDEX(DasaYears,IF(G39=0,9,G39),1) -> Moon | H40: =INDEX(DasaYears,IF(H39=0,9,H39),1) -> Ketu | I40: =INDIRECT("'JHora'!$B$"&($K40)) -> 37926 | J40: =INDIRECT("'JHora'!$C$"&($K40)) -> Bought Car D16 | K40: =K32+1 -> 4 | N40: =JHora!B41 -> 0 | O40: =JHora!C41 -> 0
A41: Calculate Retrograde? | B41: =$B$7 -> TRUE | C41: =IF(VLOOKUP(C40,ChartInfo,11,0),1,0)*B41 -> 1 | D41: =IF(VLOOKUP(D40,ChartInfo,11,0),1,0)*B41 -> 0 | E41: =IF(VLOOKUP(E40,ChartInfo,11,0),1,0)*B41 -> 1 | F41: =IF(VLOOKUP(F40,ChartInfo,11,0),1,0)*B41 -> 0 | G41: =IF(VLOOKUP(G40,ChartInfo,11,0),1,0)*B41 -> 0 | H41: =IF(VLOOKUP(H40,ChartInfo,11,0),1,0)*B41 -> 0 | K41: =K33 -> 0
K42: =K34+1 -> 4 | N42: =JHora!B43 -> 0 | O42: =JHora!C43 -> 0
A43: Start Date | B43: =DoB-$E$6*DaysInYear -> 22567.781 | C43: =B43+B45*INDEX(INDEX(VimFrac,,VLOOKUP(B48,PlanetData,3,0)+1),MATCH(B46,INDEX(VimFrac,,VLOOKUP(B48,PlanetData,3,0)+1),1)) -> 35351.702 | D43: =C43+C45*INDEX(INDEX(VimFrac,0,9*C49+VLOOKUP(C48,PlanetData,3,0)+1),IF(C49,1,0)+MATCH(C46,INDEX(VimFrac,0,9*C49+VLOOKUP(C48,PlanetData,3,0)+1),IF(C49,-1,1))) -> 38663.346 | E43: =D43+D45*INDEX(INDEX(VimFrac,0,9*D49+VLOOKUP(D48,PlanetData,3,0)+1),IF(D49,1,0)+MATCH(D46,INDEX(VimFrac,0,9*D49+VLOOKUP(D48,PlanetData,3,0)+1),IF(D49,-1,1))) -> 38663.346 | F43: =E43+E45*INDEX(INDEX(VimFrac,0,9*E49+VLOOKUP(E48,PlanetData,3,0)+1),IF(E49,1,0)+MATCH(E46,INDEX(VimFrac,0,9*E49+VLOOKUP(E48,PlanetData,3,0)+1),IF(E49,-1,1))) -> 38762.063 | G43: =F43+F45*INDEX(INDEX(VimFrac,0,9*F49+VLOOKUP(F48,PlanetData,3,0)+1),IF(F49,1,0)+MATCH(F46,INDEX(VimFrac,0,9*F49+VLOOKUP(F48,PlanetData,3,0)+1),IF(F49,-1,1))) -> 38778.157 | H43: =G43+G45*INDEX(INDEX(VimFrac,0,9*G49+VLOOKUP(G48,PlanetData,3,0)+1),IF(G49,1,0)+MATCH(G46,INDEX(VimFrac,0,9*G49+VLOOKUP(G48,PlanetData,3,0)+1),IF(G49,-1,1))) -> 38778.88 | J43: =J48 -> Marriage D9 | K43: =K35+1 -> 5 | N43: =JHora!B44 -> 0 | O43: =JHora!C44 -> 0
A44: End Date | B44: =B43+B45 -> 66398.366 | C44: =B43+B45*INDEX(INDEX(VimFrac,,VLOOKUP(B48,PlanetData,3,0)+1),MATCH(B46,INDEX(VimFrac,,VLOOKUP(B48,PlanetData,3,0)+1),1)+1) -> 41195.78 | D44: =C43+C45*INDEX(INDEX(VimFrac,0,9*C49+VLOOKUP(C48,PlanetData,3,0)+1),IF(C49,0,1)+MATCH(C46,INDEX(VimFrac,0,9*C49+VLOOKUP(C48,PlanetData,3,0)+1),IF(C49,-1,1))) -> 39491.257 | E44: =D43+D45*INDEX(INDEX(VimFrac,0,9*D49+VLOOKUP(D48,PlanetData,3,0)+1),IF(D49,0,1)+MATCH(D46,INDEX(VimFrac,0,9*D49+VLOOKUP(D48,PlanetData,3,0)+1),IF(D49,-1,1))) -> 38780.633 | F44: =E43+E45*INDEX(INDEX(VimFrac,0,9*E49+VLOOKUP(E48,PlanetData,3,0)+1),IF(E49,0,1)+MATCH(E46,INDEX(VimFrac,0,9*E49+VLOOKUP(E48,PlanetData,3,0)+1),IF(E49,-1,1))) -> 38780.633 | G44: =F43+F45*INDEX(INDEX(VimFrac,0,9*F49+VLOOKUP(F48,PlanetData,3,0)+1),IF(F49,0,1)+MATCH(F46,INDEX(VimFrac,0,9*F49+VLOOKUP(F48,PlanetData,3,0)+1),IF(F49,-1,1))) -> 38780.633 | H44: =G43+G45*INDEX(INDEX(VimFrac,0,9*G49+VLOOKUP(G48,PlanetData,3,0)+1),IF(G49,0,1)+MATCH(G46,INDEX(VimFrac,0,9*G49+VLOOKUP(G48,PlanetData,3,0)+1),IF(G49,-1,1))) -> 38779.003 | J44: =J48 -> Marriage D9 | K44: =K36+1 -> 5 | N44: =JHora!B45 -> 0 | O44: =JHora!C45 -> 0
A45: Cycle Duration Days | B45: =120*DaysInYear -> 43830.585 | C45: =C44-C43 -> 5844.078 | D45: =D44-D43 -> 827.91104 | E45: =E44-E43 -> 117.2874 | F45: =F44-F43 -> 18.570505 | G45: =G44-G43 -> 2.4760673 | H45: =H44-H43 -> 0.12380336 | K45: =K37 -> 0
A46: %Frac Past in Cyc | B46: =(I48-B43)/(B44-B43) -> 0.36986088 | C46: =(I48-C43)/(C44-C43) -> 0.58645661 | D46: =(I48-D43)/(D44-D43) -> 0.13969373 | E46: =(I48-E43)/(E44-E43) -> 0.98607339 | F46: =(I48-F43)/(F44-F43) -> 0.91204244 | G46: =(I48-G43)/(G44-G43) -> 0.34031828 | H46: =(I48-H43)/(H44-H43) -> 0.97303235 | K46: =K38 -> 0
A47: Dasa# @ Given time | C47: =MOD(VLOOKUP(B48,PlanetData,3,0)+MATCH(B46,INDEX(VimFrac,,VLOOKUP(B48,PlanetData,3,0)+1),1)-1,9) -> 7 | D47: =MOD(VLOOKUP(C48,PlanetData,3,0)+MATCH(C46,INDEX(VimFrac,0,9*C49+VLOOKUP(C48,PlanetData,3,0)+1),IF(C49,-1,1))-1,9) -> 0 | E47: =MOD(VLOOKUP(D48,PlanetData,3,0)+MATCH(D46,INDEX(VimFrac,0,9*D49+VLOOKUP(D48,PlanetData,3,0)+1),IF(D49,-1,1))-1,9) -> 0 | F47: =MOD(VLOOKUP(E48,PlanetData,3,0)+MATCH(E46,INDEX(VimFrac,0,9*E49+VLOOKUP(E48,PlanetData,3,0)+1),IF(E49,-1,1))-1,9) -> 8 | G47: =MOD(VLOOKUP(F48,PlanetData,3,0)+MATCH(F46,INDEX(VimFrac,0,9*F49+VLOOKUP(F48,PlanetData,3,0)+1),IF(F49,-1,1))-1,9) -> 7 | H47: =MOD(VLOOKUP(G48,PlanetData,3,0)+MATCH(G46,INDEX(VimFrac,0,9*G49+VLOOKUP(G48,PlanetData,3,0)+1),IF(G49,-1,1))-1,9) -> 3 | K47: =K39 -> 0
A48: Dasa @ Given time | B48: =$B$4 -> Moon | C48: =INDEX(DasaYears,IF(C47=0,9,C47),1) -> Jupiter | D48: =INDEX(DasaYears,IF(D47=0,9,D47),1) -> Mercury | E48: =INDEX(DasaYears,IF(E47=0,9,E47),1) -> Mercury | F48: =INDEX(DasaYears,IF(F47=0,9,F47),1) -> Saturn | G48: =INDEX(DasaYears,IF(G47=0,9,G47),1) -> Jupiter | H48: =INDEX(DasaYears,IF(H47=0,9,H47),1) -> Sun | I48: =INDIRECT("'JHora'!$B$"&($K48)) -> 38779 | J48: =INDIRECT("'JHora'!$C$"&($K48)) -> Marriage D9 | K48: =K40+1 -> 5 | N48: =JHora!B49 -> 0 | O48: =JHora!C49 -> 0
A49: Calculate Retrograde? | B49: =$B$7 -> TRUE | C49: =IF(VLOOKUP(C48,ChartInfo,11,0),1,0)*B49 -> 1 | D49: =IF(VLOOKUP(D48,ChartInfo,11,0),1,0)*B49 -> 0 | E49: =IF(VLOOKUP(E48,ChartInfo,11,0),1,0)*B49 -> 0 | F49: =IF(VLOOKUP(F48,ChartInfo,11,0),1,0)*B49 -> 0 | G49: =IF(VLOOKUP(G48,ChartInfo,11,0),1,0)*B49 -> 1 | H49: =IF(VLOOKUP(H48,ChartInfo,11,0),1,0)*B49 -> 0 | K49: =K41 -> 0
K50: =K42+1 -> 5 | N50: =JHora!B51 -> 0 | O50: =JHora!C51 -> 0
A51: Start Date | B51: =DoB-$E$6*DaysInYear -> 22567.781 | C51: =B51+B53*INDEX(INDEX(VimFrac,,VLOOKUP(B56,PlanetData,3,0)+1),MATCH(B54,INDEX(VimFrac,,VLOOKUP(B56,PlanetData,3,0)+1),1)) -> 41195.78 | D51: =C51+C53*INDEX(INDEX(VimFrac,0,9*C57+VLOOKUP(C56,PlanetData,3,0)+1),IF(C57,1,0)+MATCH(C54,INDEX(VimFrac,0,9*C57+VLOOKUP(C56,PlanetData,3,0)+1),IF(C57,-1,1))) -> 41195.78 | E51: =D51+D53*INDEX(INDEX(VimFrac,0,9*D57+VLOOKUP(D56,PlanetData,3,0)+1),IF(D57,1,0)+MATCH(D54,INDEX(VimFrac,0,9*D57+VLOOKUP(D56,PlanetData,3,0)+1),IF(D57,-1,1))) -> 41589.519 | F51: =E51+E53*INDEX(INDEX(VimFrac,0,9*E57+VLOOKUP(E56,PlanetData,3,0)+1),IF(E57,1,0)+MATCH(E54,INDEX(VimFrac,0,9*E57+VLOOKUP(E56,PlanetData,3,0)+1),IF(E57,-1,1))) -> 41682.613 | G51: =F51+F53*INDEX(INDEX(VimFrac,0,9*F57+VLOOKUP(F56,PlanetData,3,0)+1),IF(F57,1,0)+MATCH(F54,INDEX(VimFrac,0,9*F57+VLOOKUP(F56,PlanetData,3,0)+1),IF(F57,-1,1))) -> 41690.956 | H51: =G51+G53*INDEX(INDEX(VimFrac,0,9*G57+VLOOKUP(G56,PlanetData,3,0)+1),IF(G57,1,0)+MATCH(G54,INDEX(VimFrac,0,9*G57+VLOOKUP(G56,PlanetData,3,0)+1),IF(G57,-1,1))) -> 41693.567 | J51: =J56 -> Bought Car D16 | K51: =K43+1 -> 6 | N51: =JHora!B52 -> 0 | O51: =JHora!C52 -> 0
A52: End Date | B52: =B51+B53 -> 66398.366 | C52: =B51+B53*INDEX(INDEX(VimFrac,,VLOOKUP(B56,PlanetData,3,0)+1),MATCH(B54,INDEX(VimFrac,,VLOOKUP(B56,PlanetData,3,0)+1),1)+1) -> 48135.622 | D52: =C51+C53*INDEX(INDEX(VimFrac,0,9*C57+VLOOKUP(C56,PlanetData,3,0)+1),IF(C57,0,1)+MATCH(C54,INDEX(VimFrac,0,9*C57+VLOOKUP(C56,PlanetData,3,0)+1),IF(C57,-1,1))) -> 42294.588 | E52: =D51+D53*INDEX(INDEX(VimFrac,0,9*D57+VLOOKUP(D56,PlanetData,3,0)+1),IF(D57,0,1)+MATCH(D54,INDEX(VimFrac,0,9*D57+VLOOKUP(D56,PlanetData,3,0)+1),IF(D57,-1,1))) -> 41772.654 | F52: =E51+E53*INDEX(INDEX(VimFrac,0,9*E57+VLOOKUP(E56,PlanetData,3,0)+1),IF(E57,0,1)+MATCH(E54,INDEX(VimFrac,0,9*E57+VLOOKUP(E56,PlanetData,3,0)+1),IF(E57,-1,1))) -> 41707.031 | G52: =F51+F53*INDEX(INDEX(VimFrac,0,9*F57+VLOOKUP(F56,PlanetData,3,0)+1),IF(F57,0,1)+MATCH(F54,INDEX(VimFrac,0,9*F57+VLOOKUP(F56,PlanetData,3,0)+1),IF(F57,-1,1))) -> 41695.025 | H52: =G51+G53*INDEX(INDEX(VimFrac,0,9*G57+VLOOKUP(G56,PlanetData,3,0)+1),IF(G57,0,1)+MATCH(G54,INDEX(VimFrac,0,9*G57+VLOOKUP(G56,PlanetData,3,0)+1),IF(G57,-1,1))) -> 41694.212 | J52: =J56 -> Bought Car D16 | K52: =K44+1 -> 6 | N52: =JHora!B53 -> 0 | O52: =JHora!C53 -> 0
A53: Cycle Duration Days | B53: =120*DaysInYear -> 43830.585 | C53: =C52-C51 -> 6939.8426 | D53: =D52-D51 -> 1098.8084 | E53: =E52-E51 -> 183.13473 | F53: =F52-F51 -> 24.417965 | G53: =G52-G51 -> 4.0696608 | H53: =H52-H51 -> 0.64436296 | K53: =K45 -> 0
A54: %Frac Past in Cyc | B54: =(I56-B51)/(B52-B51) -> 0.43636695 | C54: =(I56-C51)/(C52-C51) -> 0.071791282 | D54: =(I56-D51)/(D52-D51) -> 0.45341862 | E54: =(I56-E51)/(E52-E51) -> 0.57051175 | F54: =(I56-F51)/(F52-F51) -> 0.46633812 | G54: =(I56-G51)/(G52-G51) -> 0.74802874 | H54: =(I56-H51)/(H52-H51) -> 0.67176044 | K54: =K46 -> 0
A55: Dasa# @ Given time | C55: =MOD(VLOOKUP(B56,PlanetData,3,0)+MATCH(B54,INDEX(VimFrac,,VLOOKUP(B56,PlanetData,3,0)+1),1)-1,9) -> 8 | D55: =MOD(VLOOKUP(C56,PlanetData,3,0)+MATCH(C54,INDEX(VimFrac,0,9*C57+VLOOKUP(C56,PlanetData,3,0)+1),IF(C57,-1,1))-1,9) -> 8 | E55: =MOD(VLOOKUP(D56,PlanetData,3,0)+MATCH(D54,INDEX(VimFrac,0,9*D57+VLOOKUP(D56,PlanetData,3,0)+1),IF(D57,-1,1))-1,9) -> 2 | F55: =MOD(VLOOKUP(E56,PlanetData,3,0)+MATCH(E54,INDEX(VimFrac,0,9*E57+VLOOKUP(E56,PlanetData,3,0)+1),IF(E57,-1,1))-1,9) -> 7 | G55: =MOD(VLOOKUP(F56,PlanetData,3,0)+MATCH(F54,INDEX(VimFrac,0,9*F57+VLOOKUP(F56,PlanetData,3,0)+1),IF(F57,-1,1))-1,9) -> 2 | H55: =MOD(VLOOKUP(G56,PlanetData,3,0)+MATCH(G54,INDEX(VimFrac,0,9*G57+VLOOKUP(G56,PlanetData,3,0)+1),IF(G57,-1,1))-1,9) -> 8 | K55: =K47 -> 0
A56: Dasa @ Given time | B56: =$B$4 -> Moon | C56: =INDEX(DasaYears,IF(C55=0,9,C55),1) -> Saturn | D56: =INDEX(DasaYears,IF(D55=0,9,D55),1) -> Saturn | E56: =INDEX(DasaYears,IF(E55=0,9,E55),1) -> Venus | F56: =INDEX(DasaYears,IF(F55=0,9,F55),1) -> Jupiter | G56: =INDEX(DasaYears,IF(G55=0,9,G55),1) -> Venus | H56: =INDEX(DasaYears,IF(H55=0,9,H55),1) -> Saturn | I56: =INDIRECT("'JHora'!$B$"&($K56)) -> 41694 | J56: =INDIRECT("'JHora'!$C$"&($K56)) -> Bought Car D16 | K56: =K48+1 -> 6 | N56: =JHora!B57 -> 0 | O56: =JHora!C57 -> 0
A57: Calculate Retrograde? | B57: =$B$7 -> TRUE | C57: =IF(VLOOKUP(C56,ChartInfo,11,0),1,0)*B57 -> 0 | D57: =IF(VLOOKUP(D56,ChartInfo,11,0),1,0)*B57 -> 0 | E57: =IF(VLOOKUP(E56,ChartInfo,11,0),1,0)*B57 -> 0 | F57: =IF(VLOOKUP(F56,ChartInfo,11,0),1,0)*B57 -> 1 | G57: =IF(VLOOKUP(G56,ChartInfo,11,0),1,0)*B57 -> 0 | H57: =IF(VLOOKUP(H56,ChartInfo,11,0),1,0)*B57 -> 0 | K57: =K49 -> 0
K58: =K50+1 -> 6 | N58: =JHora!B59 -> 0 | O58: =JHora!C59 -> 0
A59: Start Date | B59: =DoB-$E$6*DaysInYear -> 22567.781 | C59: =B59+B61*INDEX(INDEX(VimFrac,,VLOOKUP(B64,PlanetData,3,0)+1),MATCH(B62,INDEX(VimFrac,,VLOOKUP(B64,PlanetData,3,0)+1),1)) -> #N/A | D59: =C59+C61*INDEX(INDEX(VimFrac,0,9*C65+VLOOKUP(C64,PlanetData,3,0)+1),IF(C65,1,0)+MATCH(C62,INDEX(VimFrac,0,9*C65+VLOOKUP(C64,PlanetData,3,0)+1),IF(C65,-1,1))) -> #N/A | E59: =D59+D61*INDEX(INDEX(VimFrac,0,9*D65+VLOOKUP(D64,PlanetData,3,0)+1),IF(D65,1,0)+MATCH(D62,INDEX(VimFrac,0,9*D65+VLOOKUP(D64,PlanetData,3,0)+1),IF(D65,-1,1))) -> #N/A | F59: =E59+E61*INDEX(INDEX(VimFrac,0,9*E65+VLOOKUP(E64,PlanetData,3,0)+1),IF(E65,1,0)+MATCH(E62,INDEX(VimFrac,0,9*E65+VLOOKUP(E64,PlanetData,3,0)+1),IF(E65,-1,1))) -> #N/A | G59: =F59+F61*INDEX(INDEX(VimFrac,0,9*F65+VLOOKUP(F64,PlanetData,3,0)+1),IF(F65,1,0)+MATCH(F62,INDEX(VimFrac,0,9*F65+VLOOKUP(F64,PlanetData,3,0)+1),IF(F65,-1,1))) -> #N/A | H59: =G59+G61*INDEX(INDEX(VimFrac,0,9*G65+VLOOKUP(G64,PlanetData,3,0)+1),IF(G65,1,0)+MATCH(G62,INDEX(VimFrac,0,9*G65+VLOOKUP(G64,PlanetData,3,0)+1),IF(G65,-1,1))) -> #N/A | J59: =J64 -> 0 | K59: =K51+1 -> 7 | N59: =JHora!B60 -> 0 | O59: =JHora!C60 -> 0
A60: End Date | B60: =B59+B61 -> 66398.366 | C60: =B59+B61*INDEX(INDEX(VimFrac,,VLOOKUP(B64,PlanetData,3,0)+1),MATCH(B62,INDEX(VimFrac,,VLOOKUP(B64,PlanetData,3,0)+1),1)+1) -> #N/A | D60: =C59+C61*INDEX(INDEX(VimFrac,0,9*C65+VLOOKUP(C64,PlanetData,3,0)+1),IF(C65,0,1)+MATCH(C62,INDEX(VimFrac,0,9*C65+VLOOKUP(C64,PlanetData,3,0)+1),IF(C65,-1,1))) -> #N/A | E60: =D59+D61*INDEX(INDEX(VimFrac,0,9*D65+VLOOKUP(D64,PlanetData,3,0)+1),IF(D65,0,1)+MATCH(D62,INDEX(VimFrac,0,9*D65+VLOOKUP(D64,PlanetData,3,0)+1),IF(D65,-1,1))) -> #N/A | F60: =E59+E61*INDEX(INDEX(VimFrac,0,9*E65+VLOOKUP(E64,PlanetData,3,0)+1),IF(E65,0,1)+MATCH(E62,INDEX(VimFrac,0,9*E65+VLOOKUP(E64,PlanetData,3,0)+1),IF(E65,-1,1))) -> #N/A | G60: =F59+F61*INDEX(INDEX(VimFrac,0,9*F65+VLOOKUP(F64,PlanetData,3,0)+1),IF(F65,0,1)+MATCH(F62,INDEX(VimFrac,0,9*F65+VLOOKUP(F64,PlanetData,3,0)+1),IF(F65,-1,1))) -> #N/A | H60: =G59+G61*INDEX(INDEX(VimFrac,0,9*G65+VLOOKUP(G64,PlanetData,3,0)+1),IF(G65,0,1)+MATCH(G62,INDEX(VimFrac,0,9*G65+VLOOKUP(G64,PlanetData,3,0)+1),IF(G65,-1,1))) -> #N/A | J60: =J64 -> 0 | K60: =K52+1 -> 7 | N60: =JHora!B61 -> 0 | O60: =JHora!C61 -> 0
A61: Cycle Duration Days | B61: =120*DaysInYear -> 43830.585 | C61: =C60-C59 -> #N/A | D61: =D60-D59 -> #N/A | E61: =E60-E59 -> #N/A | F61: =F60-F59 -> #N/A | G61: =G60-G59 -> #N/A | H61: =H60-H59 -> #N/A | K61: =K53 -> 0
A62: %Frac Past in Cyc | B62: =(I64-B59)/(B60-B59) -> -0.51488661 | C62: =(I64-C59)/(C60-C59) -> #N/A | D62: =(I64-D59)/(D60-D59) -> #N/A | E62: =(I64-E59)/(E60-E59) -> #N/A | F62: =(I64-F59)/(F60-F59) -> #N/A | G62: =(I64-G59)/(G60-G59) -> #N/A | H62: =(I64-H59)/(H60-H59) -> #N/A | K62: =K54 -> 0
A63: Dasa# @ Given time | C63: =MOD(VLOOKUP(B64,PlanetData,3,0)+MATCH(B62,INDEX(VimFrac,,VLOOKUP(B64,PlanetData,3,0)+1),1)-1,9) -> #N/A | D63: =MOD(VLOOKUP(C64,PlanetData,3,0)+MATCH(C62,INDEX(VimFrac,0,9*C65+VLOOKUP(C64,PlanetData,3,0)+1),IF(C65,-1,1))-1,9) -> #N/A | E63: =MOD(VLOOKUP(D64,PlanetData,3,0)+MATCH(D62,INDEX(VimFrac,0,9*D65+VLOOKUP(D64,PlanetData,3,0)+1),IF(D65,-1,1))-1,9) -> #N/A | F63: =MOD(VLOOKUP(E64,PlanetData,3,0)+MATCH(E62,INDEX(VimFrac,0,9*E65+VLOOKUP(E64,PlanetData,3,0)+1),IF(E65,-1,1))-1,9) -> #N/A | G63: =MOD(VLOOKUP(F64,PlanetData,3,0)+MATCH(F62,INDEX(VimFrac,0,9*F65+VLOOKUP(F64,PlanetData,3,0)+1),IF(F65,-1,1))-1,9) -> #N/A | H63: =MOD(VLOOKUP(G64,PlanetData,3,0)+MATCH(G62,INDEX(VimFrac,0,9*G65+VLOOKUP(G64,PlanetData,3,0)+1),IF(G65,-1,1))-1,9) -> #N/A | K63: =K55 -> 0
A64: Dasa @ Given time | B64: =$B$4 -> Moon | C64: =INDEX(DasaYears,IF(C63=0,9,C63),1) -> #N/A | D64: =INDEX(DasaYears,IF(D63=0,9,D63),1) -> #N/A | E64: =INDEX(DasaYears,IF(E63=0,9,E63),1) -> #N/A | F64: =INDEX(DasaYears,IF(F63=0,9,F63),1) -> #N/A | G64: =INDEX(DasaYears,IF(G63=0,9,G63),1) -> #N/A | H64: =INDEX(DasaYears,IF(H63=0,9,H63),1) -> #N/A | I64: =INDIRECT("'JHora'!$B$"&($K64)) -> 0 | J64: =INDIRECT("'JHora'!$C$"&($K64)) -> 0 | K64: =K56+1 -> 7 | N64: =JHora!B65 -> 0 | O64: =JHora!C65 -> 0
A65: Calculate Retrograde? | B65: =$B$7 -> TRUE | C65: =IF(VLOOKUP(C64,ChartInfo,11,0),1,0)*B65 -> #N/A | D65: =IF(VLOOKUP(D64,ChartInfo,11,0),1,0)*B65 -> #N/A | E65: =IF(VLOOKUP(E64,ChartInfo,11,0),1,0)*B65 -> #N/A | F65: =IF(VLOOKUP(F64,ChartInfo,11,0),1,0)*B65 -> #N/A | G65: =IF(VLOOKUP(G64,ChartInfo,11,0),1,0)*B65 -> #N/A | H65: =IF(VLOOKUP(H64,ChartInfo,11,0),1,0)*B65 -> #N/A | K65: =K57 -> 0
K66: =K58+1 -> 7 | N66: =JHora!B67 -> 0 | O66: =JHora!C67 -> 0
A67: Start Date | B67: =DoB-$E$6*DaysInYear -> 22567.781 | C67: =B67+B69*INDEX(INDEX(VimFrac,,VLOOKUP(B72,PlanetData,3,0)+1),MATCH(B70,INDEX(VimFrac,,VLOOKUP(B72,PlanetData,3,0)+1),1)) -> #N/A | D67: =C67+C69*INDEX(INDEX(VimFrac,0,9*C73+VLOOKUP(C72,PlanetData,3,0)+1),IF(C73,1,0)+MATCH(C70,INDEX(VimFrac,0,9*C73+VLOOKUP(C72,PlanetData,3,0)+1),IF(C73,-1,1))) -> #N/A | E67: =D67+D69*INDEX(INDEX(VimFrac,0,9*D73+VLOOKUP(D72,PlanetData,3,0)+1),IF(D73,1,0)+MATCH(D70,INDEX(VimFrac,0,9*D73+VLOOKUP(D72,PlanetData,3,0)+1),IF(D73,-1,1))) -> #N/A | F67: =E67+E69*INDEX(INDEX(VimFrac,0,9*E73+VLOOKUP(E72,PlanetData,3,0)+1),IF(E73,1,0)+MATCH(E70,INDEX(VimFrac,0,9*E73+VLOOKUP(E72,PlanetData,3,0)+1),IF(E73,-1,1))) -> #N/A | G67: =F67+F69*INDEX(INDEX(VimFrac,0,9*F73+VLOOKUP(F72,PlanetData,3,0)+1),IF(F73,1,0)+MATCH(F70,INDEX(VimFrac,0,9*F73+VLOOKUP(F72,PlanetData,3,0)+1),IF(F73,-1,1))) -> #N/A | H67: =G67+G69*INDEX(INDEX(VimFrac,0,9*G73+VLOOKUP(G72,PlanetData,3,0)+1),IF(G73,1,0)+MATCH(G70,INDEX(VimFrac,0,9*G73+VLOOKUP(G72,PlanetData,3,0)+1),IF(G73,-1,1))) -> #N/A | J67: =J72 -> 0 | K67: =K59+1 -> 8 | N67: =JHora!B68 -> 0 | O67: =JHora!C68 -> 0
A68: End Date | B68: =B67+B69 -> 66398.366 | C68: =B67+B69*INDEX(INDEX(VimFrac,,VLOOKUP(B72,PlanetData,3,0)+1),MATCH(B70,INDEX(VimFrac,,VLOOKUP(B72,PlanetData,3,0)+1),1)+1) -> #N/A | D68: =C67+C69*INDEX(INDEX(VimFrac,0,9*C73+VLOOKUP(C72,PlanetData,3,0)+1),IF(C73,0,1)+MATCH(C70,INDEX(VimFrac,0,9*C73+VLOOKUP(C72,PlanetData,3,0)+1),IF(C73,-1,1))) -> #N/A | E68: =D67+D69*INDEX(INDEX(VimFrac,0,9*D73+VLOOKUP(D72,PlanetData,3,0)+1),IF(D73,0,1)+MATCH(D70,INDEX(VimFrac,0,9*D73+VLOOKUP(D72,PlanetData,3,0)+1),IF(D73,-1,1))) -> #N/A | F68: =E67+E69*INDEX(INDEX(VimFrac,0,9*E73+VLOOKUP(E72,PlanetData,3,0)+1),IF(E73,0,1)+MATCH(E70,INDEX(VimFrac,0,9*E73+VLOOKUP(E72,PlanetData,3,0)+1),IF(E73,-1,1))) -> #N/A | G68: =F67+F69*INDEX(INDEX(VimFrac,0,9*F73+VLOOKUP(F72,PlanetData,3,0)+1),IF(F73,0,1)+MATCH(F70,INDEX(VimFrac,0,9*F73+VLOOKUP(F72,PlanetData,3,0)+1),IF(F73,-1,1))) -> #N/A | H68: =G67+G69*INDEX(INDEX(VimFrac,0,9*G73+VLOOKUP(G72,PlanetData,3,0)+1),IF(G73,0,1)+MATCH(G70,INDEX(VimFrac,0,9*G73+VLOOKUP(G72,PlanetData,3,0)+1),IF(G73,-1,1))) -> #N/A | J68: =J72 -> 0 | K68: =K60+1 -> 8 | N68: =JHora!B69 -> 0 | O68: =JHora!C69 -> 0
A69: Cycle Duration Days | B69: =120*DaysInYear -> 43830.585 | C69: =C68-C67 -> #N/A | D69: =D68-D67 -> #N/A | E69: =E68-E67 -> #N/A | F69: =F68-F67 -> #N/A | G69: =G68-G67 -> #N/A | H69: =H68-H67 -> #N/A | K69: =K61 -> 0
A70: %Frac Past in Cyc | B70: =(I72-B67)/(B68-B67) -> -0.51488661 | C70: =(I72-C67)/(C68-C67) -> #N/A | D70: =(I72-D67)/(D68-D67) -> #N/A | E70: =(I72-E67)/(E68-E67) -> #N/A | F70: =(I72-F67)/(F68-F67) -> #N/A | G70: =(I72-G67)/(G68-G67) -> #N/A | H70: =(I72-H67)/(H68-H67) -> #N/A | K70: =K62 -> 0
A71: Dasa# @ Given time | C71: =MOD(VLOOKUP(B72,PlanetData,3,0)+MATCH(B70,INDEX(VimFrac,,VLOOKUP(B72,PlanetData,3,0)+1),1)-1,9) -> #N/A | D71: =MOD(VLOOKUP(C72,PlanetData,3,0)+MATCH(C70,INDEX(VimFrac,0,9*C73+VLOOKUP(C72,PlanetData,3,0)+1),IF(C73,-1,1))-1,9) -> #N/A | E71: =MOD(VLOOKUP(D72,PlanetData,3,0)+MATCH(D70,INDEX(VimFrac,0,9*D73+VLOOKUP(D72,PlanetData,3,0)+1),IF(D73,-1,1))-1,9) -> #N/A | F71: =MOD(VLOOKUP(E72,PlanetData,3,0)+MATCH(E70,INDEX(VimFrac,0,9*E73+VLOOKUP(E72,PlanetData,3,0)+1),IF(E73,-1,1))-1,9) -> #N/A | G71: =MOD(VLOOKUP(F72,PlanetData,3,0)+MATCH(F70,INDEX(VimFrac,0,9*F73+VLOOKUP(F72,PlanetData,3,0)+1),IF(F73,-1,1))-1,9) -> #N/A | H71: =MOD(VLOOKUP(G72,PlanetData,3,0)+MATCH(G70,INDEX(VimFrac,0,9*G73+VLOOKUP(G72,PlanetData,3,0)+1),IF(G73,-1,1))-1,9) -> #N/A | K71: =K63 -> 0
A72: Dasa @ Given time | B72: =$B$4 -> Moon | C72: =INDEX(DasaYears,IF(C71=0,9,C71),1) -> #N/A | D72: =INDEX(DasaYears,IF(D71=0,9,D71),1) -> #N/A | E72: =INDEX(DasaYears,IF(E71=0,9,E71),1) -> #N/A | F72: =INDEX(DasaYears,IF(F71=0,9,F71),1) -> #N/A | G72: =INDEX(DasaYears,IF(G71=0,9,G71),1) -> #N/A | H72: =INDEX(DasaYears,IF(H71=0,9,H71),1) -> #N/A | I72: =INDIRECT("'JHora'!$B$"&($K72)) -> 0 | J72: =INDIRECT("'JHora'!$C$"&($K72)) -> 0 | K72: =K64+1 -> 8 | N72: =JHora!B73 -> 0 | O72: =JHora!C73 -> 0
A73: Calculate Retrograde? | B73: =$B$7 -> TRUE | C73: =IF(VLOOKUP(C72,ChartInfo,11,0),1,0)*B73 -> #N/A | D73: =IF(VLOOKUP(D72,ChartInfo,11,0),1,0)*B73 -> #N/A | E73: =IF(VLOOKUP(E72,ChartInfo,11,0),1,0)*B73 -> #N/A | F73: =IF(VLOOKUP(F72,ChartInfo,11,0),1,0)*B73 -> #N/A | G73: =IF(VLOOKUP(G72,ChartInfo,11,0),1,0)*B73 -> #N/A | H73: =IF(VLOOKUP(H72,ChartInfo,11,0),1,0)*B73 -> #N/A | K73: =K65 -> 0
K74: =K66+1 -> 8 | N74: =JHora!B75 -> 0 | O74: =JHora!C75 -> 0
A75: Start Date | B75: =DoB-$E$6*DaysInYear -> 22567.781 | C75: =B75+B77*INDEX(INDEX(VimFrac,,VLOOKUP(B80,PlanetData,3,0)+1),MATCH(B78,INDEX(VimFrac,,VLOOKUP(B80,PlanetData,3,0)+1),1)) -> #N/A | D75: =C75+C77*INDEX(INDEX(VimFrac,0,9*C81+VLOOKUP(C80,PlanetData,3,0)+1),IF(C81,1,0)+MATCH(C78,INDEX(VimFrac,0,9*C81+VLOOKUP(C80,PlanetData,3,0)+1),IF(C81,-1,1))) -> #N/A | E75: =D75+D77*INDEX(INDEX(VimFrac,0,9*D81+VLOOKUP(D80,PlanetData,3,0)+1),IF(D81,1,0)+MATCH(D78,INDEX(VimFrac,0,9*D81+VLOOKUP(D80,PlanetData,3,0)+1),IF(D81,-1,1))) -> #N/A | F75: =E75+E77*INDEX(INDEX(VimFrac,0,9*E81+VLOOKUP(E80,PlanetData,3,0)+1),IF(E81,1,0)+MATCH(E78,INDEX(VimFrac,0,9*E81+VLOOKUP(E80,PlanetData,3,0)+1),IF(E81,-1,1))) -> #N/A | G75: =F75+F77*INDEX(INDEX(VimFrac,0,9*F81+VLOOKUP(F80,PlanetData,3,0)+1),IF(F81,1,0)+MATCH(F78,INDEX(VimFrac,0,9*F81+VLOOKUP(F80,PlanetData,3,0)+1),IF(F81,-1,1))) -> #N/A | H75: =G75+G77*INDEX(INDEX(VimFrac,0,9*G81+VLOOKUP(G80,PlanetData,3,0)+1),IF(G81,1,0)+MATCH(G78,INDEX(VimFrac,0,9*G81+VLOOKUP(G80,PlanetData,3,0)+1),IF(G81,-1,1))) -> #N/A | J75: =J80 -> 0 | K75: =K67+1 -> 9 | N75: =JHora!B76 -> 0 | O75: =JHora!C76 -> 0
A76: End Date | B76: =B75+B77 -> 66398.366 | C76: =B75+B77*INDEX(INDEX(VimFrac,,VLOOKUP(B80,PlanetData,3,0)+1),MATCH(B78,INDEX(VimFrac,,VLOOKUP(B80,PlanetData,3,0)+1),1)+1) -> #N/A | D76: =C75+C77*INDEX(INDEX(VimFrac,0,9*C81+VLOOKUP(C80,PlanetData,3,0)+1),IF(C81,0,1)+MATCH(C78,INDEX(VimFrac,0,9*C81+VLOOKUP(C80,PlanetData,3,0)+1),IF(C81,-1,1))) -> #N/A | E76: =D75+D77*INDEX(INDEX(VimFrac,0,9*D81+VLOOKUP(D80,PlanetData,3,0)+1),IF(D81,0,1)+MATCH(D78,INDEX(VimFrac,0,9*D81+VLOOKUP(D80,PlanetData,3,0)+1),IF(D81,-1,1))) -> #N/A | F76: =E75+E77*INDEX(INDEX(VimFrac,0,9*E81+VLOOKUP(E80,PlanetData,3,0)+1),IF(E81,0,1)+MATCH(E78,INDEX(VimFrac,0,9*E81+VLOOKUP(E80,PlanetData,3,0)+1),IF(E81,-1,1))) -> #N/A | G76: =F75+F77*INDEX(INDEX(VimFrac,0,9*F81+VLOOKUP(F80,PlanetData,3,0)+1),IF(F81,0,1)+MATCH(F78,INDEX(VimFrac,0,9*F81+VLOOKUP(F80,PlanetData,3,0)+1),IF(F81,-1,1))) -> #N/A | H76: =G75+G77*INDEX(INDEX(VimFrac,0,9*G81+VLOOKUP(G80,PlanetData,3,0)+1),IF(G81,0,1)+MATCH(G78,INDEX(VimFrac,0,9*G81+VLOOKUP(G80,PlanetData,3,0)+1),IF(G81,-1,1))) -> #N/A | J76: =J80 -> 0 | K76: =K68+1 -> 9 | N76: =JHora!B77 -> 0 | O76: =JHora!C77 -> 0
A77: Cycle Duration Days | B77: =120*DaysInYear -> 43830.585 | C77: =C76-C75 -> #N/A | D77: =D76-D75 -> #N/A | E77: =E76-E75 -> #N/A | F77: =F76-F75 -> #N/A | G77: =G76-G75 -> #N/A | H77: =H76-H75 -> #N/A | K77: =K69 -> 0
A78: %Frac Past in Cyc | B78: =(I80-B75)/(B76-B75) -> -0.51488661 | C78: =(I80-C75)/(C76-C75) -> #N/A | D78: =(I80-D75)/(D76-D75) -> #N/A | E78: =(I80-E75)/(E76-E75) -> #N/A | F78: =(I80-F75)/(F76-F75) -> #N/A | G78: =(I80-G75)/(G76-G75) -> #N/A | H78: =(I80-H75)/(H76-H75) -> #N/A | K78: =K70 -> 0
A79: Dasa# @ Given time | C79: =MOD(VLOOKUP(B80,PlanetData,3,0)+MATCH(B78,INDEX(VimFrac,,VLOOKUP(B80,PlanetData,3,0)+1),1)-1,9) -> #N/A | D79: =MOD(VLOOKUP(C80,PlanetData,3,0)+MATCH(C78,INDEX(VimFrac,0,9*C81+VLOOKUP(C80,PlanetData,3,0)+1),IF(C81,-1,1))-1,9) -> #N/A | E79: =MOD(VLOOKUP(D80,PlanetData,3,0)+MATCH(D78,INDEX(VimFrac,0,9*D81+VLOOKUP(D80,PlanetData,3,0)+1),IF(D81,-1,1))-1,9) -> #N/A | F79: =MOD(VLOOKUP(E80,PlanetData,3,0)+MATCH(E78,INDEX(VimFrac,0,9*E81+VLOOKUP(E80,PlanetData,3,0)+1),IF(E81,-1,1))-1,9) -> #N/A | G79: =MOD(VLOOKUP(F80,PlanetData,3,0)+MATCH(F78,INDEX(VimFrac,0,9*F81+VLOOKUP(F80,PlanetData,3,0)+1),IF(F81,-1,1))-1,9) -> #N/A | H79: =MOD(VLOOKUP(G80,PlanetData,3,0)+MATCH(G78,INDEX(VimFrac,0,9*G81+VLOOKUP(G80,PlanetData,3,0)+1),IF(G81,-1,1))-1,9) -> #N/A | K79: =K71 -> 0
A80: Dasa @ Given time | B80: =$B$4 -> Moon | C80: =INDEX(DasaYears,IF(C79=0,9,C79),1) -> #N/A | D80: =INDEX(DasaYears,IF(D79=0,9,D79),1) -> #N/A | E80: =INDEX(DasaYears,IF(E79=0,9,E79),1) -> #N/A | F80: =INDEX(DasaYears,IF(F79=0,9,F79),1) -> #N/A | G80: =INDEX(DasaYears,IF(G79=0,9,G79),1) -> #N/A | H80: =INDEX(DasaYears,IF(H79=0,9,H79),1) -> #N/A | I80: =INDIRECT("'JHora'!$B$"&($K80)) -> 0 | J80: =INDIRECT("'JHora'!$C$"&($K80)) -> 0 | K80: =K72+1 -> 9 | N80: =JHora!B81 -> 0 | O80: =JHora!C81 -> 0
A81: Calculate Retrograde? | B81: =$B$7 -> TRUE | C81: =IF(VLOOKUP(C80,ChartInfo,11,0),1,0)*B81 -> #N/A | D81: =IF(VLOOKUP(D80,ChartInfo,11,0),1,0)*B81 -> #N/A | E81: =IF(VLOOKUP(E80,ChartInfo,11,0),1,0)*B81 -> #N/A | F81: =IF(VLOOKUP(F80,ChartInfo,11,0),1,0)*B81 -> #N/A | G81: =IF(VLOOKUP(G80,ChartInfo,11,0),1,0)*B81 -> #N/A | H81: =IF(VLOOKUP(H80,ChartInfo,11,0),1,0)*B81 -> #N/A | K81: =K73 -> 0
K82: =K74+1 -> 9 | N82: =JHora!B83 -> 0 | O82: =JHora!C83 -> 0
A83: Start Date | B83: =DoB-$E$6*DaysInYear -> 22567.781 | C83: =B83+B85*INDEX(INDEX(VimFrac,,VLOOKUP(B88,PlanetData,3,0)+1),MATCH(B86,INDEX(VimFrac,,VLOOKUP(B88,PlanetData,3,0)+1),1)) -> #N/A | D83: =C83+C85*INDEX(INDEX(VimFrac,0,9*C89+VLOOKUP(C88,PlanetData,3,0)+1),IF(C89,1,0)+MATCH(C86,INDEX(VimFrac,0,9*C89+VLOOKUP(C88,PlanetData,3,0)+1),IF(C89,-1,1))) -> #N/A | E83: =D83+D85*INDEX(INDEX(VimFrac,0,9*D89+VLOOKUP(D88,PlanetData,3,0)+1),IF(D89,1,0)+MATCH(D86,INDEX(VimFrac,0,9*D89+VLOOKUP(D88,PlanetData,3,0)+1),IF(D89,-1,1))) -> #N/A | F83: =E83+E85*INDEX(INDEX(VimFrac,0,9*E89+VLOOKUP(E88,PlanetData,3,0)+1),IF(E89,1,0)+MATCH(E86,INDEX(VimFrac,0,9*E89+VLOOKUP(E88,PlanetData,3,0)+1),IF(E89,-1,1))) -> #N/A | G83: =F83+F85*INDEX(INDEX(VimFrac,0,9*F89+VLOOKUP(F88,PlanetData,3,0)+1),IF(F89,1,0)+MATCH(F86,INDEX(VimFrac,0,9*F89+VLOOKUP(F88,PlanetData,3,0)+1),IF(F89,-1,1))) -> #N/A | H83: =G83+G85*INDEX(INDEX(VimFrac,0,9*G89+VLOOKUP(G88,PlanetData,3,0)+1),IF(G89,1,0)+MATCH(G86,INDEX(VimFrac,0,9*G89+VLOOKUP(G88,PlanetData,3,0)+1),IF(G89,-1,1))) -> #N/A | J83: =J88 -> 0 | K83: =K75+1 -> 10 | N83: =JHora!B84 -> 0 | O83: =JHora!C84 -> 0
A84: End Date | B84: =B83+B85 -> 66398.366 | C84: =B83+B85*INDEX(INDEX(VimFrac,,VLOOKUP(B88,PlanetData,3,0)+1),MATCH(B86,INDEX(VimFrac,,VLOOKUP(B88,PlanetData,3,0)+1),1)+1) -> #N/A | D84: =C83+C85*INDEX(INDEX(VimFrac,0,9*C89+VLOOKUP(C88,PlanetData,3,0)+1),IF(C89,0,1)+MATCH(C86,INDEX(VimFrac,0,9*C89+VLOOKUP(C88,PlanetData,3,0)+1),IF(C89,-1,1))) -> #N/A | E84: =D83+D85*INDEX(INDEX(VimFrac,0,9*D89+VLOOKUP(D88,PlanetData,3,0)+1),IF(D89,0,1)+MATCH(D86,INDEX(VimFrac,0,9*D89+VLOOKUP(D88,PlanetData,3,0)+1),IF(D89,-1,1))) -> #N/A | F84: =E83+E85*INDEX(INDEX(VimFrac,0,9*E89+VLOOKUP(E88,PlanetData,3,0)+1),IF(E89,0,1)+MATCH(E86,INDEX(VimFrac,0,9*E89+VLOOKUP(E88,PlanetData,3,0)+1),IF(E89,-1,1))) -> #N/A | G84: =F83+F85*INDEX(INDEX(VimFrac,0,9*F89+VLOOKUP(F88,PlanetData,3,0)+1),IF(F89,0,1)+MATCH(F86,INDEX(VimFrac,0,9*F89+VLOOKUP(F88,PlanetData,3,0)+1),IF(F89,-1,1))) -> #N/A | H84: =G83+G85*INDEX(INDEX(VimFrac,0,9*G89+VLOOKUP(G88,PlanetData,3,0)+1),IF(G89,0,1)+MATCH(G86,INDEX(VimFrac,0,9*G89+VLOOKUP(G88,PlanetData,3,0)+1),IF(G89,-1,1))) -> #N/A | J84: =J88 -> 0 | K84: =K76+1 -> 10 | N84: =JHora!B85 -> 0 | O84: =JHora!C85 -> 0
A85: Cycle Duration Days | B85: =120*DaysInYear -> 43830.585 | C85: =C84-C83 -> #N/A | D85: =D84-D83 -> #N/A | E85: =E84-E83 -> #N/A | F85: =F84-F83 -> #N/A | G85: =G84-G83 -> #N/A | H85: =H84-H83 -> #N/A | K85: =K77 -> 0
A86: %Frac Past in Cyc | B86: =(I88-B83)/(B84-B83) -> -0.51488661 | C86: =(I88-C83)/(C84-C83) -> #N/A | D86: =(I88-D83)/(D84-D83) -> #N/A | E86: =(I88-E83)/(E84-E83) -> #N/A | F86: =(I88-F83)/(F84-F83) -> #N/A | G86: =(I88-G83)/(G84-G83) -> #N/A | H86: =(I88-H83)/(H84-H83) -> #N/A | K86: =K78 -> 0
A87: Dasa# @ Given time | C87: =MOD(VLOOKUP(B88,PlanetData,3,0)+MATCH(B86,INDEX(VimFrac,,VLOOKUP(B88,PlanetData,3,0)+1),1)-1,9) -> #N/A | D87: =MOD(VLOOKUP(C88,PlanetData,3,0)+MATCH(C86,INDEX(VimFrac,0,9*C89+VLOOKUP(C88,PlanetData,3,0)+1),IF(C89,-1,1))-1,9) -> #N/A | E87: =MOD(VLOOKUP(D88,PlanetData,3,0)+MATCH(D86,INDEX(VimFrac,0,9*D89+VLOOKUP(D88,PlanetData,3,0)+1),IF(D89,-1,1))-1,9) -> #N/A | F87: =MOD(VLOOKUP(E88,PlanetData,3,0)+MATCH(E86,INDEX(VimFrac,0,9*E89+VLOOKUP(E88,PlanetData,3,0)+1),IF(E89,-1,1))-1,9) -> #N/A | G87: =MOD(VLOOKUP(F88,PlanetData,3,0)+MATCH(F86,INDEX(VimFrac,0,9*F89+VLOOKUP(F88,PlanetData,3,0)+1),IF(F89,-1,1))-1,9) -> #N/A | H87: =MOD(VLOOKUP(G88,PlanetData,3,0)+MATCH(G86,INDEX(VimFrac,0,9*G89+VLOOKUP(G88,PlanetData,3,0)+1),IF(G89,-1,1))-1,9) -> #N/A | K87: =K79 -> 0
A88: Dasa @ Given time | B88: =$B$4 -> Moon | C88: =INDEX(DasaYears,IF(C87=0,9,C87),1) -> #N/A | D88: =INDEX(DasaYears,IF(D87=0,9,D87),1) -> #N/A | E88: =INDEX(DasaYears,IF(E87=0,9,E87),1) -> #N/A | F88: =INDEX(DasaYears,IF(F87=0,9,F87),1) -> #N/A | G88: =INDEX(DasaYears,IF(G87=0,9,G87),1) -> #N/A | H88: =INDEX(DasaYears,IF(H87=0,9,H87),1) -> #N/A | I88: =INDIRECT("'JHora'!$B$"&($K88)) -> 0 | J88: =INDIRECT("'JHora'!$C$"&($K88)) -> 0 | K88: =K80+1 -> 10 | N88: =JHora!B89 -> 0 | O88: =JHora!C89 -> 0
A89: Calculate Retrograde? | B89: =$B$7 -> TRUE | C89: =IF(VLOOKUP(C88,ChartInfo,11,0),1,0)*B89 -> #N/A | D89: =IF(VLOOKUP(D88,ChartInfo,11,0),1,0)*B89 -> #N/A | E89: =IF(VLOOKUP(E88,ChartInfo,11,0),1,0)*B89 -> #N/A | F89: =IF(VLOOKUP(F88,ChartInfo,11,0),1,0)*B89 -> #N/A | G89: =IF(VLOOKUP(G88,ChartInfo,11,0),1,0)*B89 -> #N/A | H89: =IF(VLOOKUP(H88,ChartInfo,11,0),1,0)*B89 -> #N/A | K89: =K81 -> 0
K90: =K82+1 -> 10 | N90: =JHora!B91 -> 0 | O90: =JHora!C91 -> 0
A91: Start Date | B91: =DoB-$E$6*DaysInYear -> 22567.781 | C91: =B91+B93*INDEX(INDEX(VimFrac,,VLOOKUP(B96,PlanetData,3,0)+1),MATCH(B94,INDEX(VimFrac,,VLOOKUP(B96,PlanetData,3,0)+1),1)) -> #N/A | D91: =C91+C93*INDEX(INDEX(VimFrac,0,9*C97+VLOOKUP(C96,PlanetData,3,0)+1),IF(C97,1,0)+MATCH(C94,INDEX(VimFrac,0,9*C97+VLOOKUP(C96,PlanetData,3,0)+1),IF(C97,-1,1))) -> #N/A | E91: =D91+D93*INDEX(INDEX(VimFrac,0,9*D97+VLOOKUP(D96,PlanetData,3,0)+1),IF(D97,1,0)+MATCH(D94,INDEX(VimFrac,0,9*D97+VLOOKUP(D96,PlanetData,3,0)+1),IF(D97,-1,1))) -> #N/A | F91: =E91+E93*INDEX(INDEX(VimFrac,0,9*E97+VLOOKUP(E96,PlanetData,3,0)+1),IF(E97,1,0)+MATCH(E94,INDEX(VimFrac,0,9*E97+VLOOKUP(E96,PlanetData,3,0)+1),IF(E97,-1,1))) -> #N/A | G91: =F91+F93*INDEX(INDEX(VimFrac,0,9*F97+VLOOKUP(F96,PlanetData,3,0)+1),IF(F97,1,0)+MATCH(F94,INDEX(VimFrac,0,9*F97+VLOOKUP(F96,PlanetData,3,0)+1),IF(F97,-1,1))) -> #N/A | H91: =G91+G93*INDEX(INDEX(VimFrac,0,9*G97+VLOOKUP(G96,PlanetData,3,0)+1),IF(G97,1,0)+MATCH(G94,INDEX(VimFrac,0,9*G97+VLOOKUP(G96,PlanetData,3,0)+1),IF(G97,-1,1))) -> #N/A | J91: =J96 -> 0 | K91: =K83+1 -> 11 | N91: =JHora!B92 -> 0 | O91: =JHora!C92 -> 0
A92: End Date | B92: =B91+B93 -> 66398.366 | C92: =B91+B93*INDEX(INDEX(VimFrac,,VLOOKUP(B96,PlanetData,3,0)+1),MATCH(B94,INDEX(VimFrac,,VLOOKUP(B96,PlanetData,3,0)+1),1)+1) -> #N/A | D92: =C91+C93*INDEX(INDEX(VimFrac,0,9*C97+VLOOKUP(C96,PlanetData,3,0)+1),IF(C97,0,1)+MATCH(C94,INDEX(VimFrac,0,9*C97+VLOOKUP(C96,PlanetData,3,0)+1),IF(C97,-1,1))) -> #N/A | E92: =D91+D93*INDEX(INDEX(VimFrac,0,9*D97+VLOOKUP(D96,PlanetData,3,0)+1),IF(D97,0,1)+MATCH(D94,INDEX(VimFrac,0,9*D97+VLOOKUP(D96,PlanetData,3,0)+1),IF(D97,-1,1))) -> #N/A | F92: =E91+E93*INDEX(INDEX(VimFrac,0,9*E97+VLOOKUP(E96,PlanetData,3,0)+1),IF(E97,0,1)+MATCH(E94,INDEX(VimFrac,0,9*E97+VLOOKUP(E96,PlanetData,3,0)+1),IF(E97,-1,1))) -> #N/A | G92: =F91+F93*INDEX(INDEX(VimFrac,0,9*F97+VLOOKUP(F96,PlanetData,3,0)+1),IF(F97,0,1)+MATCH(F94,INDEX(VimFrac,0,9*F97+VLOOKUP(F96,PlanetData,3,0)+1),IF(F97,-1,1))) -> #N/A | H92: =G91+G93*INDEX(INDEX(VimFrac,0,9*G97+VLOOKUP(G96,PlanetData,3,0)+1),IF(G97,0,1)+MATCH(G94,INDEX(VimFrac,0,9*G97+VLOOKUP(G96,PlanetData,3,0)+1),IF(G97,-1,1))) -> #N/A | J92: =J96 -> 0 | K92: =K84+1 -> 11 | N92: =JHora!B93 -> 0 | O92: =JHora!C93 -> 0
A93: Cycle Duration Days | B93: =120*DaysInYear -> 43830.585 | C93: =C92-C91 -> #N/A | D93: =D92-D91 -> #N/A | E93: =E92-E91 -> #N/A | F93: =F92-F91 -> #N/A | G93: =G92-G91 -> #N/A | H93: =H92-H91 -> #N/A | K93: =K85 -> 0
A94: %Frac Past in Cyc | B94: =(I96-B91)/(B92-B91) -> -0.51488661 | C94: =(I96-C91)/(C92-C91) -> #N/A | D94: =(I96-D91)/(D92-D91) -> #N/A | E94: =(I96-E91)/(E92-E91) -> #N/A | F94: =(I96-F91)/(F92-F91) -> #N/A | G94: =(I96-G91)/(G92-G91) -> #N/A | H94: =(I96-H91)/(H92-H91) -> #N/A | K94: =K86 -> 0
A95: Dasa# @ Given time | C95: =MOD(VLOOKUP(B96,PlanetData,3,0)+MATCH(B94,INDEX(VimFrac,,VLOOKUP(B96,PlanetData,3,0)+1),1)-1,9) -> #N/A | D95: =MOD(VLOOKUP(C96,PlanetData,3,0)+MATCH(C94,INDEX(VimFrac,0,9*C97+VLOOKUP(C96,PlanetData,3,0)+1),IF(C97,-1,1))-1,9) -> #N/A | E95: =MOD(VLOOKUP(D96,PlanetData,3,0)+MATCH(D94,INDEX(VimFrac,0,9*D97+VLOOKUP(D96,PlanetData,3,0)+1),IF(D97,-1,1))-1,9) -> #N/A | F95: =MOD(VLOOKUP(E96,PlanetData,3,0)+MATCH(E94,INDEX(VimFrac,0,9*E97+VLOOKUP(E96,PlanetData,3,0)+1),IF(E97,-1,1))-1,9) -> #N/A | G95: =MOD(VLOOKUP(F96,PlanetData,3,0)+MATCH(F94,INDEX(VimFrac,0,9*F97+VLOOKUP(F96,PlanetData,3,0)+1),IF(F97,-1,1))-1,9) -> #N/A | H95: =MOD(VLOOKUP(G96,PlanetData,3,0)+MATCH(G94,INDEX(VimFrac,0,9*G97+VLOOKUP(G96,PlanetData,3,0)+1),IF(G97,-1,1))-1,9) -> #N/A | K95: =K87 -> 0
A96: Dasa @ Given time | B96: =$B$4 -> Moon | C96: =INDEX(DasaYears,IF(C95=0,9,C95),1) -> #N/A | D96: =INDEX(DasaYears,IF(D95=0,9,D95),1) -> #N/A | E96: =INDEX(DasaYears,IF(E95=0,9,E95),1) -> #N/A | F96: =INDEX(DasaYears,IF(F95=0,9,F95),1) -> #N/A | G96: =INDEX(DasaYears,IF(G95=0,9,G95),1) -> #N/A | H96: =INDEX(DasaYears,IF(H95=0,9,H95),1) -> #N/A | I96: =INDIRECT("'JHora'!$B$"&($K96)) -> 0 | J96: =INDIRECT("'JHora'!$C$"&($K96)) -> 0 | K96: =K88+1 -> 11 | N96: =JHora!B97 -> 0 | O96: =JHora!C97 -> 0
A97: Calculate Retrograde? | B97: =$B$7 -> TRUE | C97: =IF(VLOOKUP(C96,ChartInfo,11,0),1,0)*B97 -> #N/A | D97: =IF(VLOOKUP(D96,ChartInfo,11,0),1,0)*B97 -> #N/A | E97: =IF(VLOOKUP(E96,ChartInfo,11,0),1,0)*B97 -> #N/A | F97: =IF(VLOOKUP(F96,ChartInfo,11,0),1,0)*B97 -> #N/A | G97: =IF(VLOOKUP(G96,ChartInfo,11,0),1,0)*B97 -> #N/A | H97: =IF(VLOOKUP(H96,ChartInfo,11,0),1,0)*B97 -> #N/A | K97: =K89 -> 0
K98: =K90+1 -> 11 | N98: =JHora!B99 -> 0 | O98: =JHora!C99 -> 0
A99: Start Date | B99: =DoB-$E$6*DaysInYear -> 22567.781 | C99: =B99+B101*INDEX(INDEX(VimFrac,,VLOOKUP(B104,PlanetData,3,0)+1),MATCH(B102,INDEX(VimFrac,,VLOOKUP(B104,PlanetData,3,0)+1),1)) -> #N/A | D99: =C99+C101*INDEX(INDEX(VimFrac,0,9*C105+VLOOKUP(C104,PlanetData,3,0)+1),IF(C105,1,0)+MATCH(C102,INDEX(VimFrac,0,9*C105+VLOOKUP(C104,PlanetData,3,0)+1),IF(C105,-1,1))) -> #N/A | E99: =D99+D101*INDEX(INDEX(VimFrac,0,9*D105+VLOOKUP(D104,PlanetData,3,0)+1),IF(D105,1,0)+MATCH(D102,INDEX(VimFrac,0,9*D105+VLOOKUP(D104,PlanetData,3,0)+1),IF(D105,-1,1))) -> #N/A | F99: =E99+E101*INDEX(INDEX(VimFrac,0,9*E105+VLOOKUP(E104,PlanetData,3,0)+1),IF(E105,1,0)+MATCH(E102,INDEX(VimFrac,0,9*E105+VLOOKUP(E104,PlanetData,3,0)+1),IF(E105,-1,1))) -> #N/A | G99: =F99+F101*INDEX(INDEX(VimFrac,0,9*F105+VLOOKUP(F104,PlanetData,3,0)+1),IF(F105,1,0)+MATCH(F102,INDEX(VimFrac,0,9*F105+VLOOKUP(F104,PlanetData,3,0)+1),IF(F105,-1,1))) -> #N/A | H99: =G99+G101*INDEX(INDEX(VimFrac,0,9*G105+VLOOKUP(G104,PlanetData,3,0)+1),IF(G105,1,0)+MATCH(G102,INDEX(VimFrac,0,9*G105+VLOOKUP(G104,PlanetData,3,0)+1),IF(G105,-1,1))) -> #N/A | J99: =J104 -> 0 | K99: =K91+1 -> 12 | N99: =JHora!B100 -> 0 | O99: =JHora!C100 -> 0
A100: End Date | B100: =B99+B101 -> 66398.366 | C100: =B99+B101*INDEX(INDEX(VimFrac,,VLOOKUP(B104,PlanetData,3,0)+1),MATCH(B102,INDEX(VimFrac,,VLOOKUP(B104,PlanetData,3,0)+1),1)+1) -> #N/A | D100: =C99+C101*INDEX(INDEX(VimFrac,0,9*C105+VLOOKUP(C104,PlanetData,3,0)+1),IF(C105,0,1)+MATCH(C102,INDEX(VimFrac,0,9*C105+VLOOKUP(C104,PlanetData,3,0)+1),IF(C105,-1,1))) -> #N/A | E100: =D99+D101*INDEX(INDEX(VimFrac,0,9*D105+VLOOKUP(D104,PlanetData,3,0)+1),IF(D105,0,1)+MATCH(D102,INDEX(VimFrac,0,9*D105+VLOOKUP(D104,PlanetData,3,0)+1),IF(D105,-1,1))) -> #N/A | F100: =E99+E101*INDEX(INDEX(VimFrac,0,9*E105+VLOOKUP(E104,PlanetData,3,0)+1),IF(E105,0,1)+MATCH(E102,INDEX(VimFrac,0,9*E105+VLOOKUP(E104,PlanetData,3,0)+1),IF(E105,-1,1))) -> #N/A | G100: =F99+F101*INDEX(INDEX(VimFrac,0,9*F105+VLOOKUP(F104,PlanetData,3,0)+1),IF(F105,0,1)+MATCH(F102,INDEX(VimFrac,0,9*F105+VLOOKUP(F104,PlanetData,3,0)+1),IF(F105,-1,1))) -> #N/A | H100: =G99+G101*INDEX(INDEX(VimFrac,0,9*G105+VLOOKUP(G104,PlanetData,3,0)+1),IF(G105,0,1)+MATCH(G102,INDEX(VimFrac,0,9*G105+VLOOKUP(G104,PlanetData,3,0)+1),IF(G105,-1,1))) -> #N/A | J100: =J104 -> 0 | K100: =K92+1 -> 12 | N100: =JHora!B101 -> 0 | O100: =JHora!C101 -> 0
...

Sheet Yuti Yoga
A1: Yoga# | B1: Sat | C1: Ve | D1: Ju | E1: Me | F1: Ma | G1: Mo | H1: Su | I1: Grahas | J1: Yoga Name/Results | K1: References | L1: Conjoined Grahas | M1: Sat2 | N1: Column2 | O1: Column3 | P1: Column4 | Q1: Column5 | R1: Column6 | S1: Column7
A2: 1 | B2: =MOD(INT($A2/64),2) -> 0 | C2: =MOD(INT($A2/32),2) -> 0 | D2: =MOD(INT($A2/16),2) -> 0 | E2: =MOD(INT($A2/8),2) -> 0 | F2: =MOD(INT($A2/4),2) -> 0 | G2: =MOD(INT($A2/2),2) -> 0 | H2: =MOD(A2,2) -> 1 | I2: =SUM(Table122[[#This Row],[Sat]:[Su]]) -> 1 | L2: =Table122[[#This Row],[Sat2]]&" "&Table122[[#This Row],[Column2]]&" "&Table122[[#This Row],[Column3]]&" "&Table122[[#This Row],[Column4]]&" "&Table122[[#This Row],[Column5]]&" "&Table122[[#This Row],[Column6]]&" "&Table122[[#This Row],[Column7]] -> Su | M2: =IF(Table122[[#This Row],[Sat]],Table122[[#Headers],[Sat]],"") | N2: =IF(Table122[[#This Row],[Ve]],Table122[[#Headers],[Ve]],"") | O2: =IF(Table122[[#This Row],[Ju]],Table122[[#Headers],[Ju]],"") | P2: =IF(Table122[[#This Row],[Me]],Table122[[#Headers],[Me]],"") | Q2: =IF(Table122[[#This Row],[Ma]],Table122[[#Headers],[Ma]],"") | R2: =IF(Table122[[#This Row],[Mo]],Table122[[#Headers],[Mo]],"") | S2: =IF(Table122[[#This Row],[Su]],Table122[[#Headers],[Su]],"") -> Su
A3: 2 | B3: =MOD(INT($A3/64),2) -> 0 | C3: =MOD(INT($A3/32),2) -> 0 | D3: =MOD(INT($A3/16),2) -> 0 | E3: =MOD(INT($A3/8),2) -> 0 | F3: =MOD(INT($A3/4),2) -> 0 | G3: =MOD(INT($A3/2),2) -> 1 | H3: =MOD(A3,2) -> 0 | I3: =SUM(Table122[[#This Row],[Sat]:[Su]]) -> 1 | L3: =Table122[[#This Row],[Sat2]]&" "&Table122[[#This Row],[Column2]]&" "&Table122[[#This Row],[Column3]]&" "&Table122[[#This Row],[Column4]]&" "&Table122[[#This Row],[Column5]]&" "&Table122[[#This Row],[Column6]]&" "&Table122[[#This Row],[Column7]] -> Mo | M3: =IF(Table122[[#This Row],[Sat]],Table122[[#Headers],[Sat]],"") | N3: =IF(Table122[[#This Row],[Ve]],Table122[[#Headers],[Ve]],"") | O3: =IF(Table122[[#This Row],[Ju]],Table122[[#Headers],[Ju]],"") | P3: =IF(Table122[[#This Row],[Me]],Table122[[#Headers],[Me]],"") | Q3: =IF(Table122[[#This Row],[Ma]],Table122[[#Headers],[Ma]],"") | R3: =IF(Table122[[#This Row],[Mo]],Table122[[#Headers],[Mo]],"") -> Mo | S3: =IF(Table122[[#This Row],[Su]],Table122[[#Headers],[Su]],"")
